Workbook
Name ___________GIP100: [1]library!$D$218
Name __________GIP100: [1]library!$D$218
Name _________GIP100: [1]library!$D$218
Name ________GIP100: [1]library!$D$218
Name ________zl152: #REF!
Name ________zl152: #REF!
Name _______GIP100: [1]library!$D$218
Name ______GIP100: [1]library!$D$218
Name _____GIP100: [1]library!$D$218
Name ____GIP100: [1]library!$D$218
Name ____HPC8: #REF!
Name ____HPC8: #REF!
Name ____TAR20: #REF!
Name ____TAR20: #REF!
Name ___GIP100: [1]library!$D$218
Name ___HPC8: #REF!
Name ___HPC8: #REF!
Name ___TAR20: #REF!
Name ___TAR20: #REF!
Name __123Graph_B: '[2]CProy laba rugi'!#REF!
Name __123Graph_B: '[3]CProy laba rugi'!#REF!
Name __123Graph_X: '[4]CProy laba rugi'!#REF!
Name __123Graph_X: '[5]CProy laba rugi'!#REF!
Name __FDS_HYPERLINK_TOGGLE_STATE__: "ON"
Name __GIP100: [1]library!$D$218
Name __HPC8: #REF!
Name __HPC8: #REF!
Name __TAR20: #REF!
Name __TAR20: #REF!
Name _1Excel_BuiltIn_Print_Area_2: #REF!
Name _1Excel_BuiltIn_Print_Area_2: #REF!
Name _2Excel_BuiltIn_Print_Area_2: #REF!
Name _2Excel_BuiltIn_Print_Area_2: #REF!
Name _4Excel_BuiltIn_Print_Area_2: #REF!
Name _4Excel_BuiltIn_Print_Area_2: #REF!
Name _910A: #REF!
Name _910A: #REF!
Name _91A: #REF!
Name _91A: #REF!
Name _92A: #REF!
Name _92A: #REF!
Name _93A: #REF!
Name _93A: #REF!
Name _94A: #REF!
Name _94A: #REF!
Name _95A: #REF!
Name _95A: #REF!
Name _96A: #REF!
Name _96A: #REF!
Name _97AA: #REF!
Name _97AA: #REF!
Name _98A: #REF!
Name _98A: #REF!
Name _99A: #REF!
Name _99A: #REF!
Name _99B: #REF!
Name _99B: #REF!
Name _GIP100: [1]library!$D$218
Name _HPC8: #REF!
Name _HPC8: #REF!

Sheet GUIDE SHEET
E2: 1. INPUT DATA FROM TECHNICAL
B3: GET DATA FROM TECHNICAL | E3: 2. GET DATA FROM COMMERCIAL & FINANCE | H3: CALCULATIONS | K3: OUTPUT
B9: DEMAND AND PROJECTIONS | H9: OPEX
B11: CAPEX | E11: INPUT DATA & ASSUMPTIONS | H11: DEPRECIATION SCHEDULE | K11: TARIFF CALCULATION
B13: OPEX | H13: AMORTIZATION SCHEDULE
D18: OPEX
D19: DEPRECIATION
D20: AMORTIZATION | H20: BILLED VOLUME | K20: PHP TARIFF / CU.M.
D21: EQUITY
D22: 2- MOS. WORKING CAPITAL

Sheet BOHOL DEMAND PROJECTION
B2: Demand Projection
C4: POPULATION
C5: City/Municipality | D5: WSPs | G5: 2019 | H5: 2020 | I5: 2021 | J5: 2022 | K5: 2023 | L5: 45352 | M5: 2024 | N5: 2025 | O5: 2026 | P5: 2027 | Q5: 2028 | R5: 2029 | S5: 2030 | T5: 2031 | U5: 2032 | V5: 2033 | W5: 2034 | X5: 2035 | Y5: 2036 | Z5: 2037 | AA5: 2038 | AB5: 2039 | AC5: 2040 | AD5: 2041 | AE5: 2042 | AF5: 2043 | AG5: 2044 | AH5: 2045 | AI5: 2046 | AJ5: 2047 | AK5: 2048 | AL5: 2049 | AM5: 2050 | AN5: 2051 | AO5: 2052 | AP5: 2053 | AQ5: 2054 | AR5: 2055
B8: 1 | C8: Alburquerque | D8: LGU-run, BLGU-run | H8: 11246 | I8: 11438.448 | J8: 11634.189 | K8: 11833.279 | L8: 12035.777 | M8: 12035.777 | N8: 12241.74 | O8: 12437.214 | P8: 12635.809 | Q8: 12837.575 | R8: 13042.563 | S8: 13250.825 | T8: 13446.202 | U8: 13644.459 | V8: 13845.64 | W8: 14049.787 | X8: 14256.944 | Y8: 14446.956 | Z8: 14639.5 | AA8: 14834.61 | AB8: 15032.32 | AC8: 15232.665 | AD8: 15418.9 | AE8: 15607.411 | AF8: 15798.226 | AG8: 15991.375 | AH8: 16186.885 | AI8: 16384.785 | AJ8: 16585.105 | AK8: 16787.874 | AL8: 16993.122 | AM8: 17200.88 | AN8: 17411.177 | AO8: 17624.046 | AP8: 17839.517 | AQ8: 18057.622 | AR8: 18278.394
B9: 2 | C9: Baclayon | D9: LGU-run, BWUI, BLGU-run | H9: 22461 | I9: 22845.365 | J9: 23236.307 | K9: 23633.94 | L9: 24038.377 | M9: 24038.377 | N9: 24449.734 | O9: 24840.144 | P9: 25236.787 | Q9: 25639.763 | R9: 26049.175 | S9: 26465.123 | T9: 26855.339 | U9: 27251.307 | V9: 27653.114 | W9: 28060.846 | X9: 28474.589 | Y9: 28854.088 | Z9: 29238.645 | AA9: 29628.327 | AB9: 30023.203 | AC9: 30423.342 | AD9: 30795.296 | AE9: 31171.799 | AF9: 31552.904 | AG9: 31938.669 | AH9: 32329.15 | AI9: 32724.406 | AJ9: 33124.493 | AK9: 33529.472 | AL9: 33939.402 | AM9: 34354.345 | AN9: 34774.36 | AO9: 35199.51 | AP9: 35629.858 | AQ9: 36065.468 | AR9: 36506.403
B10: 3 | C10: Corella | D10: LGU-run | H10: 9479 | I10: 9641.2098 | J10: 9806.1955 | K10: 9974.0045 | L10: 10144.685 | M10: 10144.685 | N10: 10318.286 | O10: 10483.047 | P10: 10650.439 | Q10: 10820.503 | R10: 10993.283 | S10: 11168.822 | T10: 11333.5 | U10: 11500.607 | V10: 11670.178 | W10: 11842.249 | X10: 12016.857 | Y10: 12177.014 | Z10: 12339.304 | AA10: 12503.758 | AB10: 12670.404 | AC10: 12839.271 | AD10: 12996.243 | AE10: 13155.135 | AF10: 13315.969 | AG10: 13478.77 | AH10: 13643.561 | AI10: 13810.366 | AJ10: 13979.212 | AK10: 14150.121 | AL10: 14323.12 | AM10: 14498.234 | AN10: 14675.489 | AO10: 14854.911 | AP10: 15036.527 | AQ10: 15220.363 | AR10: 15406.446
B11: 4 | C11: Dauis | D11: LGU-run, BLGU-run, Richli, Balibago, BWUI (bulk) | H11: 52492 | I11: 53390.272 | J11: 54303.915 | K11: 55233.194 | L11: 56178.374 | M11: 56178.374 | N11: 57139.729 | O11: 58052.127 | P11: 58979.093 | Q11: 59920.861 | R11: 60877.667 | S11: 61849.751 | T11: 62761.695 | U11: 63687.085 | V11: 64626.12 | W11: 65579 | X11: 66545.93 | Y11: 67432.83 | Z11: 68331.551 | AA11: 69242.249 | AB11: 70165.085 | AC11: 71100.22 | AD11: 71969.489 | AE11: 72849.386 | AF11: 73740.041 | AG11: 74641.584 | AH11: 75554.15 | AI11: 76477.873 | AJ11: 77412.889 | AK11: 78359.336 | AL11: 79317.355 | AM11: 80287.087 | AN11: 81268.674 | AO11: 82262.263 | AP11: 83267.999 | AQ11: 84286.031 | AR11: 85316.509
B12: 5 | C12: Loboc | D12: LGU-run, BLGU-run | H12: 17418 | I12: 17716.066 | J12: 18019.233 | K12: 18327.588 | L12: 18641.22 | M12: 18641.22 | N12: 18960.219 | O12: 19262.972 | P12: 19570.56 | Q12: 19883.059 | R12: 20200.549 | S12: 20523.108 | T12: 20825.711 | U12: 21132.776 | V12: 21444.368 | W12: 21760.554 | X12: 22081.403 | Y12: 22375.696 | Z12: 22673.911 | AA12: 22976.101 | AB12: 23282.318 | AC12: 23592.617 | AD12: 23881.059 | AE12: 24173.028 | AF12: 24468.567 | AG12: 24767.719 | AH12: 25070.528 | AI12: 25377.04 | AJ12: 25687.299 | AK12: 26001.351 | AL12: 26319.243 | AM12: 26641.021 | AN12: 26966.733 | AO12: 27296.428 | AP12: 27630.153 | AQ12: 27967.959 | AR12: 28309.894
B13: 6 | C13: Panglao | D13: LGU-run, BLGU-run, Richli, Balibago, Mactan Rock, Abejo | H13: 39839 | I13: 40520.747 | J13: 41214.16 | K13: 41919.439 | L13: 42636.787 | M13: 42636.787 | N13: 43366.411 | O13: 44058.879 | P13: 44762.403 | Q13: 45477.162 | R13: 46203.333 | S13: 46941.1 | T13: 47633.224 | U13: 48335.552 | V13: 49048.236 | W13: 49771.428 | X13: 50505.283 | Y13: 51178.399 | Z13: 51860.487 | AA13: 52551.664 | AB13: 53252.054 | AC13: 53961.778 | AD13: 54621.513 | AE13: 55289.314 | AF13: 55965.28 | AG13: 56649.51 | AH13: 57342.105 | AI13: 58043.168 | AJ13: 58752.802 | AK13: 59471.112 | AL13: 60198.204 | AM13: 60934.185 | AN13: 61679.165 | AO13: 62433.252 | AP13: 63196.559 | AQ13: 63969.199 | AR13: 64751.284
B14: 7 | C14: Sikatuna | D14: LGU-run | H14: 6906 | I14: 7024.1792 | J14: 7144.3808 | K14: 7266.6394 | L14: 7390.9901 | M14: 7390.9901 | N14: 7517.4688 | O14: 7637.5064 | P14: 7759.4608 | Q14: 7883.3625 | R14: 8009.2427 | S14: 8137.1329 | T14: 8257.1109 | U14: 8378.8579 | V14: 8502.4001 | W14: 8627.7638 | X14: 8754.9759 | Y14: 8871.659 | Z14: 8989.8973 | AA14: 9109.7115 | AB14: 9231.1224 | AC14: 9354.1515 | AD14: 9468.5151 | AE14: 9584.2769 | AF14: 9701.4539 | AG14: 9820.0636 | AH14: 9940.1234 | AI14: 10061.651 | AJ14: 10184.665 | AK14: 10309.182 | AL14: 10435.222 | AM14: 10562.802 | AN14: 10691.943 | AO14: 10822.662 | AP14: 10954.98 | AQ14: 11088.915 | AR14: 11224.488
B15: 8 | C15: Tagbilaran City | D15: LGU-run, BWUI, Richli | H15: 104976 | I15: 106772.41 | J15: 108599.55 | K15: 110457.97 | L15: 112348.19 | M15: 112348.19 | N15: 114270.75 | O15: 116095.41 | P15: 117949.2 | Q15: 119832.59 | R15: 121746.06 | S15: 123690.08 | T15: 125513.83 | U15: 127364.46 | V15: 129242.39 | W15: 131148.01 | X15: 133081.72 | Y15: 134855.38 | Z15: 136652.69 | AA15: 138473.95 | AB15: 140319.48 | AC15: 142189.6 | AD15: 143928.01 | AE15: 145687.67 | AF15: 147468.84 | AG15: 149271.79 | AH15: 151096.78 | AI15: 152944.09 | AJ15: 154813.98 | AK15: 156706.73 | AL15: 158622.62 | AM15: 160561.94 | AN15: 162524.96 | AO15: 164511.99 | AP15: 166523.31 | AQ15: 168559.22 | AR15: 170620.02
C16: TOTAL | H16: 264817 | I16: 269348.69 | J16: 273957.94 | K16: 278646.05 | L16: 283414.4 | M16: 283414.4 | N16: 288264.34 | O16: 292867.29 | P16: 297543.75 | Q16: 302294.88 | R16: 307121.87 | S16: 312025.94 | T16: 316626.61 | U16: 321295.11 | V16: 326032.45 | W16: 330839.63 | X16: 335717.7 | Y16: 340192.03 | Z16: 344725.98 | AA16: 349320.37 | AB16: 353975.98 | AC16: 358693.65 | AD16: 363079.03 | AE16: 367518.02 | AF16: 372011.28 | AG16: 376559.48 | AH16: 381163.29 | AI16: 385823.38 | AJ16: 390540.44 | AK16: 395315.18 | AL16: 400148.29 | AM16: 405040.49 | AN16: 409992.5 | AO16: 415005.06 | AP16: 420078.9 | AQ16: 425214.77 | AR16: 430413.43
C18: HOUSEHOLDS
C19: City/Municipality | D19: WSPs | G19: 2019 | H19: 2020 | I19: 2021 | J19: 2022 | K19: 2023 | L19: 45352 | M19: 2024 | N19: 2025 | O19: 2026 | P19: 2027 | Q19: 2028 | R19: 2029 | S19: 2030 | T19: 2031 | U19: 2032 | V19: 2033 | W19: 2034 | X19: 2035 | Y19: 2036 | Z19: 2037 | AA19: 2038 | AB19: 2039 | AC19: 2040 | AD19: 2041 | AE19: 2042 | AF19: 2043 | AG19: 2044 | AH19: 2045 | AI19: 2046 | AJ19: 2047 | AK19: 2048 | AL19: 2049 | AM19: 2050 | AN19: 2051 | AO19: 2052 | AP19: 2053 | AQ19: 2054 | AR19: 2055
B22: 1 | C22: Alburquerque | D22: LGU-run, BLGU-run | H22: 2615.3488 | I22: 2660.1041 | J22: 2705.6253 | K22: 2751.9254 | L22: 2799.0179 | M22: 2799.0179 | N22: 2846.9162 | O22: 2892.3753 | P22: 2938.5602 | Q22: 2985.4826 | R22: 3033.1543 | S22: 3081.5872 | T22: 3127.0237 | U22: 3173.1301 | V22: 3219.9163 | W22: 3267.3924 | X22: 3315.5685 | Y22: 3359.7572 | Z22: 3404.5348 | AA22: 3449.9092 | AB22: 3495.8884 | AC22: 3542.4803 | AD22: 3585.7906 | AE22: 3629.6304 | AF22: 3674.0061 | AG22: 3718.9244 | AH22: 3764.3919 | AI22: 3810.4152 | AJ22: 3857.0012 | AK22: 3904.1568 | AL22: 3951.8889 | AM22: 4000.2046 | AN22: 4049.111 | AO22: 4098.6153 | AP22: 4148.7248 | AQ22: 4199.447 | AR22: 4250.7893
B23: 2 | C23: Baclayon | D23: LGU-run, BWUI, BLGU-run | H23: 5104.7727 | I23: 5192.1284 | J23: 5280.9789 | K23: 5371.3499 | L23: 5463.2674 | M23: 5463.2674 | N23: 5556.7578 | O23: 5645.4872 | P23: 5735.6333 | Q23: 5827.2189 | R23: 5920.267 | S23: 6014.8008 | T23: 6103.486 | U23: 6193.4789 | V23: 6284.7987 | W23: 6377.465 | X23: 6471.4975 | Y23: 6557.7473 | Z23: 6645.1466 | AA23: 6733.7108 | AB23: 6823.4553 | AC23: 6914.3958 | AD23: 6998.931 | AE23: 7084.4997 | AF23: 7171.1146 | AG23: 7258.7884 | AH23: 7347.5342 | AI23: 7437.3649 | AJ23: 7528.2939 | AK23: 7620.3346 | AL23: 7713.5006 | AM23: 7807.8056 | AN23: 7903.2636 | AO23: 7999.8886 | AP23: 8097.695 | AQ23: 8196.6972 | AR23: 8296.9098
B24: 3 | C24: Corella | D24: LGU-run | H24: 2204.4186 | I24: 2242.1418 | J24: 2280.5106 | K24: 2319.5359 | L24: 2359.2291 | M24: 2359.2291 | N24: 2399.6015 | O24: 2437.9179 | P24: 2476.8462 | Q24: 2516.396 | R24: 2556.5774 | S24: 2597.4004 | T24: 2635.6978 | U24: 2674.5599 | V24: 2713.9949 | W24: 2754.0114 | X24: 2794.618 | Y24: 2831.8636 | Z24: 2869.6057 | AA24: 2907.8508 | AB24: 2946.6056 | AC24: 2985.8769 | AD24: 3022.3821 | AE24: 3059.3337 | AF24: 3096.737 | AG24: 3134.5976 | AH24: 3172.9211 | AI24: 3211.7131 | AJ24: 3250.9794 | AK24: 3290.7258 | AL24: 3330.9581 | AM24: 3371.6823 | AN24: 3412.9044 | AO24: 3454.6305 | AP24: 3496.8667 | AQ24: 3539.6193 | AR24: 3582.8945
B25: 4 | C25: Dauis | D25: LGU-run, BLGU-run, Richli, Balibago, BWUI (bulk) | H25: 11411.304 | I25: 11606.581 | J25: 11805.199 | K25: 12007.216 | L25: 12212.69 | M25: 12212.69 | N25: 12421.68 | O25: 12620.028 | P25: 12821.542 | Q25: 13026.274 | R25: 13234.275 | S25: 13445.598 | T25: 13643.847 | U25: 13845.019 | V25: 14049.157 | W25: 14256.304 | X25: 14466.507 | Y25: 14659.311 | Z25: 14854.685 | AA25: 15052.663 | AB25: 15253.279 | AC25: 15456.57 | AD25: 15645.541 | AE25: 15836.823 | AF25: 16030.444 | AG25: 16226.431 | AH25: 16424.815 | AI25: 16625.624 | AJ25: 16828.889 | AK25: 17034.638 | AL25: 17242.903 | AM25: 17453.715 | AN25: 17667.103 | AO25: 17883.101 | AP25: 18101.739 | AQ25: 18323.05 | AR25: 18547.067
B26: 5 | C26: Loboc | D26: LGU-run, BLGU-run | H26: 3958.6364 | I26: 4026.3787 | J26: 4095.2803 | K26: 4165.361 | L26: 4236.6409 | M26: 4236.6409 | N26: 4309.1406 | O26: 4377.9482 | P26: 4447.8546 | Q26: 4518.8771 | R26: 4591.0338 | S26: 4664.3426 | T26: 4733.1161 | U26: 4802.9035 | V26: 4873.72 | W26: 4945.5806 | X26: 5018.5007 | Y26: 5085.3855 | Z26: 5153.1617 | AA26: 5221.8412 | AB26: 5291.436 | AC26: 5361.9583 | AD26: 5427.5135 | AE26: 5493.8701 | AF26: 5561.038 | AG26: 5629.0271 | AH26: 5697.8474 | AI26: 5767.5091 | AJ26: 5838.0225 | AK26: 5909.398 | AL26: 5981.6461 | AM26: 6054.7775 | AN26: 6128.803 | AO26: 6203.7336 | AP26: 6279.5803 | AQ26: 6356.3542 | AR26: 6434.0668
B27: 6 | C27: Panglao | D27: LGU-run, BLGU-run, Richli, Balibago, Mactan Rock, Abejo | H27: 8660.6522 | I27: 8808.858 | J27: 8959.6 | K27: 9112.9215 | L27: 9268.8668 | M27: 9268.8668 | N27: 9427.4808 | O27: 9578.0171 | P27: 9730.9573 | Q27: 9886.3395 | R27: 10044.203 | S27: 10204.587 | T27: 10355.049 | U27: 10507.729 | V27: 10662.66 | W27: 10819.876 | X27: 10979.409 | Y27: 11125.739 | Z27: 11274.019 | AA27: 11424.275 | AB27: 11576.534 | AC27: 11730.821 | AD27: 11874.242 | AE27: 12019.416 | AF27: 12166.365 | AG27: 12315.111 | AH27: 12465.675 | AI27: 12618.08 | AJ27: 12772.348 | AK27: 12928.503 | AL27: 13086.566 | AM27: 13246.562 | AN27: 13408.514 | AO27: 13572.446 | AP27: 13738.382 | AQ27: 13906.348 | AR27: 14076.366
B28: 7 | C28: Sikatuna | D28: LGU-run | H28: 1726.5 | I28: 1756.0448 | J28: 1786.0952 | K28: 1816.6598 | L28: 1847.7475 | M28: 1847.7475 | N28: 1879.3672 | O28: 1909.3766 | P28: 1939.8652 | Q28: 1970.8406 | R28: 2002.3107 | S28: 2034.2832 | T28: 2064.2777 | U28: 2094.7145 | V28: 2125.6 | W28: 2156.9409 | X28: 2188.744 | Y28: 2217.9148 | Z28: 2247.4743 | AA28: 2277.4279 | AB28: 2307.7806 | AC28: 2338.5379 | AD28: 2367.1288 | AE28: 2396.0692 | AF28: 2425.3635 | AG28: 2455.0159 | AH28: 2485.0309 | AI28: 2515.4128 | AJ28: 2546.1661 | AK28: 2577.2955 | AL28: 2608.8054 | AM28: 2640.7006 | AN28: 2672.9857 | AO28: 2705.6656 | AP28: 2738.7449 | AQ28: 2772.2288 | AR28: 2806.1219
B29: 8 | C29: Tagbilaran City | D29: LGU-run, BWUI, Richli | H29: 23328 | I29: 23727.201 | J29: 24133.234 | K29: 24546.215 | L29: 24966.264 | M29: 24966.264 | N29: 25393.5 | O29: 25798.979 | P29: 26210.933 | Q29: 26629.464 | R29: 27054.679 | S29: 27486.684 | T29: 27891.961 | U29: 28303.214 | V29: 28720.531 | W29: 29144.001 | X29: 29573.715 | Y29: 29967.863 | Z29: 30367.264 | AA29: 30771.988 | AB29: 31182.106 | AC29: 31597.69 | AD29: 31984.002 | AE29: 32375.038 | AF29: 32770.854 | AG29: 33171.509 | AH29: 33577.063 | AI29: 33987.575 | AJ29: 34403.107 | AK29: 34823.718 | AL29: 35249.472 | AM29: 35680.431 | AN29: 36116.658 | AO29: 36558.22 | AP29: 37005.179 | AQ29: 37457.603 | AR29: 37915.559
C30: TOTAL | H30: 59009.633 | I30: 60019.438 | J30: 61046.524 | K30: 62091.185 | L30: 63153.723 | M30: 63153.723 | N30: 64234.444 | O30: 65260.129 | P30: 66302.191 | Q30: 67360.893 | R30: 68436.501 | S30: 69529.283 | T30: 70554.458 | U30: 71594.748 | V30: 72650.378 | W30: 73721.572 | X30: 74808.56 | Y30: 75805.581 | Z30: 76815.891 | AA30: 77839.666 | AB30: 78877.085 | AC30: 79928.33 | AD30: 80905.531 | AE30: 81894.68 | AF30: 82895.922 | AG30: 83909.405 | AH30: 84935.279 | AI30: 85973.695 | AJ30: 87024.807 | AK30: 88088.769 | AL30: 89165.74 | AM30: 90255.878 | AN30: 91359.343 | AO30: 92476.3 | AP30: 93606.912 | AQ30: 94751.348 | AR30: 95909.775
C32: HOUSEHOLD SIZE
C33: City/Municipality | D33: WSPs | G33: 2019 | H33: 2020 | I33: 2021 | J33: 2022 | K33: 2023 | L33: 45352 | M33: 2024 | N33: 2025 | O33: 2026 | P33: 2027 | Q33: 2028 | R33: 2029 | S33: 2030 | T33: 2031 | U33: 2032 | V33: 2033 | W33: 2034 | X33: 2035 | Y33: 2036 | Z33: 2037 | AA33: 2038 | AB33: 2039 | AC33: 2040 | AD33: 2041 | AE33: 2042 | AF33: 2043 | AG33: 2044 | AH33: 2045 | AI33: 2046 | AJ33: 2047 | AK33: 2048 | AL33: 2049 | AM33: 2050 | AN33: 2051 | AO33: 2052 | AP33: 2053 | AQ33: 2054 | AR33: 2055
B36: 1 | C36: Alburquerque | D36: LGU-run, BLGU-run | G36: 4.3 | H36: 4.3 | I36: 4.3 | J36: 4.3 | K36: 4.3 | L36: 4.3 | M36: 4.3 | N36: 4.3 | O36: 4.3 | P36: 4.3 | Q36: 4.3 | R36: 4.3 | S36: 4.3 | T36: 4.3 | U36: 4.3 | V36: 4.3 | W36: 4.3 | X36: 4.3 | Y36: 4.3 | Z36: 4.3 | AA36: 4.3 | AB36: 4.3 | AC36: 4.3 | AD36: 4.3 | AE36: 4.3 | AF36: 4.3 | AG36: 4.3 | AH36: 4.3 | AI36: 4.3 | AJ36: 4.3 | AK36: 4.3 | AL36: 4.3 | AM36: 4.3 | AN36: 4.3 | AO36: 4.3 | AP36: 4.3 | AQ36: 4.3 | AR36: 4.3
B37: 2 | C37: Baclayon | D37: LGU-run, BWUI, BLGU-run | G37: 4.4 | H37: 4.4 | I37: 4.4 | J37: 4.4 | K37: 4.4 | L37: 4.4 | M37: 4.4 | N37: 4.4 | O37: 4.4 | P37: 4.4 | Q37: 4.4 | R37: 4.4 | S37: 4.4 | T37: 4.4 | U37: 4.4 | V37: 4.4 | W37: 4.4 | X37: 4.4 | Y37: 4.4 | Z37: 4.4 | AA37: 4.4 | AB37: 4.4 | AC37: 4.4 | AD37: 4.4 | AE37: 4.4 | AF37: 4.4 | AG37: 4.4 | AH37: 4.4 | AI37: 4.4 | AJ37: 4.4 | AK37: 4.4 | AL37: 4.4 | AM37: 4.4 | AN37: 4.4 | AO37: 4.4 | AP37: 4.4 | AQ37: 4.4 | AR37: 4.4
B38: 3 | C38: Corella | D38: LGU-run | G38: 4.3 | H38: 4.3 | I38: 4.3 | J38: 4.3 | K38: 4.3 | L38: 4.3 | M38: 4.3 | N38: 4.3 | O38: 4.3 | P38: 4.3 | Q38: 4.3 | R38: 4.3 | S38: 4.3 | T38: 4.3 | U38: 4.3 | V38: 4.3 | W38: 4.3 | X38: 4.3 | Y38: 4.3 | Z38: 4.3 | AA38: 4.3 | AB38: 4.3 | AC38: 4.3 | AD38: 4.3 | AE38: 4.3 | AF38: 4.3 | AG38: 4.3 | AH38: 4.3 | AI38: 4.3 | AJ38: 4.3 | AK38: 4.3 | AL38: 4.3 | AM38: 4.3 | AN38: 4.3 | AO38: 4.3 | AP38: 4.3 | AQ38: 4.3 | AR38: 4.3
B39: 4 | C39: Dauis | D39: LGU-run, BLGU-run, Richli, Balibago, BWUI (bulk) | G39: 4.6 | H39: 4.6 | I39: 4.6 | J39: 4.6 | K39: 4.6 | L39: 4.6 | M39: 4.6 | N39: 4.6 | O39: 4.6 | P39: 4.6 | Q39: 4.6 | R39: 4.6 | S39: 4.6 | T39: 4.6 | U39: 4.6 | V39: 4.6 | W39: 4.6 | X39: 4.6 | Y39: 4.6 | Z39: 4.6 | AA39: 4.6 | AB39: 4.6 | AC39: 4.6 | AD39: 4.6 | AE39: 4.6 | AF39: 4.6 | AG39: 4.6 | AH39: 4.6 | AI39: 4.6 | AJ39: 4.6 | AK39: 4.6 | AL39: 4.6 | AM39: 4.6 | AN39: 4.6 | AO39: 4.6 | AP39: 4.6 | AQ39: 4.6 | AR39: 4.6
B40: 5 | C40: Loboc | D40: LGU-run, BLGU-run | G40: 4.4 | H40: 4.4 | I40: 4.4 | J40: 4.4 | K40: 4.4 | L40: 4.4 | M40: 4.4 | N40: 4.4 | O40: 4.4 | P40: 4.4 | Q40: 4.4 | R40: 4.4 | S40: 4.4 | T40: 4.4 | U40: 4.4 | V40: 4.4 | W40: 4.4 | X40: 4.4 | Y40: 4.4 | Z40: 4.4 | AA40: 4.4 | AB40: 4.4 | AC40: 4.4 | AD40: 4.4 | AE40: 4.4 | AF40: 4.4 | AG40: 4.4 | AH40: 4.4 | AI40: 4.4 | AJ40: 4.4 | AK40: 4.4 | AL40: 4.4 | AM40: 4.4 | AN40: 4.4 | AO40: 4.4 | AP40: 4.4 | AQ40: 4.4 | AR40: 4.4
B41: 6 | C41: Panglao | D41: LGU-run, BLGU-run, Richli, Balibago, Mactan Rock, Abejo | G41: 4.6 | H41: 4.6 | I41: 4.6 | J41: 4.6 | K41: 4.6 | L41: 4.6 | M41: 4.6 | N41: 4.6 | O41: 4.6 | P41: 4.6 | Q41: 4.6 | R41: 4.6 | S41: 4.6 | T41: 4.6 | U41: 4.6 | V41: 4.6 | W41: 4.6 | X41: 4.6 | Y41: 4.6 | Z41: 4.6 | AA41: 4.6 | AB41: 4.6 | AC41: 4.6 | AD41: 4.6 | AE41: 4.6 | AF41: 4.6 | AG41: 4.6 | AH41: 4.6 | AI41: 4.6 | AJ41: 4.6 | AK41: 4.6 | AL41: 4.6 | AM41: 4.6 | AN41: 4.6 | AO41: 4.6 | AP41: 4.6 | AQ41: 4.6 | AR41: 4.6
B42: 7 | C42: Sikatuna | D42: LGU-run | G42: 4 | H42: 4 | I42: 4 | J42: 4 | K42: 4 | L42: 4 | M42: 4 | N42: 4 | O42: 4 | P42: 4 | Q42: 4 | R42: 4 | S42: 4 | T42: 4 | U42: 4 | V42: 4 | W42: 4 | X42: 4 | Y42: 4 | Z42: 4 | AA42: 4 | AB42: 4 | AC42: 4 | AD42: 4 | AE42: 4 | AF42: 4 | AG42: 4 | AH42: 4 | AI42: 4 | AJ42: 4 | AK42: 4 | AL42: 4 | AM42: 4 | AN42: 4 | AO42: 4 | AP42: 4 | AQ42: 4 | AR42: 4
B43: 8 | C43: Tagbilaran City | D43: LGU-run, BWUI, Richli | G43: 4.5 | H43: 4.5 | I43: 4.5 | J43: 4.5 | K43: 4.5 | L43: 4.5 | M43: 4.5 | N43: 4.5 | O43: 4.5 | P43: 4.5 | Q43: 4.5 | R43: 4.5 | S43: 4.5 | T43: 4.5 | U43: 4.5 | V43: 4.5 | W43: 4.5 | X43: 4.5 | Y43: 4.5 | Z43: 4.5 | AA43: 4.5 | AB43: 4.5 | AC43: 4.5 | AD43: 4.5 | AE43: 4.5 | AF43: 4.5 | AG43: 4.5 | AH43: 4.5 | AI43: 4.5 | AJ43: 4.5 | AK43: 4.5 | AL43: 4.5 | AM43: 4.5 | AN43: 4.5 | AO43: 4.5 | AP43: 4.5 | AQ43: 4.5 | AR43: 4.5
L44: 4.487691 | M44: 4.487691 | N44: 4.487691 | O44: 4.487691 | P44: 4.487691 | Q44: 4.487691 | R44: 4.487691 | S44: 4.487691 | T44: 4.487691 | U44: 4.487691 | V44: 4.487691 | W44: 4.487691 | X44: 4.487691 | Y44: 4.487691 | Z44: 4.487691 | AA44: 4.487691 | AB44: 4.487691 | AC44: 4.487691 | AD44: 4.487691 | AE44: 4.487691 | AF44: 4.487691 | AG44: 4.487691 | AH44: 4.487691 | AI44: 4.487691 | AJ44: 4.487691 | AK44: 4.487691 | AL44: 4.487691 | AM44: 4.487691 | AN44: 4.487691 | AO44: 4.487691 | AP44: 4.487691 | AQ44: 4.487691 | AR44: 4.487691
C46: HOUSEHOLD COVERAGE (%) - served by all
C47: City/Municipality | D47: WSPs | G47: 2019 | H47: 2020 | I47: 2021 | J47: 2022 | K47: 2023 | L47: 45352 | M47: 2024 | N47: 2025 | O47: 2026 | P47: 2027 | Q47: 2028 | R47: 2029 | S47: 2030 | T47: 2031 | U47: 2032 | V47: 2033 | W47: 2034 | X47: 2035 | Y47: 2036 | Z47: 2037 | AA47: 2038 | AB47: 2039 | AC47: 2040 | AD47: 2041 | AE47: 2042 | AF47: 2043 | AG47: 2044 | AH47: 2045 | AI47: 2046 | AJ47: 2047 | AK47: 2048 | AL47: 2049 | AM47: 2050 | AN47: 2051 | AO47: 2052 | AP47: 2053 | AQ47: 2054 | AR47: 2055
K48: based on WSC of LGU waterworks | L48: based on WSC of LGU waterworks | M48: based on WSC of LGU waterworks | N48: assumed saturation of brgys served by the waterworks
B50: 1 | C50: Alburquerque | D50: LGU-run, BLGU-run | K50: 0.73766534 | L50: 0.74025966 | M50: 0.74766225 | N50: 1 | O50: 1 | P50: 1 | Q50: 1 | R50: 1 | S50: 1 | T50: 1 | U50: 1 | V50: 1 | W50: 1 | X50: 1 | Y50: 1 | Z50: 1 | AA50: 1 | AB50: 1 | AC50: 1 | AD50: 1 | AE50: 1 | AF50: 1 | AG50: 1 | AH50: 1 | AI50: 1 | AJ50: 1 | AK50: 1 | AL50: 1 | AM50: 1 | AN50: 1 | AO50: 1 | AP50: 1 | AQ50: 1 | AR50: 1
B51: 2 | C51: Baclayon | D51: LGU-run, BWUI, BLGU-run | K51: 0.71229766 | L51: 0.70031352 | M51: 0.70031352 | N51: 1 | O51: 1 | P51: 1 | Q51: 1 | R51: 1 | S51: 1 | T51: 1 | U51: 1 | V51: 1 | W51: 1 | X51: 1 | Y51: 1 | Z51: 1 | AA51: 1 | AB51: 1 | AC51: 1 | AD51: 1 | AE51: 1 | AF51: 1 | AG51: 1 | AH51: 1 | AI51: 1 | AJ51: 1 | AK51: 1 | AL51: 1 | AM51: 1 | AN51: 1 | AO51: 1 | AP51: 1 | AQ51: 1 | AR51: 1
B52: 3 | C52: Corella | D52: LGU-run | K52: 0.97864404 | L52: 0.96217871 | M52: 0.96217871 | N52: 1.082497 | O52: 1.0820124 | P52: 1.0815307 | Q52: 1.0810518 | R52: 1.0805757 | S52: 1.0801024 | T52: 1.0797279 | U52: 1.0793551 | V52: 1.0789841 | W52: 1.0786148 | X52: 1.0782472 | Y52: 1.0779902 | Z52: 1.0777341 | AA52: 1.0774789 | AB52: 1.0772244 | AC52: 1.0769708 | AD52: 1.0768016 | AE52: 1.0766327 | AF52: 1.0764641 | AG52: 1.076296 | AH52: 1.0761282 | AI52: 1.0759608 | AJ52: 1.0757938 | AK52: 1.0756271 | AL52: 1.0754608 | AM52: 1.0752948 | AN52: 1.0751292 | AO52: 1.074964 | AP52: 1.0747992 | AQ52: 1.0746347 | AR52: 1.0744706
B53: 4 | C53: Dauis | D53: LGU-run, BLGU-run, Richli, Balibago, BWUI (bulk) | K53: 0.58448187 | L53: 0.57464817 | M53: 0.57464817 | N53: 1.0328179 | O53: 1.0301697 | P53: 1.0275631 | Q53: 1.0249974 | R53: 1.0224721 | S53: 1.0199865 | T53: 1.0177247 | U53: 1.0154957 | V53: 1.0132991 | W53: 1.0111344 | X53: 1.0090012 | Y53: 1.0070983 | Z53: 1.0052205 | AA53: 1.0042862 | AB53: 1.0033968 | AC53: 1.002519 | AD53: 1.0017235 | AE53: 1.0009376 | AF53: 1.0001612 | AG53: 1 | AH53: 1 | AI53: 1 | AJ53: 1 | AK53: 1 | AL53: 1 | AM53: 1 | AN53: 1 | AO53: 1 | AP53: 1 | AQ53: 1 | AR53: 1
B54: 5 | C54: Loboc | D54: LGU-run, BLGU-run | K54: 0.2849693 | L54: 0.28253516 | M54: 0.28371534 | N54: 1.0055073 | O54: 1.0050806 | P54: 1.0046605 | Q54: 1.0042471 | R54: 1.0038402 | S54: 1.0034396 | T54: 1.0030752 | U54: 1.002716 | V54: 1.002362 | W54: 1.0020132 | X54: 1.0016695 | Y54: 1.0013628 | Z54: 1.0010602 | AA54: 1.0007616 | AB54: 1.0004669 | AC54: 1.0001761 | AD54: 1 | AE54: 1 | AF54: 1 | AG54: 1 | AH54: 1 | AI54: 1 | AJ54: 1 | AK54: 1 | AL54: 1 | AM54: 1 | AN54: 1 | AO54: 1 | AP54: 1 | AQ54: 1 | AR54: 1
B55: 6 | C55: Panglao | D55: LGU-run, BLGU-run, Richli, Balibago, Mactan Rock, Abejo | K55: 0.78043029 | L55: 0.79599806 | M55: 0.81034717 | N55: 1.0514495 | O55: 1.0459522 | P55: 1.0405412 | Q55: 1.0352153 | R55: 1.0299731 | S55: 1.0248132 | T55: 1.0201179 | U55: 1.0154909 | V55: 1.0125344 | W55: 1.011699 | X55: 1.0108758 | Y55: 1.0101415 | Z55: 1.0094169 | AA55: 1.0087017 | AB55: 1.007996 | AC55: 1.0072996 | AD55: 1.0066684 | AE55: 1.0060449 | AF55: 1.0054289 | AG55: 1.0048203 | AH55: 1.0042191 | AI55: 1.0036251 | AJ55: 1.0030384 | AK55: 1.0024587 | AL55: 1.001886 | AM55: 1.0013202 | AN55: 1.0007613 | AO55: 1.0002091 | AP55: 1 | AQ55: 1 | AR55: 1
B56: 7 | C56: Sikatuna | D56: LGU-run | K56: 1.0590865 | L56: 1.0845638 | M56: 1.0855109 | N56: 1.0812649 | O56: 1.0716172 | P56: 1.0633364 | Q56: 1.0551858 | R56: 1.0471632 | S56: 1.0392668 | T56: 1.0320812 | U56: 1.0281317 | V56: 1.0238726 | W56: 1.0196754 | X56: 1.0166746 | Y56: 1.0150041 | Z56: 1.0133556 | AA56: 1.0117287 | AB56: 1.0101232 | AC56: 1.0085389 | AD56: 1.007103 | AE56: 1.0056845 | AF56: 1.0042832 | AG56: 1.0028987 | AH56: 1.001531 | AI56: 1.0010798 | AJ56: 1.0005036 | AK56: 0.99993431 | AL56: 1 | AM56: 1 | AN56: 1 | AO56: 1 | AP56: 1 | AQ56: 1 | AR56: 1
B57: 8 | C57: Tagbilaran City | D57: LGU-run, BWUI, Richli | K57: 0.23702228 | L57: 0.23259387 | M57: 0.23323474 | N57: 1 | O57: 1 | P57: 1 | Q57: 1 | R57: 1 | S57: 1 | T57: 1 | U57: 1 | V57: 1 | W57: 1 | X57: 1 | Y57: 1 | Z57: 1 | AA57: 1 | AB57: 1 | AC57: 1 | AD57: 1 | AE57: 1 | AF57: 1 | AG57: 1 | AH57: 1 | AI57: 1 | AJ57: 1 | AK57: 1 | AL57: 1 | AM57: 1 | AN57: 1 | AO57: 1 | AP57: 1 | AQ57: 1 | AR57: 1
C58: TOTAL | K58: 0.50224521 | L58: 0.49992302 | M58: 0.50271731 | N58: 1.0197264 | O58: 1.0180784 | P58: 1.0164917 | Q58: 1.0149298 | R58: 1.0133923 | S58: 1.0118787 | T58: 1.0105036 | U58: 1.0092398 | V58: 1.0082189 | W58: 1.0075177 | X58: 1.0068598 | Y58: 1.006305 | Z58: 1.0057574 | AA58: 1.0053946 | AB58: 1.0050428 | AC58: 1.0046955 | AD58: 1.0043889 | AE58: 1.0040976 | AF58: 1.0038097 | AG58: 1.0036425 | AH58: 1.0035079 | AI58: 1.0034013 | AJ58: 1.0032921 | AK58: 1.0031841 | AL58: 1.0030958 | AM58: 1.0030065 | AN58: 1.0029183 | AO58: 1.0028311 | AP58: 1.0027943 | AQ58: 1.0027881 | AR58: 1.002782
C60: WATER SERVICE CONNECTIONS (WSC)
C61: RESIDENTIAL WSC (served by all)
C62: City/Municipality | D62: WSPs | G62: 2019 | H62: 2020 | I62: 2021 | J62: 2022 | K62: 2023 | L62: 45352 | M62: 2024 | N62: 2025 | O62: 2026 | P62: 2027 | Q62: 2028 | R62: 2029 | S62: 2030 | T62: 2031 | U62: 2032 | V62: 2033 | W62: 2034 | X62: 2035 | Y62: 2036 | Z62: 2037 | AA62: 2038 | AB62: 2039 | AC62: 2040 | AD62: 2041 | AE62: 2042 | AF62: 2043 | AG62: 2044 | AH62: 2045 | AI62: 2046 | AJ62: 2047 | AK62: 2048 | AL62: 2049 | AM62: 2050 | AN62: 2051 | AO62: 2052 | AP62: 2053 | AQ62: 2054 | AR62: 2055
K63: based on WSC of LGU waterworks | L63: based on WSC of LGU waterworks | M63: based on WSC of LGU waterworks | N63: assumed saturation of brgys served by the waterworks
B65: 1 | C65: Alburquerque | D65: LGU-run, BLGU-run | G65: 0 | H65: 0 | I65: 0 | J65: 0 | K65: 2030 | L65: 2072 | M65: 2092.72 | N65: 2846.9162 | O65: 2892.3753 | P65: 2938.5602 | Q65: 2985.4826 | R65: 3033.1543 | S65: 3081.5872 | T65: 3127.0237 | U65: 3173.1301 | V65: 3219.9163 | W65: 3267.3924 | X65: 3315.5685 | Y65: 3359.7572 | Z65: 3404.5348 | AA65: 3449.9092 | AB65: 3495.8884 | AC65: 3542.4803 | AD65: 3585.7906 | AE65: 3629.6304 | AF65: 3674.0061 | AG65: 3718.9244 | AH65: 3764.3919 | AI65: 3810.4152 | AJ65: 3857.0012 | AK65: 3904.1568 | AL65: 3951.8889 | AM65: 4000.2046 | AN65: 4049.111 | AO65: 4098.6153 | AP65: 4148.7248 | AQ65: 4199.447 | AR65: 4250.7893
B66: 2 | C66: Baclayon | D66: LGU-run, BWUI, BLGU-run | G66: 0 | H66: 0 | I66: 0 | J66: 0 | K66: 3826 | L66: 3826 | M66: 3826 | N66: 5556.7578 | O66: 5645.4872 | P66: 5735.6333 | Q66: 5827.2189 | R66: 5920.267 | S66: 6014.8008 | T66: 6103.486 | U66: 6193.4789 | V66: 6284.7987 | W66: 6377.465 | X66: 6471.4975 | Y66: 6557.7473 | Z66: 6645.1466 | AA66: 6733.7108 | AB66: 6823.4553 | AC66: 6914.3958 | AD66: 6998.931 | AE66: 7084.4997 | AF66: 7171.1146 | AG66: 7258.7884 | AH66: 7347.5342 | AI66: 7437.3649 | AJ66: 7528.2939 | AK66: 7620.3346 | AL66: 7713.5006 | AM66: 7807.8056 | AN66: 7903.2636 | AO66: 7999.8886 | AP66: 8097.695 | AQ66: 8196.6972 | AR66: 8296.9098
B67: 3 | C67: Corella | D67: LGU-run | G67: 0 | H67: 0 | I67: 0 | J67: 0 | K67: 2270 | L67: 2270 | M67: 2270 | N67: 2597.5615 | O67: 2637.8575 | P67: 2678.7852 | Q67: 2720.3544 | R67: 2762.5754 | S67: 2805.4584 | T67: 2845.8363 | U67: 2886.7998 | V67: 2928.3572 | W67: 2970.5174 | X67: 3013.289 | Y67: 3052.7213 | Z67: 3092.672 | AA67: 3133.1477 | AB67: 3174.1555 | AC67: 3215.7023 | AD67: 3254.5058 | AE67: 3293.7786 | AF67: 3333.5263 | AG67: 3373.7548 | AH67: 3414.4699 | AI67: 3455.6774 | AJ67: 3497.3834 | AK67: 3539.5938 | AL67: 3582.3148 | AM67: 3625.5525 | AN67: 3669.3133 | AO67: 3713.6035 | AP67: 3758.4294 | AQ67: 3803.7976 | AR67: 3849.7147
B68: 4 | C68: Dauis | D68: LGU-run, BLGU-run, Richli, Balibago, BWUI (bulk) | G68: 0 | H68: 0 | I68: 0 | J68: 0 | K68: 7018 | L68: 7018 | M68: 7018 | N68: 12829.334 | O68: 13000.77 | P68: 13174.943 | Q68: 13351.898 | R68: 13531.678 | S68: 13714.329 | T68: 13885.679 | U68: 14059.557 | V68: 14235.998 | W68: 14415.04 | X68: 14596.723 | Y68: 14763.368 | Z68: 14932.234 | AA68: 15117.182 | AB68: 15305.091 | AC68: 15495.504 | AD68: 15672.506 | AE68: 15851.671 | AF68: 16033.027 | AG68: 16226.431 | AH68: 16424.815 | AI68: 16625.624 | AJ68: 16828.889 | AK68: 17034.638 | AL68: 17242.903 | AM68: 17453.715 | AN68: 17667.103 | AO68: 17883.101 | AP68: 18101.739 | AQ68: 18323.05 | AR68: 18547.067
B69: 5 | C69: Loboc | D69: LGU-run, BLGU-run | G69: 0 | H69: 0 | I69: 0 | J69: 0 | K69: 1187 | L69: 1197 | M69: 1202 | N69: 4332.8724 | O69: 4400.1907 | P69: 4468.584 | Q69: 4538.0693 | R69: 4608.6642 | S69: 4680.3863 | T69: 4747.6712 | U69: 4815.9482 | V69: 4885.2318 | W69: 4955.537 | X69: 5026.8789 | Y69: 5092.316 | Z69: 5158.6252 | AA69: 5225.8182 | AB69: 5293.9067 | AC69: 5362.9026 | AD69: 5427.5135 | AE69: 5493.8701 | AF69: 5561.038 | AG69: 5629.0271 | AH69: 5697.8474 | AI69: 5767.5091 | AJ69: 5838.0225 | AK69: 5909.398 | AL69: 5981.6461 | AM69: 6054.7775 | AN69: 6128.803 | AO69: 6203.7336 | AP69: 6279.5803 | AQ69: 6356.3542 | AR69: 6434.0668
B70: 6 | C70: Panglao | D70: LGU-run, BLGU-run, Richli, Balibago, Mactan Rock, Abejo | G70: 0 | H70: 0 | I70: 0 | J70: 0 | K70: 7112 | L70: 7378 | M70: 7511 | N70: 9912.5204 | O70: 10018.148 | P70: 10125.462 | Q70: 10234.49 | R70: 10345.258 | S70: 10457.796 | T70: 10563.371 | U70: 10670.503 | V70: 10796.31 | W70: 10946.458 | X70: 11098.82 | Y70: 11238.571 | Z70: 11380.185 | AA70: 11523.686 | AB70: 11669.099 | AC70: 11816.451 | AD70: 11953.424 | AE70: 12092.072 | AF70: 12232.415 | AG70: 12374.473 | AH70: 12518.269 | AI70: 12663.822 | AJ70: 12811.155 | AK70: 12960.289 | AL70: 13111.247 | AM70: 13264.05 | AN70: 13418.722 | AO70: 13575.284 | AP70: 13738.382 | AQ70: 13906.348 | AR70: 14076.366
B71: 7 | C71: Sikatuna | D71: LGU-run | G71: 0 | H71: 0 | I71: 0 | J71: 0 | K71: 1924 | L71: 2004 | M71: 2005.75 | N71: 2032.0938 | O71: 2046.1209 | P71: 2062.7293 | Q71: 2079.603 | R71: 2096.7461 | S71: 2114.163 | T71: 2130.5023 | U71: 2153.6424 | V71: 2176.3437 | W71: 2199.3797 | X71: 2225.2405 | Y71: 2251.1926 | Z71: 2277.4906 | AA71: 2304.1391 | AB71: 2331.1428 | AC71: 2358.5063 | AD71: 2383.9425 | AE71: 2409.6897 | AF71: 2435.7517 | AG71: 2462.1323 | AH71: 2488.8354 | AI71: 2518.1288 | AJ71: 2547.4483 | AK71: 2577.1262 | AL71: 2608.8054 | AM71: 2640.7006 | AN71: 2672.9857 | AO71: 2705.6656 | AP71: 2738.7449 | AQ71: 2772.2288 | AR71: 2806.1219
B72: 8 | C72: Tagbilaran City | D72: LGU-run, BWUI, Richli | G72: 0 | H72: 0 | I72: 0 | J72: 0 | K72: 5818 | L72: 5807 | M72: 5823 | N72: 25393.5 | O72: 25798.979 | P72: 26210.933 | Q72: 26629.464 | R72: 27054.679 | S72: 27486.684 | T72: 27891.961 | U72: 28303.214 | V72: 28720.531 | W72: 29144.001 | X72: 29573.715 | Y72: 29967.863 | Z72: 30367.264 | AA72: 30771.988 | AB72: 31182.106 | AC72: 31597.69 | AD72: 31984.002 | AE72: 32375.038 | AF72: 32770.854 | AG72: 33171.509 | AH72: 33577.063 | AI72: 33987.575 | AJ72: 34403.107 | AK72: 34823.718 | AL72: 35249.472 | AM72: 35680.431 | AN72: 36116.658 | AO72: 36558.22 | AP72: 37005.179 | AQ72: 37457.603 | AR72: 37915.559
C73: TOTAL | G73: 0 | H73: 0 | I73: 0 | J73: 0 | K73: 31185 | L73: 31572 | M73: 31748.47 | N73: 65501.556 | O73: 66439.928 | P73: 67395.63 | Q73: 68366.58 | R73: 69353.022 | S73: 70355.204 | T73: 71295.531 | U73: 72256.273 | V73: 73247.487 | W73: 74275.791 | X73: 75321.732 | Y73: 76283.536 | Z73: 77258.152 | AA73: 78259.581 | AB73: 79274.845 | AC73: 80303.633 | AD73: 81260.616 | AE73: 82230.25 | AF73: 83211.733 | AG73: 84215.041 | AH73: 85233.226 | AI73: 86266.118 | AJ73: 87311.3 | AK73: 88369.255 | AL73: 89441.778 | AM73: 90527.236 | AN73: 91625.96 | AO73: 92738.111 | AP73: 93868.475 | AQ73: 95015.526 | AR73: 96176.595
C75: COMMERCIAL WSC (served by all)
C76: City/Municipality | D76: WSPs | G76: 2019 | H76: 2020 | I76: 2021 | J76: 2022 | K76: 2023 | L76: 45352 | M76: 2024 | N76: 2025 | O76: 2026 | P76: 2027 | Q76: 2028 | R76: 2029 | S76: 2030 | T76: 2031 | U76: 2032 | V76: 2033 | W76: 2034 | X76: 2035 | Y76: 2036 | Z76: 2037 | AA76: 2038 | AB76: 2039 | AC76: 2040 | AD76: 2041 | AE76: 2042 | AF76: 2043 | AG76: 2044 | AH76: 2045 | AI76: 2046 | AJ76: 2047 | AK76: 2048 | AL76: 2049 | AM76: 2050 | AN76: 2051 | AO76: 2052 | AP76: 2053 | AQ76: 2054 | AR76: 2055
B79: 1 | C79: Alburquerque | D79: LGU-run, BLGU-run | G79: 0 | H79: 0 | I79: 0 | J79: 0 | K79: 135 | L79: 130 | M79: 131.3 | N79: 131.9565 | O79: 132.61628 | P79: 133.27936 | Q79: 133.94576 | R79: 134.61549 | S79: 137.3078 | T79: 140.05396 | U79: 142.85503 | V79: 145.71214 | W79: 148.62638 | X79: 150.85577 | Y79: 153.11861 | Z79: 155.41539 | AA79: 157.74662 | AB79: 160.11282 | AC79: 161.71395 | AD79: 163.33109 | AE79: 164.9644 | AF79: 166.61404 | AG79: 168.28018 | AH79: 169.96298 | AI79: 171.66261 | AJ79: 173.37924 | AK79: 175.11303 | AL79: 176.86416 | AM79: 178.6328 | AN79: 180.41913 | AO79: 182.22332 | AP79: 184.04556 | AQ79: 185.88601 | AR79: 187.74487
B80: 2 | C80: Baclayon | D80: LGU-run, BWUI, BLGU-run | G80: 0 | H80: 0 | I80: 0 | J80: 0 | K80: 0 | L80: 0 | M80: 0 | N80: 13.065 | O80: 13.130325 | P80: 13.195977 | Q80: 13.261957 | R80: 13.328266 | S80: 13.394908 | T80: 13.461882 | U80: 13.529192 | V80: 13.596838 | W80: 13.664822 | X80: 13.733146 | Y80: 13.801812 | Z80: 13.870821 | AA80: 13.940175 | AB80: 14.009876 | AC80: 14.079925 | AD80: 14.150325 | AE80: 14.221076 | AF80: 14.292182 | AG80: 14.363643 | AH80: 14.435461 | AI80: 14.507638 | AJ80: 14.580176 | AK80: 14.653077 | AL80: 14.726342 | AM80: 14.799974 | AN80: 14.873974 | AO80: 14.948344 | AP80: 15.023086 | AQ80: 15.098201 | AR80: 15.173692
B81: 3 | C81: Corella | D81: LGU-run | G81: 0 | H81: 0 | I81: 0 | J81: 0 | K81: 501 | L81: 501 | M81: 501 | N81: 503.505 | O81: 506.02252 | P81: 508.55264 | Q81: 511.0954 | R81: 513.65088 | S81: 534.19691 | T81: 555.56479 | U81: 577.78738 | V81: 600.89888 | W81: 624.93483 | X81: 631.18418 | Y81: 637.49602 | Z81: 643.87098 | AA81: 650.30969 | AB81: 656.81279 | AC81: 663.38092 | AD81: 670.01473 | AE81: 676.71487 | AF81: 683.48202 | AG81: 690.31684 | AH81: 693.76843 | AI81: 697.23727 | AJ81: 700.72345 | AK81: 704.22707 | AL81: 707.74821 | AM81: 711.28695 | AN81: 714.84338 | AO81: 718.4176 | AP81: 722.00969 | AQ81: 725.61974 | AR81: 729.24783
B82: 4 | C82: Dauis | D82: LGU-run, BLGU-run, Richli, Balibago, BWUI (bulk) | G82: 0 | H82: 0 | I82: 0 | J82: 0 | K82: 31 | L82: 31 | M82: 31 | N82: 222.22 | O82: 223.44745 | P82: 224.6824 | Q82: 225.9249 | R82: 227.17501 | S82: 229.00032 | T82: 230.85603 | U82: 232.74295 | V82: 234.66188 | W82: 236.61366 | X82: 238.27018 | Y82: 239.94486 | Z82: 241.63797 | AA82: 243.34982 | AB82: 245.0807 | AC82: 246.46771 | AD82: 247.86347 | AE82: 249.26805 | AF82: 250.68149 | AG82: 252.10388 | AH82: 253.53527 | AI82: 254.97572 | AJ82: 256.42531 | AK82: 257.88408 | AL82: 259.35212 | AM82: 260.82949 | AN82: 262.31625 | AO82: 263.81246 | AP82: 265.31821 | AQ82: 266.83355 | AR82: 268.35856
B83: 5 | C83: Loboc | D83: LGU-run, BLGU-run | G83: 0 | H83: 0 | I83: 0 | J83: 0 | K83: 80.07 | L83: 80.1407 | M83: 80.1407 | N83: 80.942107 | O83: 81.751528 | P83: 82.569043 | Q83: 83.394734 | R83: 85.896576 | S83: 88.473473 | T83: 91.127677 | U83: 93.861508 | V83: 96.677353 | W83: 98.6109 | X83: 100.58312 | Y83: 102.59478 | Z83: 104.64668 | AA83: 106.73961 | AB83: 107.80701 | AC83: 108.88508 | AD83: 109.97393 | AE83: 111.07367 | AF83: 112.1844 | AG83: 113.30625 | AH83: 114.43931 | AI83: 115.5837 | AJ83: 116.73954 | AK83: 117.90693 | AL83: 119.086 | AM83: 120.27686 | AN83: 121.47963 | AO83: 122.69443 | AP83: 123.92137 | AQ83: 125.16059 | AR83: 126.41219
B84: 6 | C84: Panglao | D84: LGU-run, BLGU-run, Richli, Balibago, Mactan Rock, Abejo | G84: 0 | H84: 0 | I84: 0 | J84: 0 | K84: 517 | L84: 517 | M84: 517 | N84: 978.61 | O84: 999.42815 | P84: 1019.4586 | Q84: 1039.7056 | R84: 1060.1733 | S84: 1092.2826 | T84: 1125.3064 | U84: 1161.2815 | V84: 1197.2459 | W84: 1234.2389 | X84: 1258.4123 | Y84: 1284.8649 | Z84: 1309.6022 | AA84: 1336.63 | AB84: 1362.954 | AC84: 1383.9126 | AD84: 1404.9493 | AE84: 1425.0649 | AF84: 1446.2602 | AG84: 1465.5359 | AH84: 1489.893 | AI84: 1512.3321 | AJ84: 1534.8541 | AK84: 1558.4598 | AL84: 1582.1501 | AM84: 1605.9257 | AN84: 1631.7876 | AO84: 1656.7365 | AP84: 1681.7734 | AQ84: 1708.8992 | AR84: 1735.1146
B85: 7 | C85: Sikatuna | D85: LGU-run | G85: 0 | H85: 0 | I85: 0 | J85: 0 | K85: 72 | L85: 75 | M85: 76 | N85: 76.76 | O85: 77.5276 | P85: 78.302876 | Q85: 79.085905 | R85: 79.876764 | S85: 83.071834 | T85: 86.394708 | U85: 89.850496 | V85: 93.444516 | W85: 97.182297 | X85: 99.125942 | Y85: 101.10846 | Z85: 103.13063 | AA85: 105.19324 | AB85: 107.29711 | AC85: 108.37008 | AD85: 109.45378 | AE85: 110.54832 | AF85: 111.6538 | AG85: 112.77034 | AH85: 113.89804 | AI85: 115.03702 | AJ85: 116.18739 | AK85: 117.34927 | AL85: 118.52276 | AM85: 119.70799 | AN85: 120.90507 | AO85: 122.11412 | AP85: 123.33526 | AQ85: 124.56861 | AR85: 125.8143
B86: 8 | C86: Tagbilaran City | D86: LGU-run, BWUI, Richli | G86: 0 | H86: 0 | I86: 0 | J86: 0 | K86: 38 | L86: 37 | M86: 37 | N86: 1746.292 | O86: 1753.7512 | P86: 1761.3826 | Q86: 1769.1911 | R86: 1777.1819 | S86: 1786.1383 | T86: 1795.3189 | U86: 1804.7306 | V86: 1814.3802 | W86: 1824.2747 | X86: 1833.9708 | Y86: 1843.9041 | Z86: 1854.0817 | AA86: 1864.5105 | AB86: 1875.1978 | AC86: 1885.6536 | AD86: 1896.3682 | AE86: 1907.3494 | AF86: 1918.605 | AG86: 1930.1431 | AH86: 1941.9719 | AI86: 1954.1002 | AJ86: 1966.5366 | AK86: 1979.2903 | AL86: 1992.3707 | AM86: 2005.7874 | AN86: 2019.5504 | AO86: 2033.6699 | AP86: 2048.1563 | AQ86: 2063.0207 | AR86: 2078.2741
C87: TOTAL | G87: 0 | H87: 0 | I87: 0 | J87: 0 | K87: 1374.07 | L87: 1371.1407 | M87: 1373.4407 | N87: 3753.3506 | O87: 3787.6751 | P87: 3821.4235 | Q87: 3855.6053 | R87: 3891.8983 | S87: 3963.8661 | T87: 4038.0844 | U87: 4116.6387 | V87: 4196.6176 | W87: 4278.1466 | X87: 4326.1354 | Y87: 4376.8335 | Z87: 4426.2563 | AA87: 4478.4196 | AB87: 4529.2721 | AC87: 4572.4638 | AD87: 4616.1048 | AE87: 4659.2047 | AF87: 4703.7731 | AG87: 4746.8201 | AH87: 4791.9044 | AI87: 4835.4362 | AJ87: 4879.4258 | AK87: 4924.8836 | AL87: 4970.8204 | AM87: 5017.2472 | AN87: 5066.1754 | AO87: 5114.6167 | AP87: 5163.5829 | AQ87: 5215.0865 | AR87: 5266.1401
C89: INSTITUTIONAL WSC (served by all)
C90: City/Municipality | D90: WSPs | G90: 2019 | H90: 2020 | I90: 2021 | J90: 2022 | K90: 2023 | L90: 45352 | M90: 2024 | N90: 2025 | O90: 2026 | P90: 2027 | Q90: 2028 | R90: 2029 | S90: 2030 | T90: 2031 | U90: 2032 | V90: 2033 | W90: 2034 | X90: 2035 | Y90: 2036 | Z90: 2037 | AA90: 2038 | AB90: 2039 | AC90: 2040 | AD90: 2041 | AE90: 2042 | AF90: 2043 | AG90: 2044 | AH90: 2045 | AI90: 2046 | AJ90: 2047 | AK90: 2048 | AL90: 2049 | AM90: 2050 | AN90: 2051 | AO90: 2052 | AP90: 2053 | AQ90: 2054 | AR90: 2055
K91: based on WSC of LGU waterworks | L91: based on WSC of LGU waterworks | M91: based on WSC of LGU waterworks | N91: assumed saturation of brgys served by the waterworks
G92: actual | H92: actual | I92: actual | J92: actual | K92: actual | L92: actual 3/24 | M92: annualized
B93: 1 | C93: Alburquerque | D93: LGU-run, BLGU-run | G93: 0 | H93: 0 | I93: 0 | J93: 0 | K93: 46.767442 | L93: 49 | M93: 49.245 | N93: 49.491225 | O93: 49.738681 | P93: 49.987375 | Q93: 50.237311 | R93: 50.488498 | S93: 50.74094 | T93: 50.994645 | U93: 51.249618 | V93: 51.505866 | W93: 51.763396 | X93: 52.022213 | Y93: 52.282324 | Z93: 52.543735 | AA93: 52.806454 | AB93: 53.070486 | AC93: 53.335839 | AD93: 53.602518 | AE93: 53.870531 | AF93: 54.139883 | AG93: 54.410583 | AH93: 54.682636 | AI93: 54.956049 | AJ93: 55.230829 | AK93: 55.506983 | AL93: 55.784518 | AM93: 56.063441 | AN93: 56.343758 | AO93: 56.625477 | AP93: 56.908604 | AQ93: 57.193147 | AR93: 57.479113
B94: 2 | C94: Baclayon | D94: LGU-run, BWUI, BLGU-run | G94: 0 | H94: 0 | I94: 0 | J94: 0 | K94: 0 | L94: 0 | M94: 0 | N94: 4 | O94: 4 | P94: 4 | Q94: 4 | R94: 4 | S94: 4 | T94: 4 | U94: 4 | V94: 4 | W94: 4 | X94: 4 | Y94: 4 | Z94: 4 | AA94: 4 | AB94: 4 | AC94: 4 | AD94: 4 | AE94: 4 | AF94: 4 | AG94: 4 | AH94: 4 | AI94: 4 | AJ94: 4 | AK94: 4 | AL94: 4 | AM94: 4 | AN94: 4 | AO94: 4 | AP94: 4 | AQ94: 4 | AR94: 4
B95: 3 | C95: Corella | D95: LGU-run | G95: 0 | H95: 0 | I95: 0 | J95: 0 | K95: 0 | L95: 0 | M95: 0 | N95: 0 | O95: 0 | P95: 0 | Q95: 0 | R95: 0 | S95: 0 | T95: 0 | U95: 0 | V95: 0 | W95: 0 | X95: 0 | Y95: 0 | Z95: 0 | AA95: 0 | AB95: 0 | AC95: 0 | AD95: 0 | AE95: 0 | AF95: 0 | AG95: 0 | AH95: 0 | AI95: 0 | AJ95: 0 | AK95: 0 | AL95: 0 | AM95: 0 | AN95: 0 | AO95: 0 | AP95: 0 | AQ95: 0 | AR95: 0
B96: 4 | C96: Dauis | D96: LGU-run, BLGU-run, Richli, Balibago, BWUI (bulk) | G96: 0 | H96: 0 | I96: 0 | J96: 0 | K96: 42 | L96: 42 | M96: 42 | N96: 42.33 | O96: 42.6633 | P96: 42.999933 | Q96: 43.339932 | R96: 43.683332 | S96: 44.030165 | T96: 44.380467 | U96: 44.734271 | V96: 45.091614 | W96: 45.45253 | X96: 45.817055 | Y96: 46.185226 | Z96: 46.557078 | AA96: 46.932649 | AB96: 47.311976 | AC96: 47.695095 | AD96: 48.082046 | AE96: 48.472867 | AF96: 48.867595 | AG96: 49.266271 | AH96: 49.668934 | AI96: 50.075623 | AJ96: 50.48638 | AK96: 50.901243 | AL96: 51.320256 | AM96: 51.743458 | AN96: 52.170893 | AO96: 52.602602 | AP96: 53.038628 | AQ96: 53.479014 | AR96: 53.923804
B97: 5 | C97: Loboc | D97: LGU-run, BLGU-run | G97: 0 | H97: 0 | I97: 0 | J97: 0 | K97: 16 | L97: 16 | M97: 16 | N97: 16 | O97: 16 | P97: 16 | Q97: 16 | R97: 16 | S97: 16 | T97: 16 | U97: 16 | V97: 16 | W97: 16 | X97: 16 | Y97: 16 | Z97: 16 | AA97: 16 | AB97: 16 | AC97: 16 | AD97: 16 | AE97: 16 | AF97: 16 | AG97: 16 | AH97: 16 | AI97: 16 | AJ97: 16 | AK97: 16 | AL97: 16 | AM97: 16 | AN97: 16 | AO97: 16 | AP97: 16 | AQ97: 16 | AR97: 16
B98: 6 | C98: Panglao | D98: LGU-run, BLGU-run, Richli, Balibago, Mactan Rock, Abejo | G98: 0 | H98: 0 | I98: 0 | J98: 0 | K98: 0 | L98: 0 | M98: 0 | N98: 0 | O98: 0 | P98: 0 | Q98: 0 | R98: 0 | S98: 0 | T98: 0 | U98: 0 | V98: 0 | W98: 0 | X98: 0 | Y98: 0 | Z98: 0 | AA98: 0 | AB98: 0 | AC98: 0 | AD98: 0 | AE98: 0 | AF98: 0 | AG98: 0 | AH98: 0 | AI98: 0 | AJ98: 0 | AK98: 0 | AL98: 0 | AM98: 0 | AN98: 0 | AO98: 0 | AP98: 0 | AQ98: 0 | AR98: 0
B99: 7 | C99: Sikatuna | D99: LGU-run | G99: 0 | H99: 0 | I99: 0 | J99: 0 | K99: 47 | L99: 47 | M99: 47 | N99: 47.47 | O99: 47.9447 | P99: 48.424147 | Q99: 48.908388 | R99: 49.397472 | S99: 49.891447 | T99: 50.390362 | U99: 50.894265 | V99: 51.403208 | W99: 51.91724 | X99: 52.436412 | Y99: 52.960776 | Z99: 53.490384 | AA99: 54.025288 | AB99: 54.565541 | AC99: 55.111196 | AD99: 55.662308 | AE99: 56.218931 | AF99: 56.781121 | AG99: 57.348932 | AH99: 57.922421 | AI99: 58.501645 | AJ99: 59.086662 | AK99: 59.677528 | AL99: 60.274304 | AM99: 60.877047 | AN99: 61.485817 | AO99: 62.100675 | AP99: 62.721682 | AQ99: 63.348899 | AR99: 63.982388
B100: 8 | C100: Tagbilaran City | D100: LGU-run, BWUI, Richli | G100: 0 | H100: 0 | I100: 0 | J100: 0 | K100: 11 | L100: 13 | M100: 13 | N100: 262.13 | O100: 262.2613 | P100: 262.39391 | Q100: 262.52785 | R100: 262.66313 | S100: 262.79976 | T100: 262.93776 | U100: 263.07714 | V100: 263.21791 | W100: 263.36009 | X100: 263.50369 | Y100: 263.64873 | Z100: 263.79521 | AA100: 263.94316 | AB100: 264.0926 | AC100: 264.24352 | AD100: 264.39596 | AE100: 264.54992 | AF100: 264.70542 | AG100: 264.86247 | AH100: 265.0211 | AI100: 265.18131 | AJ100: 265.34312 | AK100: 265.50655 | AL100: 265.67162 | AM100: 265.83833 | AN100: 266.00672 | AO100: 266.17678 | AP100: 266.34855 | AQ100: 266.52204 | AR100: 266.69726
C101: TOTAL | G101: 0 | H101: 0 | I101: 0 | J101: 0 | K101: 162.76744 | L101: 167 | M101: 167.245 | N101: 421.42122 | O101: 422.60798 | P101: 423.80537 | Q101: 425.01348 | R101: 426.23243 | S101: 427.46231 | T101: 428.70323 | U101: 429.95529 | V101: 431.2186 | W101: 432.49325 | X101: 433.77937 | Y101: 435.07705 | Z101: 436.38641 | AA101: 437.70756 | AB101: 439.0406 | AC101: 440.38565 | AD101: 441.74283 | AE101: 443.11225 | AF101: 444.49402 | AG101: 445.88826 | AH101: 447.29509 | AI101: 448.71462 | AJ101: 450.14699 | AK101: 451.59231 | AL101: 453.05069 | AM101: 454.52228 | AN101: 456.00718 | AO101: 457.50554 | AP101: 459.01746 | AQ101: 460.5431 | AR101: 462.08256
C103: TOTAL WSC (served by all)
C104: City/Municipality | D104: WSPs | G104: 2019 | H104: 2020 | I104: 2021 | J104: 2022 | K104: 2023 | L104: 45352 | M104: 2024 | N104: 2025 | O104: 2026 | P104: 2027 | Q104: 2028 | R104: 2029 | S104: 2030 | T104: 2031 | U104: 2032 | V104: 2033 | W104: 2034 | X104: 2035 | Y104: 2036 | Z104: 2037 | AA104: 2038 | AB104: 2039 | AC104: 2040 | AD104: 2041 | AE104: 2042 | AF104: 2043 | AG104: 2044 | AH104: 2045 | AI104: 2046 | AJ104: 2047 | AK104: 2048 | AL104: 2049 | AM104: 2050 | AN104: 2051 | AO104: 2052 | AP104: 2053 | AQ104: 2054 | AR104: 2055
K105: based on WSC of LGU waterworks | L105: based on WSC of LGU waterworks | M105: based on WSC of LGU waterworks | N105: assumed saturation of brgys served by the waterworks
G106: actual | H106: actual | I106: actual | J106: actual | K106: actual | L106: actual 3/24 | M106: annualized
B107: 1 | C107: Alburquerque | D107: LGU-run, BLGU-run | G107: 0 | H107: 0 | I107: 0 | J107: 0 | K107: 2211.7674 | L107: 2251 | M107: 2273.265 | N107: 3028.3639 | O107: 3074.7302 | P107: 3121.8269 | Q107: 3169.6657 | R107: 3218.2583 | S107: 3269.6359 | T107: 3318.0723 | U107: 3367.2347 | V107: 3417.1343 | W107: 3467.7822 | X107: 3518.4465 | Y107: 3565.1581 | Z107: 3612.494 | AA107: 3660.4623 | AB107: 3709.0717 | AC107: 3757.5301 | AD107: 3802.7242 | AE107: 3848.4653 | AF107: 3894.76 | AG107: 3941.6152 | AH107: 3989.0375 | AI107: 4037.0339 | AJ107: 4085.6113 | AK107: 4134.7768 | AL107: 4184.5376 | AM107: 4234.9008 | AN107: 4285.8739 | AO107: 4337.4641 | AP107: 4389.679 | AQ107: 4442.5262 | AR107: 4496.0133
B108: 2 | C108: Baclayon | D108: LGU-run, BWUI, BLGU-run | G108: 0 | H108: 0 | I108: 0 | J108: 0 | K108: 3826 | L108: 3826 | M108: 3826 | N108: 5573.8228 | O108: 5662.6175 | P108: 5752.8293 | Q108: 5844.4809 | R108: 5937.5952 | S108: 6032.1957 | T108: 6120.9479 | U108: 6211.0081 | V108: 6302.3956 | W108: 6395.1298 | X108: 6489.2307 | Y108: 6575.5492 | Z108: 6663.0175 | AA108: 6751.6509 | AB108: 6841.4651 | AC108: 6932.4757 | AD108: 7017.0813 | AE108: 7102.7208 | AF108: 7189.4068 | AG108: 7277.1521 | AH108: 7365.9696 | AI108: 7455.8725 | AJ108: 7546.8741 | AK108: 7638.9877 | AL108: 7732.2269 | AM108: 7826.6056 | AN108: 7922.1376 | AO108: 8018.837 | AP108: 8116.7181 | AQ108: 8215.7954 | AR108: 8316.0835
B109: 3 | C109: Corella | D109: LGU-run | G109: 0 | H109: 0 | I109: 0 | J109: 0 | K109: 2771 | L109: 2771 | M109: 2771 | N109: 3101.0665 | O109: 3143.8801 | P109: 3187.3378 | Q109: 3231.4498 | R109: 3276.2263 | S109: 3339.6553 | T109: 3401.4011 | U109: 3464.5871 | V109: 3529.2561 | W109: 3595.4522 | X109: 3644.4731 | Y109: 3690.2174 | Z109: 3736.543 | AA109: 3783.4574 | AB109: 3830.9683 | AC109: 3879.0832 | AD109: 3924.5205 | AE109: 3970.4934 | AF109: 4017.0084 | AG109: 4064.0717 | AH109: 4108.2383 | AI109: 4152.9147 | AJ109: 4198.1068 | AK109: 4243.8209 | AL109: 4290.063 | AM109: 4336.8395 | AN109: 4384.1567 | AO109: 4432.0211 | AP109: 4480.4391 | AQ109: 4529.4174 | AR109: 4578.9625
B110: 4 | C110: Dauis | D110: LGU-run, BLGU-run, Richli, Balibago, BWUI (bulk) | G110: 0 | H110: 0 | I110: 0 | J110: 0 | K110: 7091 | L110: 7091 | M110: 7091 | N110: 13093.884 | O110: 13266.88 | P110: 13442.625 | Q110: 13621.163 | R110: 13802.536 | S110: 13987.359 | T110: 14160.916 | U110: 14337.034 | V110: 14515.751 | W110: 14697.106 | X110: 14880.81 | Y110: 15049.498 | Z110: 15220.429 | AA110: 15407.465 | AB110: 15597.484 | AC110: 15789.667 | AD110: 15968.451 | AE110: 16149.412 | AF110: 16332.577 | AG110: 16527.801 | AH110: 16728.019 | AI110: 16930.676 | AJ110: 17135.801 | AK110: 17343.424 | AL110: 17553.576 | AM110: 17766.287 | AN110: 17981.59 | AO110: 18199.516 | AP110: 18420.096 | AQ110: 18643.363 | AR110: 18869.35
B111: 5 | C111: Loboc | D111: LGU-run, BLGU-run | G111: 0 | H111: 0 | I111: 0 | J111: 0 | K111: 1283.07 | L111: 1293.1407 | M111: 1298.1407 | N111: 4429.8145 | O111: 4497.9422 | P111: 4567.153 | Q111: 4637.4641 | R111: 4710.5608 | S111: 4784.8598 | T111: 4854.7989 | U111: 4925.8097 | V111: 4997.9092 | W111: 5070.1479 | X111: 5143.462 | Y111: 5210.9108 | Z111: 5279.2719 | AA111: 5348.5578 | AB111: 5417.7137 | AC111: 5487.7877 | AD111: 5553.4874 | AE111: 5620.9438 | AF111: 5689.2224 | AG111: 5758.3333 | AH111: 5828.2867 | AI111: 5899.0928 | AJ111: 5970.762 | AK111: 6043.3049 | AL111: 6116.7321 | AM111: 6191.0544 | AN111: 6266.2827 | AO111: 6342.428 | AP111: 6419.5016 | AQ111: 6497.5148 | AR111: 6576.479
B112: 6 | C112: Panglao | D112: LGU-run, BLGU-run, Richli, Balibago, Mactan Rock, Abejo | G112: 0 | H112: 0 | I112: 0 | J112: 0 | K112: 7629 | L112: 7895 | M112: 8028 | N112: 10891.13 | O112: 11017.576 | P112: 11144.921 | Q112: 11274.195 | R112: 11405.432 | S112: 11550.078 | T112: 11688.677 | U112: 11831.784 | V112: 11993.556 | W112: 12180.697 | X112: 12357.232 | Y112: 12523.436 | Z112: 12689.787 | AA112: 12860.316 | AB112: 13032.053 | AC112: 13200.364 | AD112: 13358.374 | AE112: 13517.137 | AF112: 13678.675 | AG112: 13840.009 | AH112: 14008.162 | AI112: 14176.154 | AJ112: 14346.009 | AK112: 14518.749 | AL112: 14693.397 | AM112: 14869.976 | AN112: 15050.509 | AO112: 15232.021 | AP112: 15420.156 | AQ112: 15615.247 | AR112: 15811.481
B113: 7 | C113: Sikatuna | D113: LGU-run | G113: 0 | H113: 0 | I113: 0 | J113: 0 | K113: 2043 | L113: 2126 | M113: 2128.75 | N113: 2156.3238 | O113: 2171.5932 | P113: 2189.4564 | Q113: 2207.5973 | R113: 2226.0204 | S113: 2247.1263 | T113: 2267.2874 | U113: 2294.3872 | V113: 2321.1914 | W113: 2348.4792 | X113: 2376.8029 | Y113: 2405.2619 | Z113: 2434.1116 | AA113: 2463.3577 | AB113: 2493.0054 | AC113: 2521.9876 | AD113: 2549.0586 | AE113: 2576.457 | AF113: 2604.1866 | AG113: 2632.2516 | AH113: 2660.6559 | AI113: 2691.6675 | AJ113: 2722.7223 | AK113: 2754.153 | AL113: 2787.6025 | AM113: 2821.2856 | AN113: 2855.3766 | AO113: 2889.8804 | AP113: 2924.8019 | AQ113: 2960.1463 | AR113: 2995.9186
B114: 8 | C114: Tagbilaran City | D114: LGU-run, BWUI, Richli | G114: 0 | H114: 0 | I114: 0 | J114: 0 | K114: 5867 | L114: 5857 | M114: 5873 | N114: 27401.922 | O114: 27814.992 | P114: 28234.709 | Q114: 28661.183 | R114: 29094.524 | S114: 29535.622 | T114: 29950.218 | U114: 30371.022 | V114: 30798.129 | W114: 31231.636 | X114: 31671.19 | Y114: 32075.416 | Z114: 32485.141 | AA114: 32900.442 | AB114: 33321.396 | AC114: 33747.587 | AD114: 34144.766 | AE114: 34546.937 | AF114: 34954.164 | AG114: 35366.515 | AH114: 35784.056 | AI114: 36206.857 | AJ114: 36634.986 | AK114: 37068.515 | AL114: 37507.514 | AM114: 37952.056 | AN114: 38402.216 | AO114: 38858.066 | AP114: 39319.684 | AQ114: 39787.146 | AR114: 40260.53
C115: TOTAL | G115: 0 | H115: 0 | I115: 0 | J115: 0 | K115: 32721.837 | L115: 33110.141 | M115: 33289.156 | N115: 69676.328 | O115: 70650.211 | P115: 71640.859 | Q115: 72647.199 | R115: 73671.153 | S115: 74746.532 | T115: 75762.319 | U115: 76802.867 | V115: 77875.323 | W115: 78986.431 | X115: 80081.646 | Y115: 81095.447 | Z115: 82120.794 | AA115: 83175.708 | AB115: 84243.158 | AC115: 85316.482 | AD115: 86318.463 | AE115: 87332.566 | AF115: 88360 | AG115: 89407.75 | AH115: 90472.425 | AI115: 91550.268 | AJ115: 92640.873 | AK115: 93745.731 | AL115: 94865.649 | AM115: 95999.006 | AN115: 97148.142 | AO115: 98310.233 | AP115: 99491.075 | AQ115: 100691.16 | AR115: 101904.82
S116: 373732.66 | AR116: 509524.09
C117: TOURIST COUNT-FOREIGN
C118: City/Municipality | D118: WSPs | G118: 2019 | H118: 2020 | I118: 2021 | J118: 2022 | K118: 2023 | L118: 45352 | M118: 2024 | N118: 2025 | O118: 2026 | P118: 2027 | Q118: 2028 | R118: 2029 | S118: 2030 | T118: 2031 | U118: 2032 | V118: 2033 | W118: 2034 | X118: 2035 | Y118: 2036 | Z118: 2037 | AA118: 2038 | AB118: 2039 | AC118: 2040 | AD118: 2041 | AE118: 2042 | AF118: 2043 | AG118: 2044 | AH118: 2045 | AI118: 2046 | AJ118: 2047 | AK118: 2048 | AL118: 2049 | AM118: 2050 | AN118: 2051 | AO118: 2052 | AP118: 2053 | AQ118: 2054 | AR118: 2055
B120: 1 | C120: Alburquerque | D120: LGU-run, BLGU-run | G120: 0 | H120: 0 | I120: 0 | J120: 0 | K120: 137 | L120: 0 | M120: 144.9323 | N120: 157.68634 | O120: 171.67491 | P120: 186.90442 | Q120: 203.48497 | R120: 221.53639 | S120: 241.18918 | T120: 262.5854 | U120: 285.87971 | V120: 311.24048 | W120: 338.85104 | X120: 368.91097 | Y120: 401.63756 | Z120: 437.26737 | AA120: 476.05795 | AB120: 518.28969 | AC120: 564.26787 | AD120: 614.32484 | AE120: 668.82242 | AF120: 728.15456 | AG120: 792.75013 | AH120: 863.07606 | AI120: 939.6407 | AJ120: 1022.9975 | AK120: 1113.749 | AL120: 1212.5512 | AM120: 1320.1182 | AN120: 1437.2277 | AO120: 1564.7261 | AP120: 1703.535 | AQ120: 1854.6579 | AR120: 2019.1871
...

Sheet Tagbilaran CAPEX&OPEX_realistic
B1: CAPEX
D2: Year 1 | E2: Year 2 | F2: Year 3 | G2: Year 4 | H2: Year 5 | I2: Year 6 | J2: Year 7 | K2: Year 8 | L2: Year 9 | M2: Year 10 | N2: Year 11 | O2: Year 12 | P2: Year 13 | Q2: Year 14 | R2: Year 15 | S2: Year 16 | T2: Year 17 | U2: Year 18 | V2: Year 19 | W2: Year 20 | X2: Year 21 | Y2: Year 22 | Z2: Year 23 | AA2: Year 24 | AB2: Year 25 | AC2: Year 26 | AD2: Year 27 | AE2: Year 28 | AF2: Year 29 | AG2: Year 30
B3: WATER SECURITY | D3: =SUM(D4:D12) -> 0 | E3: =SUM(E4:E12) -> 0 | F3: =SUM(F4:F12) -> 4411400 | G3: =SUM(G4:G12) -> 6617100 | H3: =SUM(H4:H12) -> 0 | I3: =SUM(I4:I12) -> 0 | J3: =SUM(J4:J12) -> 0 | K3: =SUM(K4:K12) -> 0 | ... AG3: =SUM(AG4:AG12) -> 0
B4: 1 | C4: Water Source Development
B5: 2 | C5: WTP and Facilities
B6: 3 | C6: ROW and Land Acquisition
B7: 4 | C7: Pump/Booster Stations
B8: 4.1 | C8: New Booster Stations | F8: ='[42]CAPEX dist Tagbilaran'!$G$29*0.4 -> 4411400 | G8: ='[42]CAPEX dist Tagbilaran'!$G$29*0.6 -> 6617100
B9: 4.2 | C9: New Pump Stations
B10: 5 | C10: New Well Development
B11: 6 | C11: Existing Wells Rehab Works
B12: 6.1 | C12: Well upkeep as reliability units (7 biggest well sources) | M12: =28*0.25*600000 -> 4200000
B13: SERVICE ACCESSIBILITY | D13: =SUM(D14:D51) -> 54332974 | E13: =SUM(E14:E51) -> 93140136 | F13: =SUM(F14:F51) -> 78341057 | G13: =SUM(G14:G51) -> 56634342 | H13: =SUM(H14:H51) -> 0 | I13: =SUM(I14:I51) -> 0 | J13: =SUM(J14:J51) -> 0 | K13: =SUM(K14:K51) -> 0 | ... AG13: =SUM(AG14:AG51) -> 0
B14: 1 | C14: New Lines
B15: 1.1 | C15: 400mm Main Line from Offtake | G15: ='[43]CAPEX dist Tagbilaran'!O42-6000000 -> 22267879 | M15: 6000000
B16: 1.2 | C16: 300mm Main Transmission line | F16: ='[43]CAPEX dist Tagbilaran'!$O$43*0.4-3000000 -> 11516745 | G16: ='[43]CAPEX dist Tagbilaran'!$O$43*0.6-6000000 -> 15775118 | M16: 9000000
B17: 1.3 | C17: 250mm Main Transmission Line | E17: ='[42]CAPEX dist Tagbilaran'!$G$44*0.3 -> 16294412 | F17: ='[42]CAPEX dist Tagbilaran'!$G$44*0.5-9000000 -> 18157353 | G17: ='[42]CAPEX dist Tagbilaran'!$G$44*0.2 -> 10862941 | M17: 9000000
B18: 1.4 | C18: 200mm Main distribution lines and mainline extensions | E18: ='[42]CAPEX dist Tagbilaran'!$G$45*0.4 -> 9817404.4 | F18: ='[42]CAPEX dist Tagbilaran'!$G$45*0.6 -> 14726107
B19: 2 | C19: Pipe Replacements/Reinforcements
B20: 2.1 | C20: 150mm distribution lines | E20: ='[42]CAPEX dist Tagbilaran'!$G$46 -> 7353388.2
B21: Target Areas | C21: Tiptip
C22: Manga
C23: Ubujan
B24: 2.2 | C24: 100mm distribution lines | D24: ='[42]CAPEX dist Tagbilaran'!$G$47*0.3 -> 14887327 | E24: ='[42]CAPEX dist Tagbilaran'!$G$47*0.4 -> 19849769 | F24: ='[42]CAPEX dist Tagbilaran'!$G$47*0.3 -> 14887327
C25: Tiptip
C26: Manga
C27: Ubujan
B28: 2.3 | C28: 75mm distribution lines | D28: ='[43]CAPEX dist Tagbilaran'!$H$48*0.4*0.7 -> 2817651.1 | E28: ='[43]CAPEX dist Tagbilaran'!$H$48*0.6*0.7 -> 4226476.6
C29: Tiptip
C30: Manga
C31: Ubujan
B32: 2.4 | C32: 50mm distribution lines | D32: ='[43]CAPEX dist Tagbilaran'!$H$49*0.3*0.6 -> 8962391.8 | E32: ='[43]CAPEX dist Tagbilaran'!$H$49*0.3*0.6 -> 8962391.8 | F32: ='[43]CAPEX dist Tagbilaran'!$H$49*0.3*0.6 -> 8962391.8 | G32: ='[43]CAPEX dist Tagbilaran'!$H$49*0.1*0.6 -> 2987463.9
C33: Tiptip
C34: Manga
C35: Ubujan
B36: 2.5 | C36: Pipe appurtenances | D36: =SUM('[43]CAPEX dist Tagbilaran'!$H$50:$H$51)/4 -> 1382390 | E36: =SUM('[43]CAPEX dist Tagbilaran'!$H$50:$H$51)/4 -> 1382390 | F36: =SUM('[43]CAPEX dist Tagbilaran'!$H$50:$H$51)/4 -> 1382390 | G36: =SUM('[43]CAPEX dist Tagbilaran'!$H$50:$H$51)/4 -> 1382390
B37: 2.6 | C37: Restoration works | D37: =SUM('[43]CAPEX dist Tagbilaran'!$H$52)*0.3 -> 4100721.6 | E37: =SUM('[43]CAPEX dist Tagbilaran'!$H$52)*0.4 -> 5467628.8 | F37: =SUM('[43]CAPEX dist Tagbilaran'!$H$52)*0.2 -> 2733814.4 | G37: =SUM('[43]CAPEX dist Tagbilaran'!$H$52)*0.1 -> 1366907.2
B38: 3 | C38: Expansion of Coverage
B39: 3.1 | C39: 75mm distribution lines | D39: ='[43]CAPEX dist Tagbilaran'!$H$48*0.4*0.3 -> 1207564.7 | E39: ='[43]CAPEX dist Tagbilaran'!$H$48*0.6*0.3 -> 1811347.1
C40: Cabawan
C41: San Isidro
B42: 3.2 | C42: 50mm distribution lines | D42: ='[43]CAPEX dist Tagbilaran'!$H$49*0.3*0.4 -> 5974927.9 | E42: ='[43]CAPEX dist Tagbilaran'!$H$49*0.3*0.4 -> 5974927.9 | F42: ='[43]CAPEX dist Tagbilaran'!$H$49*0.3*0.4 -> 5974927.9 | G42: ='[43]CAPEX dist Tagbilaran'!$H$49*0.1*0.4 -> 1991642.6
C43: Cabawan
C44: San Isidro
B45: 4 | C45: Reservoirs and Tanks
B46: 4.1 | C46: New Tanks | M46: =$C$98 -> 65036862
B47: 4.2 | C47: Rehab Works | D47: ='[42]CAPEX dist Tagbilaran'!G56 -> 6000000
B48: 5 | C48: NRW Reduction/Maintenance
B49: 5.1 | C49: Monitoring | D49: ='[42]CAPEX dist Tagbilaran'!G61 -> 6000000
B50: 5.2 | C50: DMA Formation | E50: =(8000/600)*900000 -> 12000000
B51: 5.3 | C51: Calibrated hydraulic model | D51: =3000000 -> 3000000
B52: SERVICE CONTINUITY | D52: =SUM(D53:D58) -> 60500036 | E52: =SUM(E53:E58) -> 55587536 | F52: =SUM(F53:F58) -> 55587536 | G52: =SUM(G53:G58) -> 0 | H52: =SUM(H53:H58) -> 0 | I52: =SUM(I53:I58) -> 0 | J52: =SUM(J53:J58) -> 0 | K52: =SUM(K53:K58) -> 0 | ... AG52: =SUM(AG53:AG58) -> 0
B53: 1 | C53: Meter Replacement | D53: ='[42]CAPEX dist Tagbilaran'!$G$70/3 -> 55587536 | E53: ='[42]CAPEX dist Tagbilaran'!$G$70/3 -> 55587536 | F53: ='[42]CAPEX dist Tagbilaran'!$G$70/3 -> 55587536
B54: 2 | C54: Lateral Lines/Interconnection of Lines
B55: 3 | C55: Extension of Lines
B56: 4 | C56: Asset Renewals
B57: 4.1 | C57: Replacement of pump and motors | D57: ='[42]CAPEX dist Tagbilaran'!G58 -> 4912500 | M57: =D57+'[42]CAPEX dist Tagbilaran'!G32 -> 5512500
B58: 5 | C58: Reliability projects | M58: =M57*0.6 -> 3307500
B59: EQUIPMENT AND OTHERS | D59: =SUM(D60:D63) -> 44018915 | E59: =SUM(E60:E63) -> 7948915.4 | F59: =SUM(F60:F63) -> 7948915.4 | G59: =SUM(G60:G63) -> 0 | H59: =SUM(H60:H63) -> 0 | I59: =SUM(I60:I63) -> 0 | J59: =SUM(J60:J63) -> 0 | K59: =SUM(K60:K63) -> 0 | ... AG59: =SUM(AG60:AG63) -> 0
B60: 1 | C60: Fleet Management | D60: ='[42]CAPEX dist Tagbilaran'!G66 -> 27000000
B61: 2 | C61: Automation | D61: ='[42]CAPEX dist Tagbilaran'!G68 -> 4070000 | M61: =12000000 -> 12000000
B62: 3 | C62: Temporary Facilities | D62: ='[42]CAPEX dist Tagbilaran'!G14 -> 5000000
B63: 4 | C63: Unplanned | D63: ='[42]CAPEX dist Tagbilaran'!$G$90/3 -> 7948915.4 | E63: ='[42]CAPEX dist Tagbilaran'!$G$90/3 -> 7948915.4 | F63: ='[42]CAPEX dist Tagbilaran'!$G$90/3 -> 7948915.4
B64: DED and Construction Supervision | D64: =D65 -> 6278956.2 | E64: =E65 -> 6278956.2 | F64: =F65 -> 6278956.2 | G64: =G65 -> 6278956.2 | H64: =H65 -> 0 | I64: =I65 -> 0 | J64: =J65 -> 0 | K64: =K65 -> 0 | ... AG64: =AG65 -> 0
D65: ='[42]CAPEX dist Tagbilaran'!$G$92/4 -> 6278956.2 | E65: ='[42]CAPEX dist Tagbilaran'!$G$92/4 -> 6278956.2 | F65: ='[42]CAPEX dist Tagbilaran'!$G$92/4 -> 6278956.2 | G65: ='[42]CAPEX dist Tagbilaran'!$G$92/4 -> 6278956.2
B66: CONTINGENCIES | D66: =SUM(D67) -> 0 | E66: =SUM(E67) -> 0 | F66: =SUM(F67) -> 0 | G66: =SUM(G67) -> 25115825 | H66: =SUM(H67) -> 0 | I66: =SUM(I67) -> 0 | J66: =SUM(J67) -> 0 | K66: =SUM(K67) -> 0 | ... AG66: =SUM(AG67) -> 0
C67: Physical Contingencies | G67: ='[42]CAPEX dist Tagbilaran'!G93 -> 25115825
B68: ENVIRONMENTAL CHARGES | D68: ='[42]CAPEX dist Tagbilaran'!G94 -> 3942285.4
B70: TOTAL | D70: =D3+D13+D52+D59+D64+D66+D68 -> 1.6907317e+08 | E70: =E3+E13+E52+E59+E64+E66+E68 -> 1.6295554e+08 | F70: =F3+F13+F52+F59+F64+F66+F68 -> 1.5256786e+08 | G70: =G3+G13+G52+G59+G64+G66+G68 -> 94646223 | H70: =H3+H13+H52+H59+H64+H66+H68 -> 0 | I70: =I3+I13+I52+I59+I64+I66+I68 -> 0 | J70: =J3+J13+J52+J59+J64+J66+J68 -> 0 | K70: =K3+K13+K52+K59+K64+K66+K68 -> 0 | ... AG70: =AG3+AG13+AG52+AG59+AG64+AG66+AG68 -> 0
B71: CUMULATIVE TOTAL | C71: =SUM(D70:G70) -> 5.792428e+08
B72: NPV | C72: =NPV(11%,D70:AG70) -> 4.9864831e+08
B73: Variance from original | C73: =(C71-'[43]CAPEX dist Tagbilaran'!H95)/'Tagbilaran CAPEX&OPEX_realistic'!C71 -> 0.039279501 | D73: including unit cost adjustment for HDPE
B75: Production Per year | H75: =([44]Tagbilaran!S590*1000000/1000)*365 -> 6689710.4 | I75: =([44]Tagbilaran!T590*1000000/1000)*365 -> 5685015.9 | J75: =([44]Tagbilaran!U590*1000000/1000)*365 -> 5753992.5 | K75: =([44]Tagbilaran!V590*1000000/1000)*365 -> 5824193.7 | L75: =([44]Tagbilaran!W590*1000000/1000)*365 -> 5895652.2 | M75: =([44]Tagbilaran!X590*1000000/1000)*365 -> 5967804.3 | N75: =([44]Tagbilaran!Y590*1000000/1000)*365 -> 6035096.4 | O75: =([44]Tagbilaran!Z590*1000000/1000)*365 -> 6103550.6 | ... AG75: =([44]Tagbilaran!AR590*1000000/1000)*365 -> 7001192.4
B76: OPEX | C76: Cost/m3 | D76: =D2 -> Year 1 | E76: =E2 -> Year 2 | F76: =F2 -> Year 3 | G76: =G2 -> Year 4 | H76: =H2 -> Year 5 | I76: =I2 -> Year 6 | J76: =J2 -> Year 7 | K76: =K2 -> Year 8 | ... AG76: =AG2 -> Year 30
B77: Power Cost | C77: 10.3 | D77: =$C77*D75 -> 0 | E77: =$C77*E75 -> 0 | F77: =$C77*F75 -> 0 | G77: =$C77*G75 -> 0 | H77: =$C77*H75 -> 68904017 | I77: =$C77*I75 -> 58555664 | J77: =$C77*J75 -> 59266123 | K77: =$C77*K75 -> 59989195 | ... AG77: =$C77*AG75 -> 72112282
B78: Treatment Cost | C78: 0.4 | D78: =$C78*D75 -> 0 | E78: =$C78*E75 -> 0 | F78: =$C78*F75 -> 0 | G78: =$C78*G75 -> 0 | H78: =$C78*H75 -> 2675884.2 | I78: =$C78*I75 -> 2274006.4 | J78: =$C78*J75 -> 2301597 | K78: =$C78*K75 -> 2329677.5 | ... AG78: =$C78*AG75 -> 2800477
B79: General and Admin | C79: 3 | D79: =$C79*D75 -> 0 | E79: =$C79*E75 -> 0 | F79: =$C79*F75 -> 0 | G79: =$C79*G75 -> 0 | H79: =$C79*H75 -> 20069131 | I79: =$C79*I75 -> 17055048 | J79: =$C79*J75 -> 17261978 | K79: =$C79*K75 -> 17472581 | ... AG79: =$C79*AG75 -> 21003577
B80: Fleet | C80: 0.3 | D80: =$C80*D75 -> 0 | E80: =$C80*E75 -> 0 | F80: =$C80*F75 -> 0 | G80: =$C80*G75 -> 0 | H80: =$C80*H75 -> 2006913.1 | I80: =$C80*I75 -> 1705504.8 | J80: =$C80*J75 -> 1726197.8 | K80: =$C80*K75 -> 1747258.1 | ... AG80: =$C80*AG75 -> 2100357.7
B81: Other Outside Services | C81: 0.9 | D81: =$C81*D75 -> 0 | E81: =$C81*E75 -> 0 | F81: =$C81*F75 -> 0 | G81: =$C81*G75 -> 0 | H81: =$C81*H75 -> 6020739.3 | I81: =$C81*I75 -> 5116514.3 | J81: =$C81*J75 -> 5178593.3 | K81: =$C81*K75 -> 5241774.3 | ... AG81: =$C81*AG75 -> 6301073.2
B82: CSR | C82: 0.25 | D82: =$C82*D75 -> 0 | E82: =$C82*E75 -> 0 | F82: =$C82*F75 -> 0 | G82: =$C82*G75 -> 0 | H82: =$C82*H75 -> 1672427.6 | I82: =$C82*I75 -> 1421254 | J82: =$C82*J75 -> 1438498.1 | K82: =$C82*K75 -> 1456048.4 | ... AG82: =$C82*AG75 -> 1750298.1
B83: Permits and licenses
B84: TOTAL | D84: =SUM(D77:D82) -> 0 | E84: =SUM(E77:E82) -> 0 | F84: =SUM(F77:F82) -> 0 | G84: =SUM(G77:G82) -> 0 | H84: =SUM(H77:H82) -> 1.0134911e+08 | I84: =SUM(I77:I82) -> 86127991 | J84: =SUM(J77:J82) -> 87172987 | K84: =SUM(K77:K82) -> 88236535 | ... AG84: =SUM(AG77:AG82) -> 1.0606807e+08
B86: Tanks at Injection points | C86: Capacity
B87: Uptown | C87: 750
B88: Dao | C88: =380+320 -> 700
B89: Bool | C89: 35
B90: Total | C90: =SUM(C87:C89) -> 1485
C92: m3
B93: Estimated Current tank capacity | C93: =C90 -> 1485
B94: 5th year demand, m3/day | C94: =[44]Tagbilaran!$S$590*1000000/1000 -> 18327.974
B95: 25% ADD | C95: =C94*0.25 -> 4581.9934
B96: Additional Storage Cap. Needed | C96: =C95-C93 -> 3096.9934
B97: Say 3000m3
B98: Cost | C98: =21000000*(C96/1000) -> 65036862

Sheet INPUT DATA  Assumptions
A1: TAGBILARAN CITY RURAL WATERWORKS
A2: ASSUMPTIONS
A3: SUPPLY AND DEMAND | B3: unit | C3: Construction Period (2026-2029) | D3: YR 1 (2030) | E3: YR 2 (2031) | F3: YR3 (2032) | G3: YR 4 (2033) | H3: YR 5 (2034) | I3: YR 6 (2035) | J3: YR 7 (2036) | K3: YR 8 (2037) | L3: YR 9 (2038) | M3: YR 10 (2039)
A4: Service Connections | B4: No. | D4: 10493 | E4: 10648 | F4: 10806 | G4: 10966 | H4: 11128 | I4: 11292 | J4: 11443 | K4: 11596 | L4: 11751 | M4: 11908
A5: DW, m3 | B5: m3 / yr | D5: 0 | E5: 0 | F5: 0 | G5: 0 | H5: 0 | I5: 0 | J5: 0 | K5: 0 | L5: 0 | M5: 0
A6: PWSP, m3 | B6: m3 / yr | D6: 8557477.5 | E6: 8621012.6 | F6: 8741461.2 | G6: 8865025.4 | H6: 8991863.3 | I6: 9122144.8 | J6: 9246266.7 | K6: 9373936.7 | L6: 9505360.8 | M6: 9640761.1
A7: BBWSP, m3 | B7: m3 / yr | D7: 6689710.4 | E7: 5685015.9 | F7: 5753992.5 | G7: 5824193.7 | H7: 5895652.2 | I7: 5967804.3 | J7: 6035096.4 | K7: 6103550.6 | L7: 6173202.1 | M7: 6244088.3
A9: CAPEX | B9: UNIT | C9: Construction Period (2026-2029) | D9: YR 1 (2030) | E9: YR 2 (2031) | F9: YR3 (2032) | G9: YR 4 (2033) | H9: YR 5 (2034) | I9: YR 6 (2035) | J9: YR 7 (2036) | K9: YR 8 (2037) | L9: YR 9 (2038) | M9: YR 10 (2039)
A10: Water Supply System | B10: Php | C10: ='Tagbilaran CAPEX&OPEX_realistic'!D70+'Tagbilaran CAPEX&OPEX_realistic'!E70+'Tagbilaran CAPEX&OPEX_realistic'!F70+'Tagbilaran CAPEX&OPEX_realistic'!G70 -> 5.792428e+08 | D10: ='Tagbilaran CAPEX&OPEX_realistic'!H70 -> 0 | E10: ='Tagbilaran CAPEX&OPEX_realistic'!I70 -> 0 | F10: ='Tagbilaran CAPEX&OPEX_realistic'!J70 -> 0 | G10: ='Tagbilaran CAPEX&OPEX_realistic'!K70 -> 0 | H10: ='Tagbilaran CAPEX&OPEX_realistic'!L70 -> 0 | I10: ='Tagbilaran CAPEX&OPEX_realistic'!M70 -> 1.1405686e+08 | J10: ='Tagbilaran CAPEX&OPEX_realistic'!N70 -> 0 | K10: ='Tagbilaran CAPEX&OPEX_realistic'!O70 -> 0 | ... M10: ='Tagbilaran CAPEX&OPEX_realistic'!Q70 -> 0
A11: Sanitation | B11: Php | D11: 0 | E11: 0 | F11: 0 | G11: 0 | H11: 0 | I11: 0 | J11: 0 | K11: 0 | L11: 0 | M11: 0
A13: OPEX (Water Supply System) | B13: UNIT | C13: Construction Period (2026-2029) | D13: YR 1 (2030) | E13: YR 2 (2031) | F13: YR3 (2032) | G13: YR 4 (2033) | H13: YR 5 (2034) | I13: YR 6 (2035) | J13: YR 7 (2036) | K13: YR 8 (2037) | L13: YR 9 (2038) | M13: YR 10 (2039)
A15: Inflation | B15: 0.05
A16: Staff (1:1000) - (No.) | B16: 250 | D16: =D4/$B$16 -> 41.972 | E16: =E4/$B$16 -> 42.592 | F16: =F4/$B$16 -> 43.224 | G16: =G4/$B$16 -> 43.864 | H16: =H4/$B$16 -> 44.512 | I16: =I4/$B$16 -> 45.168 | J16: =J4/$B$16 -> 45.772 | K16: =K4/$B$16 -> 46.384 | ... M16: =M4/$B$16 -> 47.632
A17: Average Salary per month - (Php) | B17: 19090 | D17: =B17 -> 19090 | E17: =D17*(1+$B$15) -> 20044.5 | F17: =E17*(1+$B$15) -> 21046.725 | G17: =F17*(1+$B$15) -> 22099.061 | H17: =G17*(1+$B$15) -> 23204.014 | I17: =H17*(1+$B$15) -> 24364.215 | J17: =I17*(1+$B$15) -> 25582.426 | K17: =J17*(1+$B$15) -> 26861.547 | L17: =K17*(1+$B$15) -> 28204.624 | M17: =L17*(1+$B$15) -> 29614.856
A18: Power cost / m3 produced - (Php) | B18: 13.13 | D18: =B18 -> 13.13 | E18: =D18*(1+$B$15) -> 13.7865 | F18: =E18*(1+$B$15) -> 14.475825 | G18: =F18*(1+$B$15) -> 15.199616 | H18: =G18*(1+$B$15) -> 15.959597 | I18: =H18*(1+$B$15) -> 16.757577 | J18: =I18*(1+$B$15) -> 17.595456 | K18: =J18*(1+$B$15) -> 18.475229 | L18: =K18*(1+$B$15) -> 19.39899 | M18: =L18*(1+$B$15) -> 20.368939
A19: Chemical Cost / m3 produced | B19: 0.5 | D19: =B19 -> 0.5 | E19: =D19*(1+$B$15) -> 0.525 | F19: =E19*(1+$B$15) -> 0.55125 | G19: =F19*(1+$B$15) -> 0.5788125 | H19: =G19*(1+$B$15) -> 0.60775313 | I19: =H19*(1+$B$15) -> 0.63814078 | J19: =I19*(1+$B$15) -> 0.67004782 | K19: =J19*(1+$B$15) -> 0.70355021 | L19: =K19*(1+$B$15) -> 0.73872772 | M19: =L19*(1+$B$15) -> 0.77566411
A20: Bulk Purchase (2030-2034) | B20: 19.85 | D20: =B20 -> 19.85 | E20: =D20 -> 19.85 | F20: =E20 -> 19.85 | G20: =F20 -> 19.85 | H20: =G20 -> 19.85
A21: Bulk Purchase (2035-2039) | B21: 25.8 | I21: =B21 -> 25.8 | J21: =I21 -> 25.8 | K21: =J21 -> 25.8 | L21: =K21 -> 25.8 | M21: =L21 -> 25.8
A22: Misc and Other O&M (% OF TOTAL OPEX) | B22: 0.05 | D22: =B22 -> 0.05 | E22: =D22 -> 0.05 | F22: =E22 -> 0.05 | G22: =F22 -> 0.05 | H22: =G22 -> 0.05 | I22: =H22 -> 0.05 | J22: =I22 -> 0.05 | K22: =J22 -> 0.05 | L22: =K22 -> 0.05 | M22: =L22 -> 0.05
A23: Service Fee (% OF TOTAL OPEX) | B23: 0.1 | D23: =B23 -> 0.1 | E23: =D23 -> 0.1 | F23: =E23 -> 0.1 | G23: =F23 -> 0.1 | H23: =G23 -> 0.1 | I23: =H23 -> 0.1 | J23: =I23 -> 0.1 | K23: =J23 -> 0.1 | L23: =K23 -> 0.1 | M23: =L23 -> 0.1
A24: Depreciation - Average Economic Life | B24: 25
A27: OPEX (SANITATION) | B27: UNIT | C27: Construction Period (2026-2029) | D27: YR 1 (2030) | E27: YR 2 (2031) | F27: YR3 (2032) | G27: YR 4 (2033) | H27: YR 5 (2034) | I27: YR 6 (2035) | J27: YR 7 (2036) | K27: YR 8 (2037) | L27: YR 9 (2038) | M27: YR 10 (2039)
A28: Salary (Php) | B28: 15000
A29: Staff (No.) | B29: 5
A30: Power cost / m3 - (Php) | B30: 10
A31: Chemical Cost / m3 - (Php) | B31: 5
A32: Misc and Other O&M | B32: 0.05
A33: Service Fee | B33: 0.1
A34: Depreciation - Average Economic Life | B34: 40
A37: LOAN AMORTIZATION
A38: TENOR: | B38: 1 | I38: 1
A39: Total Project Cost (Php) | B39: 0 | C39: =C10 -> 5.792428e+08 | I39: =I10 -> 1.1405686e+08
A40: Loan (%age) | B40: 0 | C40: =C39*B40 -> 0 | I40: 0
A41: Grant (%age) | B41: =B38-B40-B42 -> 1 | C41: =C39*B41 -> 5.792428e+08 | I41: =I38-I40-I42 -> 1
A42: Equity (%age) | B42: 0 | C42: =C39*B42 -> 0 | I42: 0
A43: Interest Rate | B43: 0.05 | I43: 0.05
A44: Repayment Period | B44: 30 | I44: 30
A46: RETURN ON INVESTMENT
A47: ROI (1-12%) | B47: 0 | I47: 0

Sheet OPEX
A1: OPERATIONAL EXPENDITURE (OPEX) & ANNUAL REQUIRED REVENUE (ARR)
A3: TAGBILARAN | D3: CONSTRCTN PRD | E3: year 1 | F3: year 2 | G3: year 3 | H3: year 4 | I3: year 5 | J3: year 6 | K3: year 7 | L3: year 8 | M3: year 9 | N3: year 10
D4: 2026-2029 | E4: 2030 | F4: =E4+1 -> 2031 | G4: =F4+1 -> 2032 | H4: =G4+1 -> 2033 | I4: =H4+1 -> 2034 | J4: =I4+1 -> 2035 | K4: =J4+1 -> 2036 | L4: =K4+1 -> 2037 | M4: =L4+1 -> 2038 | N4: =M4+1 -> 2039
B5: No. of Service Connection | E5: ='INPUT DATA Assumptions'!D4 -> 10493 | F5: ='INPUT DATA Assumptions'!E4 -> 10648 | G5: ='INPUT DATA Assumptions'!F4 -> 10806 | H5: ='INPUT DATA Assumptions'!G4 -> 10966 | I5: ='INPUT DATA Assumptions'!H4 -> 11128 | J5: ='INPUT DATA Assumptions'!I4 -> 11292 | K5: ='INPUT DATA Assumptions'!J4 -> 11443 | L5: ='INPUT DATA Assumptions'!K4 -> 11596 | ... N5: ='INPUT DATA Assumptions'!M4 -> 11908
B6: DW, m3 | E6: ='INPUT DATA Assumptions'!D5 -> 0 | F6: ='INPUT DATA Assumptions'!E5 -> 0 | G6: ='INPUT DATA Assumptions'!F5 -> 0 | H6: ='INPUT DATA Assumptions'!G5 -> 0 | I6: ='INPUT DATA Assumptions'!H5 -> 0 | J6: ='INPUT DATA Assumptions'!I5 -> 0 | K6: ='INPUT DATA Assumptions'!J5 -> 0 | L6: ='INPUT DATA Assumptions'!K5 -> 0 | ... N6: ='INPUT DATA Assumptions'!M5 -> 0
B7: PWSP, M3 | E7: ='INPUT DATA Assumptions'!D6 -> 8557477.5 | F7: ='INPUT DATA Assumptions'!E6 -> 8621012.6 | G7: ='INPUT DATA Assumptions'!F6 -> 8741461.2 | H7: ='INPUT DATA Assumptions'!G6 -> 8865025.4 | I7: ='INPUT DATA Assumptions'!H6 -> 8991863.3 | J7: ='INPUT DATA Assumptions'!I6 -> 9122144.8 | K7: ='INPUT DATA Assumptions'!J6 -> 9246266.7 | L7: ='INPUT DATA Assumptions'!K6 -> 9373936.7 | ... N7: ='INPUT DATA Assumptions'!M6 -> 9640761.1
B8: BBWSP, M3 | E8: ='INPUT DATA Assumptions'!D7 -> 6689710.4 | F8: ='INPUT DATA Assumptions'!E7 -> 5685015.9 | G8: ='INPUT DATA Assumptions'!F7 -> 5753992.5 | H8: ='INPUT DATA Assumptions'!G7 -> 5824193.7 | I8: ='INPUT DATA Assumptions'!H7 -> 5895652.2 | J8: ='INPUT DATA Assumptions'!I7 -> 5967804.3 | K8: ='INPUT DATA Assumptions'!J7 -> 6035096.4 | L8: ='INPUT DATA Assumptions'!K7 -> 6103550.6 | ... N8: ='INPUT DATA Assumptions'!M7 -> 6244088.3
A10: SALARIES | E10: =E11*E12*E13 -> 10416191 | F10: =F11*F12*F13 -> 11098559 | G10: =G11*G12*G13 -> 11826407 | H10: =H11*H12*H13 -> 12601592 | I10: =I11*I12*I13 -> 13427142 | J10: =J11*J12*J13 -> 14306277 | K10: =K11*K12*K13 -> 15222464 | L10: =L11*L12*L13 -> 16197298 | ... N10: =N11*N12*N13 -> 18337992
B11: Number of manpower | E11: ='INPUT DATA Assumptions'!D16 -> 41.972 | F11: ='INPUT DATA Assumptions'!E16 -> 42.592 | G11: ='INPUT DATA Assumptions'!F16 -> 43.224 | H11: ='INPUT DATA Assumptions'!G16 -> 43.864 | I11: ='INPUT DATA Assumptions'!H16 -> 44.512 | J11: ='INPUT DATA Assumptions'!I16 -> 45.168 | K11: ='INPUT DATA Assumptions'!J16 -> 45.772 | L11: ='INPUT DATA Assumptions'!K16 -> 46.384 | ... N11: ='INPUT DATA Assumptions'!M16 -> 47.632
B12: Average Salary | E12: ='INPUT DATA Assumptions'!D17 -> 19090 | F12: ='INPUT DATA Assumptions'!E17 -> 20044.5 | G12: ='INPUT DATA Assumptions'!F17 -> 21046.725 | H12: ='INPUT DATA Assumptions'!G17 -> 22099.061 | I12: ='INPUT DATA Assumptions'!H17 -> 23204.014 | J12: ='INPUT DATA Assumptions'!I17 -> 24364.215 | K12: ='INPUT DATA Assumptions'!J17 -> 25582.426 | L12: ='INPUT DATA Assumptions'!K17 -> 26861.547 | ... N12: ='INPUT DATA Assumptions'!M17 -> 29614.856
B13: 13 months | E13: 13 | F13: 13 | G13: 13 | H13: 13 | I13: 13 | J13: 13 | K13: 13 | L13: 13 | M13: 13 | N13: 13
A15: POWER Cost (Booster)+PWSP | E15: =E16*E17 -> 87835897 | F15: =F16*F17 -> 78376471 | G15: =G16*G17 -> 83293789 | H15: =H16*H17 -> 88525509 | I15: =I16*I17 -> 94092234 | J15: =J16*J17 -> 1.0000594e+08 | K15: =K16*K17 -> 1.0619027e+08 | L15: =L16*L17 -> 1.1276449e+08 | ... N15: =N16*N17 -> 1.2718546e+08
B16: Production in m3 | E16: =E8 -> 6689710.4 | F16: =F8 -> 5685015.9 | G16: =G8 -> 5753992.5 | H16: =H8 -> 5824193.7 | I16: =I8 -> 5895652.2 | J16: =J8 -> 5967804.3 | K16: =K8 -> 6035096.4 | L16: =L8 -> 6103550.6 | ... N16: =N8 -> 6244088.3
B17: Unit cost Php/M3 | E17: ='INPUT DATA Assumptions'!D18 -> 13.13 | F17: ='INPUT DATA Assumptions'!E18 -> 13.7865 | G17: ='INPUT DATA Assumptions'!F18 -> 14.475825 | H17: ='INPUT DATA Assumptions'!G18 -> 15.199616 | I17: ='INPUT DATA Assumptions'!H18 -> 15.959597 | J17: ='INPUT DATA Assumptions'!I18 -> 16.757577 | K17: ='INPUT DATA Assumptions'!J18 -> 17.595456 | L17: ='INPUT DATA Assumptions'!K18 -> 18.475229 | ... N17: ='INPUT DATA Assumptions'!M18 -> 20.368939
A19: CHEMICAL Cost | E19: =E20*E21 -> 0 | F19: =F20*F21 -> 0 | G19: =G20*G21 -> 0 | H19: =H20*H21 -> 0 | I19: =I20*I21 -> 0 | J19: =J20*J21 -> 0 | K19: =K20*K21 -> 0 | L19: =L20*L21 -> 0 | ... N19: =N20*N21 -> 0
B20: Production in m3 | D20: 0 | E20: =E6 -> 0 | F20: =F6 -> 0 | G20: =G6 -> 0 | H20: =H6 -> 0 | I20: =I6 -> 0 | J20: =J6 -> 0 | K20: =K6 -> 0 | L20: =L6 -> 0 | ... N20: =N6 -> 0
B21: Unit Cost Php/m3 | E21: ='INPUT DATA Assumptions'!D19 -> 0.5 | F21: ='INPUT DATA Assumptions'!E19 -> 0.525 | G21: ='INPUT DATA Assumptions'!F19 -> 0.55125 | H21: ='INPUT DATA Assumptions'!G19 -> 0.5788125 | I21: ='INPUT DATA Assumptions'!H19 -> 0.60775313 | J21: ='INPUT DATA Assumptions'!I19 -> 0.63814078 | K21: ='INPUT DATA Assumptions'!J19 -> 0.67004782 | L21: ='INPUT DATA Assumptions'!K19 -> 0.70355021 | ... N21: ='INPUT DATA Assumptions'!M19 -> 0.77566411
A23: BULK WATER PURCHASE | E23: =E24*E25 -> 1.3279075e+08 | F23: =F24*F25 -> 1.1284757e+08 | G23: =G24*G25 -> 1.1421675e+08 | H23: =H24*H25 -> 1.1561025e+08 | I23: =I24*I25 -> 1.170287e+08 | J23: =J24*J25 -> 1.5396935e+08 | K23: =K24*K25 -> 1.5570549e+08 | L23: =L24*L25 -> 1.574716e+08 | ... N23: =N24*N25 -> 1.6109748e+08
B24: BBWPS | D24: 0 | E24: =E8 -> 6689710.4 | F24: =F8 -> 5685015.9 | G24: =G8 -> 5753992.5 | H24: =H8 -> 5824193.7 | I24: =I8 -> 5895652.2 | J24: =J8 -> 5967804.3 | K24: =K8 -> 6035096.4 | L24: =L8 -> 6103550.6 | ... N24: =N8 -> 6244088.3
B25: Bulk Rate | E25: ='INPUT DATA Assumptions'!D20 -> 19.85 | F25: ='INPUT DATA Assumptions'!E20 -> 19.85 | G25: ='INPUT DATA Assumptions'!F20 -> 19.85 | H25: ='INPUT DATA Assumptions'!G20 -> 19.85 | I25: ='INPUT DATA Assumptions'!H20 -> 19.85 | J25: ='INPUT DATA Assumptions'!I21 -> 25.8 | K25: ='INPUT DATA Assumptions'!J21 -> 25.8 | L25: ='INPUT DATA Assumptions'!K21 -> 25.8 | M25: ='INPUT DATA Assumptions'!L21 -> 25.8 | N25: ='INPUT DATA Assumptions'!M21 -> 25.8
A27: MISC and Other O&M | E27: =E28*E29 -> 11552142 | F27: =F28*F29 -> 10116130 | G27: =G28*G29 -> 10466847 | H27: =H28*H29 -> 10836867 | I27: =I28*I29 -> 11227404 | J27: =J28*J29 -> 13414078 | K27: =K28*K29 -> 13855911 | L27: =L28*L29 -> 14321670 | ... N27: =N28*N29 -> 15331046
B28: Operational Expense | E28: =E10+E15+E19+E23 -> 2.3104284e+08 | F28: =F10+F15+F19+F23 -> 2.023226e+08 | G28: =G10+G15+G19+G23 -> 2.0933695e+08 | H28: =H10+H15+H19+H23 -> 2.1673735e+08 | I28: =I10+I15+I19+I23 -> 2.2454807e+08 | J28: =J10+J15+J19+J23 -> 2.6828157e+08 | K28: =K10+K15+K19+K23 -> 2.7711822e+08 | L28: =L10+L15+L19+L23 -> 2.8643339e+08 | ... N28: =N10+N15+N19+N23 -> 3.0662093e+08
E29: ='INPUT DATA Assumptions'!D22 -> 0.05 | F29: ='INPUT DATA Assumptions'!E22 -> 0.05 | G29: ='INPUT DATA Assumptions'!F22 -> 0.05 | H29: ='INPUT DATA Assumptions'!G22 -> 0.05 | I29: ='INPUT DATA Assumptions'!H22 -> 0.05 | J29: ='INPUT DATA Assumptions'!I22 -> 0.05 | K29: ='INPUT DATA Assumptions'!J22 -> 0.05 | L29: ='INPUT DATA Assumptions'!K22 -> 0.05 | ... N29: ='INPUT DATA Assumptions'!M22 -> 0.05
A31: SERVICE FEE | E31: =E32*E33 -> 24259498 | F31: =F32*F33 -> 21243873 | G31: =G32*G33 -> 21980380 | H31: =H32*H33 -> 22757421 | I31: =I32*I33 -> 23577548 | J31: =J32*J33 -> 28169565 | K31: =K32*K33 -> 29097413 | L31: =L32*L33 -> 30075506 | ... N31: =N32*N33 -> 32195197
B32: Operational Expense | E32: =E10+E15+E19+E23+E27 -> 2.4259498e+08 | F32: =F10+F15+F19+F23+F27 -> 2.1243873e+08 | G32: =G10+G15+G19+G23+G27 -> 2.198038e+08 | H32: =H10+H15+H19+H23+H27 -> 2.2757421e+08 | I32: =I10+I15+I19+I23+I27 -> 2.3577548e+08 | J32: =J10+J15+J19+J23+J27 -> 2.8169565e+08 | K32: =K10+K15+K19+K23+K27 -> 2.9097413e+08 | L32: =L10+L15+L19+L23+L27 -> 3.0075506e+08 | ... N32: =N10+N15+N19+N23+N27 -> 3.2195197e+08
E33: ='INPUT DATA Assumptions'!D23 -> 0.1 | F33: ='INPUT DATA Assumptions'!E23 -> 0.1 | G33: ='INPUT DATA Assumptions'!F23 -> 0.1 | H33: ='INPUT DATA Assumptions'!G23 -> 0.1 | I33: ='INPUT DATA Assumptions'!H23 -> 0.1 | J33: ='INPUT DATA Assumptions'!I23 -> 0.1 | K33: ='INPUT DATA Assumptions'!J23 -> 0.1 | L33: ='INPUT DATA Assumptions'!K23 -> 0.1 | ... N33: ='INPUT DATA Assumptions'!M23 -> 0.1
A35: TOTAL OPEX | E35: =E10+E15+E19+E23+E27+E31 -> 2.6685448e+08 | F35: =F10+F15+F19+F23+F27+F31 -> 2.336826e+08 | G35: =G10+G15+G19+G23+G27+G31 -> 2.4178418e+08 | H35: =H10+H15+H19+H23+H27+H31 -> 2.5033164e+08 | I35: =I10+I15+I19+I23+I27+I31 -> 2.5935302e+08 | J35: =J10+J15+J19+J23+J27+J31 -> 3.0986521e+08 | K35: =K10+K15+K19+K23+K27+K31 -> 3.2007155e+08 | L35: =L10+L15+L19+L23+L27+L31 -> 3.3083057e+08 | ... N35: =N10+N15+N19+N23+N27+N31 -> 3.5414717e+08
A37: 2-MONTHS WORKING CAPITAL | E37: =E35/12*2 -> 44475747 | F37: =F35/12*2 -> 38947100 | G37: =G35/12*2 -> 40297363 | H37: =H35/12*2 -> 41721939 | I37: =I35/12*2 -> 43225504 | J37: =J35/12*2 -> 51644202 | K37: =K35/12*2 -> 53345258 | L37: =L35/12*2 -> 55138428 | ... N37: =N35/12*2 -> 59024528
A39: ANNUAL DEPRECIATION | E39: ='DEPRCTN SCHED'!F35 -> 23169712 | F39: ='DEPRCTN SCHED'!G35 -> 23169712 | G39: ='DEPRCTN SCHED'!H35 -> 23169712 | H39: ='DEPRCTN SCHED'!I35 -> 23169712 | I39: ='DEPRCTN SCHED'!J35 -> 23169712 | J39: ='DEPRCTN SCHED'!K35 -> 27731986 | K39: ='DEPRCTN SCHED'!L35 -> 27731986 | L39: ='DEPRCTN SCHED'!M35 -> 27731986 | ... N39: ='DEPRCTN SCHED'!O35 -> 27731986
A42: AMORTIZATION / INTEREST EXPENSE | E42: ='AMORT SCHED'!C16 -> 0 | F42: ='AMORT SCHED'!D16 -> 0 | G42: ='AMORT SCHED'!E16 -> 0 | H42: ='AMORT SCHED'!F16 -> 0 | I42: ='AMORT SCHED'!G16 -> 0 | J42: ='AMORT SCHED'!H16 -> 0 | K42: ='AMORT SCHED'!I16 -> 0 | L42: ='AMORT SCHED'!J16 -> 0 | ... N42: ='AMORT SCHED'!L16 -> 0
A45: ALLOWABLE RETURN ON INVESTMENT | E45: ='TARIFF CALC'!D18 -> 0 | F45: ='TARIFF CALC'!E18 -> 0 | G45: ='TARIFF CALC'!F18 -> 0 | H45: ='TARIFF CALC'!G18 -> 0 | I45: ='TARIFF CALC'!H18 -> 0 | J45: ='TARIFF CALC'!K18 -> 0 | K45: ='TARIFF CALC'!L18 -> 0 | L45: ='TARIFF CALC'!M18 -> 0 | M45: ='TARIFF CALC'!N18 -> 0 | N45: ='TARIFF CALC'!O18 -> 0
A48: TOTAL ANNUAL REQUIRED REVENUE | E48: =E35+E37+E39+E42+E45 -> 3.3449994e+08 | F48: =F35+F37+F39+F42+F45 -> 2.9579941e+08 | G48: =G35+G37+G39+G42+G45 -> 3.0525125e+08 | H48: =H35+H37+H39+H42+H45 -> 3.1522329e+08 | I48: =I35+I37+I39+I42+I45 -> 3.2574824e+08 | J48: =J35+J37+J39+J42+J45 -> 3.892414e+08 | K48: =K35+K37+K39+K42+K45 -> 4.0114879e+08 | L48: =L35+L37+L39+L42+L45 -> 4.1370098e+08 | ... N48: =N35+N37+N39+N42+N45 -> 4.4090368e+08

Sheet DEPRCTN SCHED
A1: TAGBILARAN WATER WORKS
A2: Economic Life | B2: ='INPUT DATA Assumptions'!B24 -> 25
A4: Annual Depreciation | B4: Construction Period (2026-2029) | F4: Year 1 (2030) | G4: Year 2 | H4: Year 3 | I4: Year 4 | J4: Year 5 | K4: Year 6 | L4: Year 7 | M4: Year 8 | N4: Year 9 | O4: Year 10
A5: 2026 | B5: =B37/B2 -> 6762926.7 | C5: =B5 -> 6762926.7 | D5: =C5 -> 6762926.7 | E5: =D5 -> 6762926.7 | F5: =E5 -> 6762926.7 | G5: =F5 -> 6762926.7 | H5: =G5 -> 6762926.7 | I5: =H5 -> 6762926.7 | J5: =I5 -> 6762926.7 | ... O5: =N5 -> 6762926.7
A6: 2027 | C6: =C37/B2 -> 6518221.8 | D6: =C6 -> 6518221.8 | E6: =D6 -> 6518221.8 | F6: =E6 -> 6518221.8 | G6: =F6 -> 6518221.8 | H6: =G6 -> 6518221.8 | I6: =H6 -> 6518221.8 | J6: =I6 -> 6518221.8 | K6: =J6 -> 6518221.8 | ... O6: =N6 -> 6518221.8
A7: 2028 | D7: =D37/B2 -> 6102714.6 | E7: =D7 -> 6102714.6 | F7: =E7 -> 6102714.6 | G7: =F7 -> 6102714.6 | H7: =G7 -> 6102714.6 | I7: =H7 -> 6102714.6 | J7: =I7 -> 6102714.6 | K7: =J7 -> 6102714.6 | L7: =K7 -> 6102714.6 | ... O7: =N7 -> 6102714.6
A8: 2029 | E8: =E37/B2 -> 3785848.9 | F8: =E8 -> 3785848.9 | G8: =F8 -> 3785848.9 | H8: =G8 -> 3785848.9 | I8: =H8 -> 3785848.9 | J8: =I8 -> 3785848.9 | K8: =J8 -> 3785848.9 | L8: =K8 -> 3785848.9 | M8: =L8 -> 3785848.9 | ... O8: =N8 -> 3785848.9
A9: 2030 | F9: =F37/B2 -> 0 | G9: =F9 -> 0 | H9: =G9 -> 0 | I9: =H9 -> 0 | J9: =I9 -> 0 | K9: =J9 -> 0 | L9: =K9 -> 0 | M9: =L9 -> 0 | N9: =M9 -> 0 | O9: =N9 -> 0
A10: 2031 | G10: =G37/B2 -> 0 | H10: =G10 -> 0 | I10: =H10 -> 0 | J10: =I10 -> 0 | K10: =J10 -> 0 | L10: =K10 -> 0 | M10: =L10 -> 0 | N10: =M10 -> 0 | O10: =N10 -> 0
A11: 2032 | H11: =H37/B2 -> 0 | I11: =H11 -> 0 | J11: =I11 -> 0 | K11: =J11 -> 0 | L11: =K11 -> 0 | M11: =L11 -> 0 | N11: =M11 -> 0 | O11: =N11 -> 0
A12: 2033 | J12: =J37/B2 -> 0 | K12: =J12 -> 0 | L12: =K12 -> 0 | M12: =L12 -> 0 | N12: =M12 -> 0 | O12: =N12 -> 0
A13: 2034 | K13: =K37/B2 -> 4562274.5 | L13: =K13 -> 4562274.5 | M13: =L13 -> 4562274.5 | N13: =M13 -> 4562274.5 | O13: =N13 -> 4562274.5
A14: 2035 | L14: =L37/B2 -> 0 | M14: =L14 -> 0 | N14: =M14 -> 0 | O14: =N14 -> 0
A15: 2036 | M15: =M37/B2 -> 0 | N15: =M15 -> 0 | O15: =N15 -> 0
A16: 2037 | N16: =N37/B2 -> 0 | O16: =N16 -> 0
A17: 2038 | O17: =O37/B2 -> 0
A18: 2039
A19: 2040
A20: 2041
A21: 2042
A22: 2043
A23: 2044
A24: 2045
A25: 2046
A26: 2047
A27: 2048
A28: 2049
A29: 2050
... A34: 2055
A35: Annual Depreciation | B35: =SUM(B5:B34) -> 6762926.7 | C35: =SUM(C5:C34) -> 13281148 | D35: =SUM(D5:D34) -> 19383863 | E35: =SUM(E5:E34) -> 23169712 | F35: =SUM(F5:F34) -> 23169712 | G35: =SUM(G5:G34) -> 23169712 | H35: =SUM(H5:H34) -> 23169712 | I35: =SUM(I5:I34) -> 23169712 | ... O35: =SUM(O5:O34) -> 27731986
A36: Accumulated Depreciation | B36: =B35 -> 6762926.7 | C36: =B36+C35 -> 20044075 | D36: =C36+D35 -> 39427938 | E36: =D36+E35 -> 62597650 | F36: =E36+F35 -> 85767362 | G36: =F36+G35 -> 1.0893707e+08 | H36: =G36+H35 -> 1.3210679e+08 | I36: =H36+I35 -> 1.552765e+08 | J36: =I36+J35 -> 1.7844621e+08 | ... O36: =N36+O35 -> 3.1710614e+08
A37: PPE | B37: ='Tagbilaran CAPEX&OPEX_realistic'!D70 -> 1.6907317e+08 | C37: ='Tagbilaran CAPEX&OPEX_realistic'!E70 -> 1.6295554e+08 | D37: ='Tagbilaran CAPEX&OPEX_realistic'!F70 -> 1.5256786e+08 | E37: ='Tagbilaran CAPEX&OPEX_realistic'!G70 -> 94646223 | F37: ='Tagbilaran CAPEX&OPEX_realistic'!H70 -> 0 | G37: ='Tagbilaran CAPEX&OPEX_realistic'!I70 -> 0 | H37: ='Tagbilaran CAPEX&OPEX_realistic'!J70 -> 0 | I37: ='Tagbilaran CAPEX&OPEX_realistic'!K70 -> 0 | ... O37: ='Tagbilaran CAPEX&OPEX_realistic'!Q70 -> 0
A38: Net Book Value | B38: =B37-B36 -> 1.6231024e+08 | C38: =B37+C37-C36 -> 3.1198464e+08 | D38: =SUM(B37:D37)-D36 -> 4.4516864e+08 | E38: =SUM(B37:E37)-E36 -> 5.1664515e+08 | F38: =SUM(B37:F37)-F36 -> 4.9347544e+08 | G38: =SUM(B37:G37)-G36 -> 4.7030572e+08 | H38: =SUM(B37:H37)-H36 -> 4.4713601e+08 | I38: =SUM(B37:I37)-I36 -> 4.239663e+08 | J38: =SUM(B37:J37)-J36 -> 4.0079659e+08 | K38: =SUM(B37:K37)-K36 -> 4.8712146e+08 | L38: =SUM(B37:L37)-L36 -> 4.5938948e+08 | M38: =SUM(B37:M37)-M36 -> 4.3165749e+08 | N38: =SUM(B37:N37)-N36 -> 4.0392551e+08 | O38: =SUM(B37:O37)-O36 -> 3.7619352e+08

Sheet AMORT SCHED
A1: TAGBILARAN WATER WORKS
B3: CONSTRUCTION PERIOD (2026-2029) | C3: YEAR 1 (2030) | D3: YEAR 2 (2031) | E3: YEAR 3 (2032) | F3: YEAR 4 (2033) | G3: YEAR 5 (2034) | H3: YEAR 6 (2035) | I3: YEAR 7 (2036) | J3: YEAR 8 (2037) | K3: YEAR 9 (2038) | L3: YEAR 10 (2039)
A4: CAPEX | B4: ='INPUT DATA Assumptions'!C10 -> 5.792428e+08 | C4: ='INPUT DATA Assumptions'!D10 -> 0 | D4: ='INPUT DATA Assumptions'!E10 -> 0 | E4: ='INPUT DATA Assumptions'!F10 -> 0 | F4: ='INPUT DATA Assumptions'!G10 -> 0 | G4: ='INPUT DATA Assumptions'!H10 -> 0 | H4: ='INPUT DATA Assumptions'!I10 -> 1.1405686e+08 | I4: ='INPUT DATA Assumptions'!J10 -> 0 | ... L4: ='INPUT DATA Assumptions'!M10 -> 0
A5: Tenor:
A6: Loan | B6: ='INPUT DATA Assumptions'!B40 -> 0 | C6: 0 | D6: 0 | E6: 0 | F6: 0 | G6: 0 | H6: ='INPUT DATA Assumptions'!I40 -> 0 | I6: 0 | J6: 0 | K6: 0 | L6: 0
A7: Grant | B7: ='INPUT DATA Assumptions'!B41 -> 1 | C7: 0 | D7: 0 | E7: 0 | F7: 0 | G7: 0 | H7: ='INPUT DATA Assumptions'!I41 -> 1 | I7: 0 | J7: 0 | K7: 0 | L7: 0
A8: Equity | B8: ='INPUT DATA Assumptions'!B42 -> 0 | C8: 0 | D8: 0 | E8: 0 | F8: 0 | G8: 0 | H8: ='INPUT DATA Assumptions'!I42 -> 0 | I8: 0 | J8: 0 | K8: 0 | L8: ='[45]TARIFF CALC'!P7 -> 0
A9: Interest Rate | B9: ='INPUT DATA Assumptions'!B43 -> 0.05 | C9: 0 | D9: ='[45]TARIFF CALC'!E9 -> 0 | E9: ='[45]TARIFF CALC'!F9 -> 0 | F9: ='[45]TARIFF CALC'!G9 -> 0 | G9: 0 | H9: ='INPUT DATA Assumptions'!I43 -> 0.05 | I9: 0 | J9: ='[45]TARIFF CALC'!N9 -> 0 | K9: 0 | L9: ='[45]TARIFF CALC'!P9 -> 0
A10: Repayment Period | B10: ='INPUT DATA Assumptions'!B44 -> 30 | C10: ='[45]TARIFF CALC'!D10 -> 0 | D10: ='[45]TARIFF CALC'!E10 -> 0 | E10: ='[45]TARIFF CALC'!F10 -> 0 | F10: ='[45]TARIFF CALC'!G10 -> 0 | G10: ='[45]TARIFF CALC'!H10 -> 0 | H10: ='INPUT DATA Assumptions'!I44 -> 30 | I10: 0 | J10: ='[45]TARIFF CALC'!N10 -> 0 | K10: ='[45]TARIFF CALC'!O10 -> 0 | L10: ='[45]TARIFF CALC'!P10 -> 0
A13: Loan 1 (Year2) | B13: CONSTRUCTION PERIOD (2026-2029) | C13: YEAR 1 (2030) | D13: YEAR 2 (2031) | E13: YEAR 3 (2032) | F13: YEAR 4 (2033) | G13: YEAR 5 (2034) | H13: YEAR 6 (2035) | I13: YEAR 7 (2036) | J13: YEAR 8 (2037) | K13: YEAR 9 (2038) | L13: YEAR 10 (2039)
A14: Loan | B14: =B4*B6 -> 0 | C14: =C4*C6 -> 0 | D14: =D4*D6 -> 0 | E14: 0 | F14: 0 | H14: =H4*H6 -> 0
A15: TOTAL Loan | B15: =B14 -> 0 | C15: =B15+C14 -> 0 | D15: =C15+D14 -> 0 | E15: 0 | F15: =E15+F14 -> 0 | H15: =H14 -> 0
A16: Interest Expense | B16: =B15*B9 -> 0 | C16: =B19*B9 -> 0 | D16: =C19*B9 -> 0 | E16: =D19*B9 -> 0 | F16: =E19*B9 -> 0 | G16: =F19*B9 -> 0 | H16: =H15*H9 -> 0 | I16: =H19*H9 -> 0 | J16: =I19*H9 -> 0 | K16: =J19*H9 -> 0 | L16: =K19*H9 -> 0
A17: Principal Repayment | B17: =B18-B16 -> 0 | C17: =C18-C16 -> 0 | D17: =D18-D16 -> 0 | E17: =E18-E16 -> 0 | F17: =F18-F16 -> 0 | G17: =G18-G16 -> 0 | H17: =H18-H16 -> 0 | I17: =I18-I16 -> 0 | ... L17: =L18-L16 -> 0
A18: Debt Service | B18: =-PMT(B9,B10,B15) -> 0 | C18: =B18 -> 0 | D18: =C18 -> 0 | E18: =D18 -> 0 | F18: =E18 -> 0 | G18: =F18 -> 0 | H18: =-PMT(H9,H10,H15) -> 0 | I18: =H18 -> 0 | J18: =I18 -> 0 | K18: =J18 -> 0 | L18: =K18 -> 0
A19: Outstanding Loan | B19: =B15-B17 -> 0 | C19: =B19-C17 -> 0 | D19: =D15-D17 -> 0 | E19: =D19-E17 -> 0 | F19: =E19-F17 -> 0 | G19: =F19-G17 -> 0 | H19: =H15-H17 -> 0 | I19: =H19-I17 -> 0 | J19: =I19-J17 -> 0 | K19: =J19-K17 -> 0 | L19: =K19-L17 -> 0

Sheet TARIFF CALC
A1: TAGBILARAN WATERWORKS
B2: 1st Regulatory Period (1RP)
A3: ASSUMPTIONS | C3: CONSTRUCTION PERIOD (2026-2029) | D3: YEAR 1 (2030) | E3: YEAR 2 (2031) | F3: YEAR 3 (2032) | G3: YEAR 4 (2033) | H3: YEAR 5 (2034) | K3: YEAR 6 (2035) | L3: YEAR 7 (2036) | M3: YEAR 8 (2037) | N3: YEAR 9 (2038) | O3: YEAR 10 (2039)
A5: Property and Equipment, Beg, | C5: =C6 -> 5.792428e+08 | D5: =C6+D6 -> 5.792428e+08 | E5: =D5+E6 -> 5.792428e+08 | F5: =E5+F6 -> 5.792428e+08 | G5: =F5+G6 -> 5.792428e+08 | H5: =G5+H6 -> 5.792428e+08 | K5: =H5+K6 -> 6.9329966e+08 | L5: =K5+L6 -> 6.9329966e+08 | M5: =L5+M6 -> 6.9329966e+08 | N5: =M5+N6 -> 6.9329966e+08 | O5: =N5+O6 -> 6.9329966e+08
A6: New Investment | C6: ='INPUT DATA Assumptions'!C10 -> 5.792428e+08 | D6: ='INPUT DATA Assumptions'!D10 -> 0 | E6: ='INPUT DATA Assumptions'!E10 -> 0 | F6: ='INPUT DATA Assumptions'!F10 -> 0 | G6: ='INPUT DATA Assumptions'!G10 -> 0 | H6: ='INPUT DATA Assumptions'!H10 -> 0 | K6: ='INPUT DATA Assumptions'!I10 -> 1.1405686e+08 | L6: ='INPUT DATA Assumptions'!J10 -> 0 | M6: ='INPUT DATA Assumptions'!K10 -> 0 | N6: ='INPUT DATA Assumptions'!L10 -> 0 | O6: ='INPUT DATA Assumptions'!M10 -> 0
A7: Annual Acc Depreciation | C7: ='DEPRCTN SCHED'!E36 -> 62597650 | D7: ='DEPRCTN SCHED'!F36 -> 85767362 | E7: ='DEPRCTN SCHED'!G36 -> 1.0893707e+08 | F7: ='DEPRCTN SCHED'!H36 -> 1.3210679e+08 | G7: ='DEPRCTN SCHED'!I36 -> 1.552765e+08 | H7: ='DEPRCTN SCHED'!J36 -> 1.7844621e+08 | K7: ='DEPRCTN SCHED'!K36 -> 2.061782e+08 | L7: ='DEPRCTN SCHED'!L36 -> 2.3391018e+08 | M7: ='DEPRCTN SCHED'!M36 -> 2.6164217e+08 | N7: ='DEPRCTN SCHED'!N36 -> 2.8937416e+08 | O7: ='DEPRCTN SCHED'!O36 -> 3.1710614e+08
A8: NET BOOK VALUE | C8: =C5-C7 -> 5.1664515e+08 | D8: =D5-D7 -> 4.9347544e+08 | E8: =E5-E7 -> 4.7030572e+08 | F8: =F5-F7 -> 4.4713601e+08 | G8: =G5-G7 -> 4.239663e+08 | H8: =H5-H7 -> 4.0079659e+08 | K8: =K5-K7 -> 4.8712146e+08 | L8: =L5-L7 -> 4.5938948e+08 | M8: =M5-M7 -> 4.3165749e+08 | N8: =N5-N7 -> 4.0392551e+08 | O8: =O5-O7 -> 3.7619352e+08
A10: ADD: Working Capital
A11: OPEX | D11: =OPEX!E35 -> 2.6685448e+08 | E11: =OPEX!F35 -> 2.336826e+08 | F11: =OPEX!G35 -> 2.4178418e+08 | G11: =OPEX!H35 -> 2.5033164e+08 | H11: =OPEX!I35 -> 2.5935302e+08 | K11: =OPEX!J35 -> 3.0986521e+08 | L11: =OPEX!K35 -> 3.2007155e+08 | M11: =OPEX!L35 -> 3.3083057e+08 | N11: =OPEX!M35 -> 3.4217682e+08 | O11: =OPEX!N35 -> 3.5414717e+08
A12: AMORTIZATION (Interest Expense) | D12: =OPEX!E42 -> 0 | E12: =OPEX!F42 -> 0 | F12: =OPEX!G42 -> 0 | G12: =OPEX!H42 -> 0 | H12: =OPEX!I42 -> 0 | K12: =OPEX!J42 -> 0 | L12: =OPEX!K42 -> 0 | M12: =OPEX!L42 -> 0 | N12: =OPEX!M42 -> 0 | O12: =OPEX!N42 -> 0
A13: DEPRECIATION | D13: =OPEX!E39 -> 23169712 | E13: =OPEX!F39 -> 23169712 | F13: =OPEX!G39 -> 23169712 | G13: =OPEX!H39 -> 23169712 | H13: =OPEX!I39 -> 23169712 | K13: =OPEX!J39 -> 27731986 | L13: =OPEX!K39 -> 27731986 | M13: =OPEX!L39 -> 27731986 | N13: =OPEX!M39 -> 27731986 | O13: =OPEX!N39 -> 27731986
A14: 2-months WORKING CAPITAL | D14: =OPEX!E37 -> 44475747 | E14: =OPEX!F37 -> 38947100 | F14: =OPEX!G37 -> 40297363 | G14: =OPEX!H37 -> 41721939 | H14: =OPEX!I37 -> 43225504 | K14: =OPEX!J37 -> 51644202 | L14: =OPEX!K37 -> 53345258 | M14: =OPEX!L37 -> 55138428 | N14: =OPEX!M37 -> 57029471 | O14: =OPEX!N37 -> 59024528
A15: EQUITY | D15: ='INPUT DATA Assumptions'!C39*'INPUT DATA Assumptions'!B42 -> 0 | E15: ='INPUT DATA Assumptions'!D39*'INPUT DATA Assumptions'!C42 -> 0 | F15: ='INPUT DATA Assumptions'!E39*'INPUT DATA Assumptions'!D42 -> 0 | G15: ='INPUT DATA Assumptions'!F39*'INPUT DATA Assumptions'!E42 -> 0 | H15: ='INPUT DATA Assumptions'!G39*'INPUT DATA Assumptions'!F42 -> 0 | K15: ='INPUT DATA Assumptions'!I39*'INPUT DATA Assumptions'!I42 -> 0 | L15: =K15 -> 0 | M15: =L15 -> 0 | N15: =M15 -> 0 | O15: =N15 -> 0
A16: TOTAL ANNUAL REQUIRED REVENUE | C16: 0 | D16: =SUM(D11:D15) -> 3.3449994e+08 | E16: =SUM(E11:E15) -> 2.9579941e+08 | F16: =SUM(F11:F15) -> 3.0525125e+08 | G16: =SUM(G11:G15) -> 3.1522329e+08 | H16: =SUM(H11:H15) -> 3.2574824e+08 | K16: =SUM(K11:K15) -> 3.892414e+08 | L16: =SUM(L11:L15) -> 4.0114879e+08 | M16: =SUM(M11:M15) -> 4.1370098e+08 | N16: =SUM(N11:N15) -> 4.2693828e+08 | O16: =SUM(O11:O15) -> 4.4090368e+08
A18: MAXIMUN ALLOWABLE ROI | C18: 0 | D18: =D8*'INPUT DATA Assumptions'!$B$47 -> 0 | E18: =E8*'INPUT DATA Assumptions'!$B$47 -> 0 | F18: =F8*'INPUT DATA Assumptions'!$B$47 -> 0 | G18: =G8*'INPUT DATA Assumptions'!$B$47 -> 0 | H18: =H8*'INPUT DATA Assumptions'!$B$47 -> 0 | K18: =K8*'INPUT DATA Assumptions'!$I$47 -> 0 | L18: =L8*'INPUT DATA Assumptions'!$I$47 -> 0 | M18: =M8*'INPUT DATA Assumptions'!$I$47 -> 0 | N18: =N8*'INPUT DATA Assumptions'!$I$47 -> 0 | O18: =O8*'INPUT DATA Assumptions'!$I$47 -> 0
A19: MAXIMUM ALLOWABLE REVENUE | C19: =C16+C18 -> 0 | D19: =D16+D18 -> 3.3449994e+08 | E19: =E16+E18 -> 2.9579941e+08 | F19: =F16+F18 -> 3.0525125e+08 | G19: =G16+G18 -> 3.1522329e+08 | H19: =H16+H18 -> 3.2574824e+08 | K19: =K16+K18 -> 3.892414e+08 | L19: =L16+L18 -> 4.0114879e+08 | M19: =M16+M18 -> 4.1370098e+08 | N19: =N16+N18 -> 4.2693828e+08 | O19: =O16+O18 -> 4.4090368e+08
A21: VOLUME SOLD M3 | D21: ='INPUT DATA Assumptions'!D5+'INPUT DATA Assumptions'!D6+'INPUT DATA Assumptions'!D7 -> 15247188 | E21: ='INPUT DATA Assumptions'!E5+'INPUT DATA Assumptions'!E6+'INPUT DATA Assumptions'!E7 -> 14306028 | F21: ='INPUT DATA Assumptions'!F5+'INPUT DATA Assumptions'!F6+'INPUT DATA Assumptions'!F7 -> 14495454 | G21: ='INPUT DATA Assumptions'!G5+'INPUT DATA Assumptions'!G6+'INPUT DATA Assumptions'!G7 -> 14689219 | H21: ='INPUT DATA Assumptions'!H5+'INPUT DATA Assumptions'!H6+'INPUT DATA Assumptions'!H7 -> 14887516 | K21: ='INPUT DATA Assumptions'!I5+'INPUT DATA Assumptions'!I6+'INPUT DATA Assumptions'!I7 -> 15089949 | L21: ='INPUT DATA Assumptions'!J5+'INPUT DATA Assumptions'!J6+'INPUT DATA Assumptions'!J7 -> 15281363 | M21: ='INPUT DATA Assumptions'!K5+'INPUT DATA Assumptions'!K6+'INPUT DATA Assumptions'!K7 -> 15477487 | N21: ='INPUT DATA Assumptions'!L5+'INPUT DATA Assumptions'!L6+'INPUT DATA Assumptions'!L7 -> 15678563 | O21: ='INPUT DATA Assumptions'!M5+'INPUT DATA Assumptions'!M6+'INPUT DATA Assumptions'!M7 -> 15884849
A22: REQUIRED TARIFF (Php/m3) | D22: =D19/D21 -> 21.938468 | E22: =E19/E21 -> 20.676557 | F22: =F19/F21 -> 21.058413 | G22: =G19/G21 -> 21.459499 | H22: =H19/H21 -> 21.880631 | K22: =K19/K21 -> 25.794746 | L22: =L19/L21 -> 26.250851 | M22: =M19/M21 -> 26.729209 | N22: =N19/N21 -> 27.230702 | O22: =O19/O21 -> 27.756239
D25: PROPOSED TARIFF | K25: PROPOSED TARIFF
A26: Proposed Tariff | D26: YEAR1 | E26: YEAR2 | F26: YEAR3 | G26: YEAR4 | H26: YEAR5 | I26: AVERAGE | K26: YEAR1 | L26: YEAR2 | M26: YEAR3 | N26: YEAR4 | O26: YEAR5 | P26: AVERAGE
A28: Minimuim Charge 0-10m3 | D28: =D19/D21 -> 21.938468 | E28: =E19/E21 -> 20.676557 | F28: =F19/F21 -> 21.058413 | G28: =G19/G21 -> 21.459499 | H28: =H19/H21 -> 21.880631 | I28: =SUM(D28:H28)/5*10 -> 214.02714 | K28: =K19/K21 -> 25.794746 | L28: =L19/L21 -> 26.250851 | M28: =M19/M21 -> 26.729209 | N28: =N19/N21 -> 27.230702 | O28: =O19/O21 -> 27.756239 | P28: =SUM(K28:O28)/5*10 -> 267.5235
A29: Commodity Charge 11-20 per m3 | D29: =D28*(1+$D$34) -> 23.035391 | E29: =E28*(1+$D$34) -> 21.710385 | F29: =F28*(1+$D$34) -> 22.111334 | G29: =G28*(1+$D$34) -> 22.532474 | H29: =H28*(1+$D$34) -> 22.974663 | I29: =SUM(D29:H29)/5 -> 22.472849 | K29: =K28*(1+$K$34) -> 27.084483 | L29: =L28*(1+$K$34) -> 27.563394 | M29: =M28*(1+$K$34) -> 28.065669 | N29: =N28*(1+$K$34) -> 28.592238 | O29: =O28*(1+$K$34) -> 29.144051 | P29: =SUM(K29:O29)/5 -> 28.089967
A30: 21-30 per m3 | D30: =D29*(1+$D$34) -> 24.187161 | E30: =E29*(1+$D$34) -> 22.795904 | F30: =F29*(1+$D$34) -> 23.2169 | G30: =G29*(1+$D$34) -> 23.659098 | H30: =H29*(1+$D$34) -> 24.123396 | I30: =SUM(D30:H30)/5 -> 23.596492 | K30: =K29*(1+$K$34) -> 28.438707 | L30: =L29*(1+$K$34) -> 28.941564 | M30: =M29*(1+$K$34) -> 29.468952 | N30: =N29*(1+$K$34) -> 30.021849 | O30: =O29*(1+$K$34) -> 30.601254 | P30: =SUM(K30:O30)/5 -> 29.494465
A31: 31-40 per m3 | D31: =D30*(1+$D$34) -> 25.396519 | E31: =E30*(1+$D$34) -> 23.935699 | F31: =F30*(1+$D$34) -> 24.377745 | G31: =G30*(1+$D$34) -> 24.842053 | H31: =H30*(1+$D$34) -> 25.329566 | I31: =SUM(D31:H31)/5 -> 24.776316 | K31: =K30*(1+$K$34) -> 29.860642 | L31: =L30*(1+$K$34) -> 30.388642 | M31: =M30*(1+$K$34) -> 30.9424 | N31: =N30*(1+$K$34) -> 31.522942 | O31: =O30*(1+$K$34) -> 32.131317 | P31: =SUM(K31:O31)/5 -> 30.969189
A32: 41-50 per m3 | D32: =D31*(1+$D$34) -> 26.666345 | E32: =E31*(1+$D$34) -> 25.132484 | F32: =F31*(1+$D$34) -> 25.596633 | G32: =G31*(1+$D$34) -> 26.084155 | H32: =H31*(1+$D$34) -> 26.596044 | I32: =SUM(D32:H32)/5 -> 26.015132 | K32: =K31*(1+$K$34) -> 31.353675 | L32: =L31*(1+$K$34) -> 31.908074 | M32: =M31*(1+$K$34) -> 32.48952 | N32: =N31*(1+$K$34) -> 33.099089 | O32: =O31*(1+$K$34) -> 33.737883 | P32: =SUM(K32:O32)/5 -> 32.517648
A33: 51-up per m3 | D33: =D32*(1+$D$34) -> 27.999662 | E33: =E32*(1+$D$34) -> 26.389108 | F33: =F32*(1+$D$34) -> 26.876464 | G33: =G32*(1+$D$34) -> 27.388363 | H33: =H32*(1+$D$34) -> 27.925846 | I33: =SUM(D33:H33)/5 -> 27.315889 | K33: =K32*(1+$K$34) -> 32.921358 | L33: =L32*(1+$K$34) -> 33.503478 | M33: =M32*(1+$K$34) -> 34.113996 | N33: =N32*(1+$K$34) -> 34.754044 | O33: =O32*(1+$K$34) -> 35.424777 | P33: =SUM(K33:O33)/5 -> 34.14353
A34: Increase per block | D34: 0.05 | E34: =D34 -> 0.05 | F34: =E34 -> 0.05 | G34: =F34 -> 0.05 | H34: =G34 -> 0.05 | K34: 0.05 | L34: 0.05 | M34: 0.05 | N34: 0.05 | O34: 0.05
D35: =D34/5 -> 0.01 | E35: =E34/5 -> 0.01 | F35: =F34/5 -> 0.01 | G35: =G34/5 -> 0.01 | H35: =H34/5 -> 0.01 | K35: =K34/5 -> 0.01 | L35: =L34/5 -> 0.01 | M35: =M34/5 -> 0.01 | N35: =N34/5 -> 0.01 | O35: =O34/5 -> 0.01

Sheet FORMULA
B4: BILLED VOLUME | D4: = | E4: Average Consumption * Active Service Connection * 12
B6: AVERAGE CONSUMPTION | D6: = | E6: Billed Volume / Active Service Connection / 12
B8: NON-REVENUE WATER | D8: = | E8: Production in m3 - Billed in m3 / Production m3
B10: AVERAGE TARIFF | D10: = | E10: Annual Revenue / Billed Volume m3
B12: UNIT PRODUCTION COST | D12: = | E12: Total Annual O&M / Production in m3
B14: OPERATING RATIO | D14: = | E14: Operating Expenses / Operating Revenue
B16: COLLECTION EFFICIENCY | D16: = | E16: Year-To-Date Collections / Year-To-Date Pesos Billings
