Workbook

Sheet Tagbilaran summary
B2: TAGBILARAN CITY | C2: Bohol Water Utilities, Inc. (BWUI) | D2: Richli Water | E2: Tagbilaran City Waterworks System (TCWS)
B3: Served municipalities | C3: Tagbilaran City, Baclayon, Corella, Dauis | D3: Tagbilaran City, Alburquerque, Baclayon, Corella, Cortes, Dauis, Loboc, Panglao, Sevilla, Sikatuna, Trinidad | E3: Tagbilaran City
B4: Served Barangays in Tagbilaran City | C4: 13 out of 15 (Bool, Booy, Cabawan, Cogon, Dampas, Dao, Mansasa, Poblacion I,II,III, San Isidro, Taloto, Tiptip) | D4: 15 out of 15 (Bool, Booy, Cabawan, Cogon, Dampas, Dao, Manga, Mansasa, Poblacion I,II,III, San Isidro, Taloto, Tiptip, Ubujan) | E4: 10 out of 15 (Bool, Booy, Cabawan, Cogon, Dao, Manga, San Isidro, Taloto, Tiptip, Ubujan)
B5: Total population served | C5: approx. 59,500 people | D5: no data provided | E5: approx. 27,000 people
B6: Billed volume (MLD) | C6: Jan to July 2025: 15.56 MLD | D6: no data provided | E6: Jan to June 2025: 5.26 MLD
B7: Production volume (MLD) | C7: Jan to July 2025: 17.33 MLD | D7: no data provided | E7: Jan to June 2025: 7.66 MLD
B8: NRW (%) | C8: 0.1 | D8: 0.068 | E8: 0.31
B9: Water availability (hours/day) | C9: 23 hours | D9: 24 hours | E9: 22 to 24 hours
B10: Water quality | C10: for deepwells: salt intrusion in wells near coastal areas, seasonal turbidity, some wells have iron and bacterial presence | D10: no data provided | E10: distribution side: good; no customer complaints
B11: Average pressure (psi) | C11: no data provided | D11: no data provided | E11: no data provided
B12: Water supply source | C12: deepwells | D12: surface water (5 MLD WTP in Loctob, Loboc; and 10 MLD WTP in Cortes) | E12: deepwells
B13: Water supply treatment | C13: chlorination | D13: filtration, chlorination | E13: chlorination
B15: Water Service Connections in Tagbilaran City | C15: as of July 2025 | D15: as of August 2025 | E15: as of June 2025
B16: Residential | C16: ~13,200 | D16: no data provided | E16: 6017
B17: Commercial | C17: ~1500 | D17: no data provided | E17: 34
B18: Institutional | C18: ~250 | D18: no data provided | E18: 33
B19: Industrial | C19: 0 | D19: no data provided | E19: 0
B20: Bulk | C20: 0 | D20: no data provided | E20: 0
B21: Total | C21: 15040 | D21: majority of their 15,000 WSC | E21: =SUM(E16:E20) -> 6084
B22: Average monthly consumption (cu.m/conn/month) | C22: 31.3 cum/conn/mo | D22: no data provided | E22: 26.1 cum/conn/mo
B24: Annual revenue (PhP) | E24: no data provided
B25: Annual water sales (PhP) | E25: 2024: PhP22,887,685.65 Jan-Jun 2025: PhP12,036,951.99
B26: Collection efficiency (%) | E26: no calculated data
B27: Annual Operating Expenses (PhP/year) | E27: no data provided
B28: Minimum Tariff (PhP/cum) | C28: residential and institutional: 0-5 cum: PhP 100.00 6-10 cum: PhP 20/cu.m commercial: 0-15 cum: PhP 1,107.00 | D28: residential and institutional: 0-5 cum: PhP 218.96 6-10 cum: PhP 43.79/cum commercial: 0-8 cum: PhP 792.00 | E28: residential and institutional: 0-10 cum: PhP 62.00 commercial: PhP 23/cu.m
B29: Average Tariff (PhP/cum)
B31: Demand gap:
C32: *estimated WSC per classification in Tagbilaran since no disaggregated data was provided, only total WSC for Tagbilaran customes | D32: *information was based on the discussion with Richli water during the due diligence in Aug 2025

Sheet Panglao summary
B2: PANGLAO | C2: Richli Water | D2: South Balibago Waterworks | E2: Mactan Rock Industries, Inc. | F2: Panglao Water Services Inc. | G2: Panglao Waterworks
B3: Served municipalities | C3: Tagbilaran City, Alburquerque, Baclayon, Corella, Cortes, Dauis, Loboc, Panglao, Sevilla, Sikatuna, Trinidad | D3: Dauis and Panglao | E3: Panglao | F3: Panglao | G3: Panglao
B4: Served barangays in Panglao | C4: 10 out of 10 (Bil-isan, Bolod, Danao, Doljo, Libaong, Looc, Lourdes, Poblacion, Tangnan, Tawala) | D4: 6 out of 10 (Bolod, Danao, Doljo, Libaong, Poblacion, Tawala) | E4: 2 out of 10 ( Danao and Tawala) | F4: 5 out of 10 ( Danao, Doljo, Looc, Poblacion, Tawala) | G4: 10 out of 10 (Bil-isan, Bolod, Danao, Doljo, Libaong, Looc, Lourdes, Poblacion, Tangnan, Tawala)
B5: Total population served | C5: no data provided | D5: approx. 650 people | E5: approx. 620 people | F5: no data provided | G5: approx.33,900 people
B6: Billed volume (MLD) | C6: no data provided | D6: 1.23 (as of Aug 2025) | E6: 0.88 (as of June 2025) | F6: 1.32 (as of July 2025) | G6: 4.19 (as of June 2025)
B7: Production volume (MLD) | C7: no data provided | D7: 1.45 (as of Aug 2025) | E7: 1.13 (as of June 2025) | F7: 1.79 (as of July 2025) | G7: 6.65
B8: NRW (%) | C8: 0.068 | D8: 0.152 | E8: 0.223 | F8: 0.264 | G8: 0.37
B9: Water availability (hours/day) | C9: 24 hours | D9: 20 to 24 hours | E9: 24 hours | F9: 24 hours | G9: 20 to 22 hours
B10: Water quality | C10: no data provided | D10: Deepwells: iron and manganese presence | E10: salinity in water source | F10: salinity in water source | G10: Deepwells: salt intrusion in one of the wells; some wells tested positive for coliform in the recent testing
B11: Average pressure (psi) | C11: no data provided | D11: no data provided | E11: no data provided | F11: no data provided | G11: no data provided
B12: Water supply source | C12: surface water (5 MLD WTP in Loctob, Loboc; and 10 MLD WTP in Cortes) | D12: deepwells | E12: deepwell | F12: deepwell | G12: deepwells
B13: Water supply treatment | C13: filtration, chlorination | D13: chlorination | E13: reverse osmosis (RO) | F13: reverse osmosis (RO) | G13: intermittent chlorination
B15: Water Service Connections | C15: as of August 2025 | D15: as of June 2025 | E15: as of June 2025 | F15: as of July 2025 | G15: as of June 2025
B16: Residential | C16: no data provided | D16: 141 | E16: 135 | F16: no data provided | G16: 7370 | H16: =F21*50% -> 394.5 | I16: =SUM(D16:E16,G16,H16) -> 8040.5
B17: Commercial | C17: no data provided | D17: 165 | E17: 18 | F17: no data provided | G17: 646 | I17: =SUM(D17:E17,G17,H16) -> 1223.5
B18: Institutional | C18: no data provided | D18: 0 | E18: 0 | F18: no data provided | G18: 0
B19: Industrial | C19: no data provided | D19: 0 | E19: 0 | F19: no data provided | G19: 0
B20: Bulk | C20: no data provided | D20: 0 | E20: 0 | F20: no data provided | G20: 0
B21: Total | C21: no data provided | D21: =SUM(D16:D20) -> 306 | E21: =SUM(E16:E20) -> 153 | F21: =calculations!N114 -> 789 | G21: =SUM(G16:G20) -> 8016
B22: Average monthly consumption (cu.m/month) | C22: no data provided | D22: 118.5 | E22: 122.3 | F22: 33.66 | G22: 15.8
B24: Annual revenue (PhP)
B25: Annual collection (PhP)
B26: Collection efficiency (%)
B27: Annual Operating Expenses (PhP/year)
B28: Minimum Tariff (PhP/cum) | C28: residential and institutional: 0-5 cum: PhP 218.96 6-10 cum: PhP 43.79/cum commercial: 0-8 cum: PhP 792.00 | D28: residential: 0-5 cum: PhP 219 6-10 cum: PhP 43.8/cum commercial: 0-15 cum: PhP 780 to 1,102.50 (depends on area/brgy) | E28: Residential: 0-5 cum: PhP 127.68 6-10 cum: PhP 27.68/cu.m Commercial: 0-10 cum: PhP 283.00 11 & above cum: PhP 31/cu.m Resorts: PhP 60/cum | F28: Across all classifications: 0-5 cum: PhP 135.00 6-10 cum: PhP 38/cum | G28: Residential: 0-5 cum: PhP 30.00 6-10 cum: PhP 39/cu.m Commercial: 0-5 cum: PhP 60.00 6-10 cum: PhP 78/cu.m
B29: Average Tariff (PhP/cum)
G33: Bil-isan
G34: Bolod
G35: Danao
G36: Doljo
G37: Libaong
G38: Looc
G39: Lourdes
G40: Poblacion
G41: Tangnan
G42: Tawala

Sheet Dauis summary
I1: NO DATA | J1: NO DATA
B2: DAUIS | C2: Dauis Waterworks | D2: South Balibago | E2: Richli | F2: Biking Waterworks System (BLGU-run) | G2: Brgy. Dao (BLGU-run) | H2: Brgy. San Isidro (BLGU-run) | I2: BLGU-run (Brgy. Tabalong) | J2: BLGU-run (Brgy. Bingag)
B3: Served municipalities | C3: Dauis | D3: Dauis | E3: Dauis | F3: Dauis | G3: Dauis | H3: Dauis | I3: Dauis | J3: Dauis
B4: Served Barangays in Dauis | C4: 7 out of 12 (Catarman, Mariveles, Mayacabac, Poblacion, Songculan, Tinago, Totolan) | D4: 3 out of 12 (Biking, Dao, San Isidro) | E4: 12 out of 12 | F4: 1 out of 12 (Biking) | G4: 1 out of 12 (Dao) | H4: 1 out of 12 (San Isidro) | I4: 1 out of 12 (Tabalong) | J4: 1 out of 12 (Bingag)
B5: Total population served | C5: approx. 18,000 people | D5: approx. 460 people | E5: no data provided | F5: approx. 4600 people | G5: approx. 2400 people (95% of popn) | H5: no data provided
B6: Billed volume (MLD) | C6: 2.01 (as of Aug 2025) | D6: 0.54 (as of June 2025) | E6: no data provided | F6: est. 0.25 (as of Oct 2025) | G6: no data provided | H6: est. 0.14 (as of Oct 2025)
B7: Production volume (MLD) | C7: own DW: 2.06 MLD BWUI bulk: 2.5 MLD | D7: 0.63 (as of June 2025) | E7: no data provided | F7: no data provided | G7: no data provided | H7: no data provided
B8: NRW (%) | C8: 0.56 | D8: 0.152 | E8: 0.068 | F8: no data provided | G8: no data provided | H8: no data provided
B9: Water availability (hours/day) | C9: 16 to 20 hours | D9: 20 to 24 hours | E9: 24 hours | F9: 6 hours | G9: 14 to 16 hours | H9: 8 hours
B10: Water quality | C10: Source: salt intrusion | D10: Deepwells: iron and manganese presence | E10: no data provided | F10: Deepwells: traces of coliform, salt intrusion | G10: traces of coliform, salinity, hardness | H10: quality testing results pass, but water is sometimes salty
B11: Average pressure (psi) | C11: no data provided | D11: no data provided | E11: no data provided | F11: no data provided | G11: no data provided | H11: no data provided
B12: Water supply source | C12: deepwells, bulk water from BWUI | D12: deepwells | E12: surface water (5 MLD WTP in Loctob, Loboc; and 10 MLD WTP in Cortes) | F12: deepwells | G12: deepwells | H12: deepwells
B13: Water supply treatment | C13: none for WW deepwells; BWUI bulk chlorinates | D13: chlorination | E13: filtration, chlorination | F13: no data provided | G13: no data provided | H13: no data provided
B15: Water Service Connections in Dauis | C15: note: billed WSC as of Aug 2025 | D15: as of June 2025 | E15: as of August 2025 | F15: as of Oct 2025 | G15: as of Oct 2025 | H15: as of Oct 2025
B16: Residential | C16: ='dauis data'!C81 -> 3908 | D16: 101 | E16: no data provided | F16: no data provided | G16: no data provided | H16: no data provided
B17: Commercial | C17: ='dauis data'!$D$81 -> 16 | D17: 36 | E17: no data provided | F17: no data provided | G17: no data provided | H17: no data provided
B18: Institutional | C18: ='dauis data'!$E$81 -> 34 | E18: no data provided | F18: no data provided | G18: no data provided | H18: no data provided
B19: Industrial | E19: no data provided | F19: no data provided | G19: no data provided | H19: no data provided
B20: Bulk | E20: no data provided | F20: no data provided | G20: no data provided | H20: no data provided
B21: Total | C21: =SUM(C16:C20) -> 3958 | D21: =SUM(D16:D20) -> 137 | E21: no data provided | F21: approx. 1,000 | G21: approx. 527 | H21: approx. 1,000
B22: Average monthly consumption (cu.m/conn/month) | C22: 15.7 | D22: 118.5 | E22: no data provided | F22: est. 7.6 | G22: no data provided | H22: no data provided
B24: Annual revenue (PhP)
B25: Annual water sales (PhP)
B26: Collection efficiency (%)
B27: Annual Operating Expenses (PhP/year)
B28: Minimum Tariff (PhP/cum) | C28: residential: 0-5 cum: PhP 16.00/cum 6-10 cum: PhP 17.00/cum commercial: 1-25 cum: PhP 30.00/cu.m | D28: residential: 0-5 cum: PhP 219 6-10 cum: PhP 43.8/cum commercial: 0-15 cum: PhP 780 to 1,102.50 (depends on area/brgy) | E28: residential and institutional: 0-5 cum: PhP 218.96 6-10 cum: PhP 43.79/cum commercial: 0-8 cum: PhP 792.00 | F28: residential: PhP 12/cu.m commercial: PhP 20/cu.m | G28: PhP 8/cu.m | H28: PhP 10/cum (member) PhP 13/cum (non-member)
B29: Average Tariff (PhP/cum)
B31: Demand gap:
C32: *BWUI bulk supply data based on BWUI's Jan to July 2025 provided data
C33: *note: actual consumption is estimated at 3.02 MLD (assuming July 2025 consumption data of Mariveles and Mayacabac)

Sheet Tagbilaran bgy details
C1: Tagbilaran City | D1: 4.5 | E1: HH size
C3: Barangay | D3: Total Population | E3: Projected HH | F3: Prevailing WSP in the barangay | G3: Barangay Presence | J3: Total WSC | M3: % of population served | Q3: Water Availability | T3: Water Quality (customer side)
D4: (based on projected 2024 pop'n) | E4: (HH size: 4.5) | G4: Waterworks | H4: BWUI | I4: Richli | J4: TCWS | K4: BWUI | L4: Richli | M4: TCWS | N4: BWUI | O4: Richli | Q4: Waterworks | R4: BWUI | S4: Richli | T4: Waterworks | U4: BWUI | V4: Richli
B5: 1 | C5: Bool | D5: 7441.2908 | E5: =D5/$D$1 -> 1653.6202 | F5: BWUI | G5: served | H5: served | I5: served | J5: =SUM(J28,M28,P28) -> 114 | K5: 1401 | L5: no data | M5: =J28/$E5 -> 0.068334919 | N5: =K28/$E5 -> 0.76898654 | O5: no data | Q5: 24
B6: 2 | C6: Booy | D6: 10697.993 | E6: =D6/$D$1 -> 2377.3317 | F6: BWUI | G6: served | H6: served | I6: served | J6: =SUM(J29,M29,P29) -> 264 | K6: 930 | L6: no data | M6: =J29/$E6 -> 0.11020759 | N6: =K29/$E6 -> 0.37007205 | O6: no data | Q6: 24
B7: 3 | C7: Cabawan | D7: 2325.604 | E7: =D7/$D$1 -> 516.8009 | F7: TCWS | G7: served | H7: served | I7: served | J7: =SUM(J30,M30,P30) -> 231 | K7: 7 | L7: no data | M7: =J30/$E7 -> 0.43924072 | N7: =K30/$E7 -> 0 | O7: no data | Q7: 22
B8: 4 | C8: Cogon | D8: 16983.438 | E8: =D8/$D$1 -> 3774.0973 | F8: BWUI | G8: served | H8: served | I8: served | J8: =SUM(J31,M31,P31) -> 21 | K8: 3385 | L8: no data | M8: =J31/$E8 -> 0.0055642445 | N8: =K31/$E8 -> 0.75224141 | O8: no data | Q8: 24
B9: 5 | C9: Dampas | D9: 9709.1025 | E9: =D9/$D$1 -> 2157.5783 | F9: BWUI | G9: unserved | H9: served | I9: served | J9: =SUM(J32,M32,P32) -> 0 | K9: 1994 | L9: no data | M9: =J32/$E9 -> 0 | N9: =K32/$E9 -> 0.81819325 | O9: no data
B10: 6 | C10: Dao | D10: 11446.082 | E10: =D10/$D$1 -> 2543.5737 | F10: BWUI | G10: served | H10: served | I10: served | J10: =SUM(J33,M33,P33) -> 903 | K10: 1626 | L10: no data | M10: =J33/$E10 -> 0.35226029 | N10: =K33/$E10 -> 0.59586406 | O10: no data | Q10: 24
B11: 7 | C11: Manga | D11: 8082.357 | E11: =D11/$D$1 -> 1796.0793 | F11: TCWS | G11: served | H11: unserved | I11: served | J11: =SUM(J34,M34,P34) -> 1333 | K11: 0 | L11: no data | M11: =J34/$E11 -> 0.73604767 | N11: =K34/$E11 -> 0 | O11: no data | Q11: 24
B12: 8 | C12: Mansasa | D12: 6981.093 | E12: =D12/$D$1 -> 1551.354 | F12: BWUI | G12: unserved | H12: served | I12: served | J12: =SUM(J35,M35,P35) -> 0 | K12: 1201 | L12: no data | M12: =J35/$E12 -> 0 | N12: =K35/$E12 -> 0.72827644 | O12: no data
B13: 9 | C13: Poblacion I | D13: 3131.4852 | E13: =D13/$D$1 -> 695.88561 | F13: BWUI | G13: unserved | H13: served | I13: served | J13: =SUM(J36,M36,P36) -> 0 | K13: 492 | L13: no data | M13: =J36/$E13 -> 0 | N13: =K36/$E13 -> 0.64286845 | O13: no data
B14: 10 | C14: Poblacion II | D14: 4643.7165 | E14: =D14/$D$1 -> 1031.937 | F14: BWUI | G14: unserved | H14: served | I14: served | J14: =SUM(J37,M37,P37) -> 0 | K14: 1253 | L14: no data | M14: =J37/$E14 -> 0 | N14: =K37/$E14 -> 0.87061027 | O14: no data
B15: 11 | C15: Poblacion III | D15: 5390.7352 | E15: =D15/$D$1 -> 1197.9411 | F15: BWUI | G15: unserved | H15: served | I15: served | J15: =SUM(J38,M38,P38) -> 0 | K15: 1134 | L15: no data | M15: =J38/$E15 -> 0 | N15: =K38/$E15 -> 0.80299261 | O15: no data
B16: 12 | C16: San Isidro | D16: 6810.9269 | E16: =D16/$D$1 -> 1513.5393 | F16: BWUI | G16: served | H16: served | I16: served | J16: =SUM(J39,M39,P39) -> 200 | K16: 1100 | L16: no data | M16: =J39/$E16 -> 0.12751568 | N16: =K39/$E16 -> 0.70332903 | O16: no data | Q16: 22
B17: 13 | C17: Taloto | D17: 6831.2612 | E17: =D17/$D$1 -> 1518.058 | F17: TCWS | G17: served | H17: served | I17: served | J17: =SUM(J40,M40,P40) -> 831 | K17: 446 | L17: no data | M17: =J40/$E17 -> 0.5401638 | N17: =K40/$E17 -> 0.25697393 | O17: no data | Q17: 24
B18: 14 | C18: Tiptip | D18: 5921.5679 | E18: =D18/$D$1 -> 1315.904 | F18: TCWS | G18: served | H18: served | I18: served | J18: =SUM(J41,M41,P41) -> 984 | K18: 71 | L18: no data | M18: =J41/$E18 -> 0.74169545 | N18: =K41/$E18 -> 0.052269201 | O18: no data | Q18: 24
B19: 15 | C19: Ubujan | D19: 5951.5343 | E19: =D19/$D$1 -> 1322.5632 | F19: TCWS | G19: served | H19: unserved | I19: served | J19: =SUM(J42,M42,P42) -> 1203 | K19: 0 | L19: no data | M19: =J42/$E19 -> 0.89749966 | N19: =K42/$E19 -> 0 | O19: no data | Q19: 24
C20: TOTAL | D20: =SUM(D5:D19) -> 112348.19 | E20: =SUM(E5:E19) -> 24966.264 | J20: =SUM(J5:J19) -> 6084 | K20: =SUM(K5:K19) -> 15040 | L20: =SUM(L5:L19) -> 0 | M20: =J43/$E20 -> 0.24100523 | N20: =K43/$E20 -> 0.5300071
C22: Remarks | H22: Brgys. Manga and Ubujan soon to be served | L22: no data provided on WSC per barangay and classification | N22: no breakdown per classification per brgy provided
C23: Reference | G23: based on data provided during Aug 25-29, 2025 DD | H23: based on interview and data provided during Aug 25-29, 2025 DD | I23: based on interview during Aug 25-29, 2025 DD | J23: based on data provided during Aug 25-29, 2025 DD | K23: based on interview and data provided during Aug 25-29, 2025 DD | L23: based on interview during Aug 25-29, 2025 DD | Q23: based on data provided during Aug 25-29, 2025 DD | R23: based on interview and data provided during Aug 25-29, 2025 DD | S23: based on interview during Aug 25-29, 2025 DD | T23: based on data provided during Aug 25-29, 2025 DD | U23: based on interview and data provided during Aug 25-29, 2025 DD | V23: based on interview during Aug 25-29, 2025 DD
J26: Residential WSC | M26: Commercial WSC | P26: Institutional WSC
C27: Barangay | I27: Barangay | J27: Waterworks | K27: BWUI | L27: Richli | M27: Waterworks | N27: BWUI | O27: Richli | P27: Waterworks | Q27: BWUI | R27: Richli
C28: Bool | H28: 1 | I28: Bool | J28: 113 | K28: =K5*K48 -> 1271.6117 | M28: 1 | N28: =K5*N48 -> 101.81378 | P28: 0 | Q28: =K5*Q48 -> 27.574565
C29: Booy | H29: 2 | I29: Booy | J29: 262 | K29: =K6*K49 -> 879.78402 | M29: 1 | N29: =K6*N49 -> 41.177106 | P29: 1 | Q29: =K6*Q49 -> 9.0388769
C30: Cabawan | H30: 3 | I30: Cabawan | J30: 227 | K30: =K7*K50 -> 0 | M30: 1 | N30: =K7*N50 -> 0 | P30: 3 | Q30: =K7*Q50 -> 7
C31: Cogon | H31: 4 | I31: Cogon | J31: 21 | K31: =K8*K51 -> 2839.0323 | M31: 0 | N31: =K8*N51 -> 499.88606 | P31: 0 | Q31: =K8*Q51 -> 46.081681
C32: Dampas | H32: 5 | I32: Dampas | K32: =K9*K52 -> 1765.316 | N32: =K9*N52 -> 196.60612 | Q32: =K9*Q52 -> 32.077841
C33: Dao | H33: 6 | I33: Dao | J33: 896 | K33: =K10*K53 -> 1515.6241 | M33: 4 | N33: =K10*N53 -> 90.957888 | P33: 3 | Q33: =K10*Q53 -> 19.417976
C34: Manga | H34: 7 | I34: Manga | J34: 1322 | K34: =K11*K54 -> 0 | M34: 8 | N34: =K11*N54 -> 0 | P34: 3 | Q34: =K11*Q54 -> 0
C35: Mansasa | H35: 8 | I35: Mansasa | K35: =K12*K55 -> 1129.8146 | N35: =K12*N55 -> 61.016088 | Q35: =K12*Q55 -> 10.169348
C36: Poblacion I | H36: 9 | I36: Poblacion I | K36: =K13*K56 -> 447.3629 | N36: =K13*N56 -> 36.701613 | Q36: =K13*Q56 -> 7.9354839
C37: Poblacion II | H37: 10 | I37: Poblacion II | K37: =K14*K57 -> 898.41494 | N37: =K14*N57 -> 313.74801 | Q37: =K14*Q57 -> 40.837043
C38: Poblacion III | H38: 11 | I38: Poblacion III | K38: =K15*K58 -> 961.93789 | N38: =K15*N58 -> 130.80745 | Q38: =K15*Q58 -> 41.254658
C39: San Isidro | H39: 12 | I39: San Isidro | J39: 193 | K39: =K16*K59 -> 1064.5161 | M39: 0 | N39: =K16*N59 -> 29.032258 | P39: 7 | Q39: =K16*Q59 -> 6.4516129
C40: Taloto | H40: 13 | I40: Taloto | J40: 820 | K40: =K17*K60 -> 390.10133 | M40: 8 | N40: =K17*N60 -> 42.816 | P40: 3 | Q40: =K17*Q60 -> 13.082667
C41: Tiptip | H41: 14 | I41: Tiptip | J41: 976 | K41: =K18*K61 -> 68.78125 | M41: 4 | N41: =K18*N61 -> 2.21875 | P41: 4 | Q41: =K18*Q61 -> 0
C42: Ubujan | H42: 15 | I42: Ubujan | J42: 1187 | K42: =K19*K62 -> 0 | M42: 7 | N42: =K19*N62 -> 0 | P42: 9 | Q42: =K19*Q62 -> 0
C43: TOTAL | I43: TOTAL | J43: =SUM(J28:J42) -> 6017 | K43: =SUM(K28:K42) -> 13232.297 | L43: =SUM(L28:L42) -> 0 | M43: =SUM(M28:M42) -> 34 | N43: =SUM(N28:N42) -> 1546.7811 | O43: =SUM(O28:O42) -> 0 | P43: =SUM(P28:P42) -> 33 | Q43: =SUM(Q28:Q42) -> 260.92175 | R43: =SUM(R28:R42) -> 0
C44: Remarks | I44: Remarks | L44: no data provided on WSC per barangay and classification | O44: no data provided on WSC per barangay and classification | R44: no data provided on WSC per barangay and classification
C45: Reference | I45: Reference
I47: assume rough ratio & proportion for BWUI | K47: res | N47: com | Q47: inst
I48: Bool | K48: 0.90764572 | N48: 0.072672218 | Q48: 0.019682059
I49: Booy | K49: 0.94600432 | N49: 0.044276458 | Q49: 0.0097192225
I50: Cabawan | K50: 0 | N50: 0 | Q50: 1
I51: Cogon | K51: 0.83870968 | N51: 0.14767683 | Q51: 0.013613495
I52: Dampas | K52: 0.88531396 | N52: 0.098598858 | Q52: 0.016087182
I53: Dao | K53: 0.93211816 | N53: 0.055939661 | Q53: 0.011942175
I54: Manga
I55: Mansasa | K55: 0.9407282 | N55: 0.050804403 | Q55: 0.0084674005
I56: Poblacion I | K56: 0.90927419 | N56: 0.074596774 | Q56: 0.016129032
I57: Poblacion II | K57: 0.71701113 | N57: 0.25039746 | Q57: 0.032591415
I58: Poblacion III | K58: 0.84826974 | N58: 0.11535049 | Q58: 0.036379769
I59: San Isidro | K59: 0.96774194 | N59: 0.026392962 | Q59: 0.0058651026
I60: Taloto | K60: 0.87466667 | N60: 0.096 | Q60: 0.029333333
I61: Tiptip | K61: 0.96875 | N61: 0.03125 | Q61: 0
I62: Ubujan
I63: TOTAL | K63: 0.87926921 | N63: 0.10375622 | Q63: 0.016974572

Sheet Panglao bgy details
C1: Panglao | D1: 4.6 | E1: HH size
C3: Barangay | D3: Total Population | E3: Projected HH | F3: Prevailing WSP in the brgy | G3: Barangay Presence | M3: Total WSC | R3: % of population served | X3: Water Availability | AC3: NRW (%) | AH3: Water Quality (customer side)
D4: (based on projected 2024 pop'n) | E4: (HH size: 4.6) | G4: Panglao Waterworks | H4: South Balibago | I4: Mactan Rock | J4: Panglao Water Services | K4: Richli | M4: Panglao Waterworks | N4: South Balibago | O4: Mactan Rock | P4: Panglao Water Services | Q4: Richli | R4: Panglao Waterworks | S4: South Balibago | T4: Mactan Rock | U4: Panglao Water Services | V4: Richli | X4: Waterworks | Y4: Balibago | Z4: Mactan Rock | AA4: Panglao Water Services | AB4: Richli | AC4: Waterworks | AD4: Balibago | AE4: Mactan Rock | AF4: Panglao Water Services | AG4: Richli | AH4: Waterworks | AI4: Balibago | AJ4: Mactan Rock | AK4: Panglao Water Services | AL4: Richli
B5: 1 | C5: Bil-isan | D5: 4268.0667 | E5: =D5/$D$1 -> 927.84058 | F5: Panglao Waterworks | G5: served | H5: unserved | I5: unserved | J5: unserved | K5: served | M5: =SUM(L23,S23) -> 477 | N5: =SUM(M23,T23) -> 0 | O5: =SUM(N23,U23) -> 0 | P5: no data | Q5: no data | R5: =L23/$E5 -> 0.49793037 | S5: =M23/$E5 -> 0 | T5: =N23/$E5 -> 0 | U5: no data | V5: no data
B6: 2 | C6: Bolod | D6: 2454.0313 | E6: =D6/$D$1 -> 533.48507 | F6: Panglao Waterworks | G6: served | H6: served | I6: unserved | J6: unserved | K6: served | M6: =SUM(L24,S24) -> 563 | N6: =SUM(M24,T24) -> 22 | O6: =SUM(N24,U24) -> 0 | P6: no data | Q6: no data | R6: =L24/$E6 -> 0.99534182 | S6: =M24/$E6 -> 0.014995734 | T6: =N24/$E6 -> 0 | U6: no data | V6: no data
B7: 3 | C7: Danao | D7: 6636.4798 | E7: =D7/$D$1 -> 1442.713 | F7: Panglao Waterworks | G7: served | H7: served | I7: served | J7: served | K7: served | M7: =SUM(L25,S25) -> 826 | N7: =SUM(M25,T25) -> 79 | O7: =SUM(N25,U25) -> 74 | P7: no data | Q7: no data | R7: =L25/$E7 -> 0.53718238 | S7: =M25/$E7 -> 0.027725542 | T7: =N25/$E7 -> 0.033963789 | U7: no data | V7: no data
B8: 4 | C8: Doljo | D8: 4398.6344 | E8: =D8/$D$1 -> 956.22487 | F8: Panglao Waterworks | G8: served | H8: served | I8: unserved | J8: served | K8: served | M8: =SUM(L26,S26) -> 785 | N8: =SUM(M26,T26) -> 5 | O8: =SUM(N26,U26) -> 0 | P8: no data | Q8: no data | R8: =L26/$E8 -> 0.77387654 | S8: =M26/$E8 -> 0.0041831165 | T8: =N26/$E8 -> 0 | U8: no data | V8: no data
B9: 5 | C9: Libaong | D9: 2771.8888 | E9: =D9/$D$1 -> 602.58453 | F9: Panglao Waterworks | G9: served | H9: served | I9: unserved | J9: unserved | K9: served | M9: =SUM(L27,S27) -> 616 | N9: =SUM(M27,T27) -> 46 | O9: =SUM(N27,U27) -> 0 | P9: no data | Q9: no data | R9: =L27/$E9 -> 0.9475849 | S9: =M27/$E9 -> 0.049785546 | T9: =N27/$E9 -> 0 | U9: no data | V9: no data
B10: 6 | C10: Looc | D10: 3330.5475 | E10: =D10/$D$1 -> 724.03207 | F10: Panglao Waterworks | G10: served | H10: unserved | I10: unserved | J10: served | K10: served | M10: =SUM(L28,S28) -> 404 | N10: =SUM(M28,T28) -> 0 | O10: =SUM(N28,U28) -> 0 | P10: no data | Q10: no data | R10: =L28/$E10 -> 0.51931401 | S10: =M28/$E10 -> 0 | T10: =N28/$E10 -> 0 | U10: no data | V10: no data
B11: 7 | C11: Lourdes | D11: 1916.7772 | E11: =D11/$D$1 -> 416.69069 | F11: Panglao Waterworks | G11: served | H11: unserved | I11: unserved | J11: unserved | K11: served | M11: =SUM(L29,S29) -> 963 | N11: =SUM(M29,T29) -> 0 | O11: =SUM(N29,U29) -> 0 | P11: no data | Q11: no data | R11: =L29/$E11 -> 2.0062843 | S11: =M29/$E11 -> 0 | T11: =N29/$E11 -> 0 | U11: no data | V11: no data
B12: 8 | C12: Poblacion | D12: 6479.1564 | E12: =D12/$D$1 -> 1408.5123 | F12: Panglao Waterworks | G12: served | H12: served | I12: unserved | J12: served | K12: served | M12: =SUM(L30,S30) -> 1524 | N12: =SUM(M30,T30) -> 4 | O12: =SUM(N30,U30) -> 0 | P12: no data | Q12: no data | R12: =L30/$E12 -> 0.984017 | S12: =M30/$E12 -> 0.0014199379 | T12: =N30/$E12 -> 0 | U12: no data | V12: no data
B13: 9 | C13: Tangnan | D13: 4323.7185 | E13: =D13/$D$1 -> 939.9388 | F13: Panglao Waterworks | G13: served | H13: unserved | I13: unserved | J13: unserved | K13: served | M13: =SUM(L31,S31) -> 1112 | N13: =SUM(M31,T31) -> 0 | O13: =SUM(N31,U31) -> 0 | P13: no data | Q13: no data | R13: =L31/$E13 -> 1.1404998 | S13: =M31/$E13 -> 0 | T13: =N31/$E13 -> 0 | U13: no data | V13: no data
B14: 10 | C14: Tawala | D14: 6057.4868 | E14: =D14/$D$1 -> 1316.845 | F14: Panglao Waterworks | G14: served | H14: served | I14: served | J14: served | K14: served | M14: =SUM(L32,S32) -> 746 | N14: =SUM(M32,T32) -> 150 | O14: =SUM(N32,U32) -> 142 | P14: no data | Q14: no data | R14: =L32/$E14 -> 0.47158171 | S14: =M32/$E14 -> 0.043285278 | T14: =N32/$E14 -> 0.065307612 | U14: no data | V14: no data
C15: TOTAL | D15: =SUM(D5:D14) -> 42636.787 | E15: =SUM(E5:E14) -> 9268.8668 | M15: =SUM(M5:M14) -> 8016 | N15: =SUM(N5:N14) -> 306 | O15: =SUM(O5:O14) -> 216 | P15: 789 | Q15: no data | R15: =L33/$E15 -> 0.79513495 | S15: =M33/$E15 -> 0.015212216 | T15: =N33/$E15 -> 0.014564887 | U15: =P15/E15 -> 0.085123674 | V15: no data | X15: 20-22 hours/day | Y15: 20-24 hours/day | Z15: 24 hours/day | AA15: no data | AB15: no data | AD15: 0.1491
C17: Remarks | H17: ~4% of pop'n served | L17: inconsistent sum in the forwarded data for WSC and BV | O17: no barangay and classification disaggregated WSC data | P17: no WSC data provided | AC17: as of July 2025
C18: Reference | G18: based on interview and data provided during Aug 25-29, 2025 DD | H18: based on interview and data provided during Aug 25-29, 2025 DD | I18: based on interview and data provided during Aug 25-29, 2025 DD | J18: based on interview during Aug 25-29, 2025 DD | K18: based on interview during Aug 25-29, 2025 DD | L18: based on data provided during Oct 21-24, 2025 validation | M18: based on data provided during Aug 25-29, 2025 DD | N18: based on data provided during Aug 25-29, 2025 DD | O18: total WSC based on data provided during Aug 25-29, 2025 DD
L20: Residential | R20: Commercial
L21: JAN-JUNE 2025 | M21: JAN-JUNE 2025 | N21: JAN-JUNE 2025 | O21: as of JULY 2025 | T21: JAN-JUNE 2025 | U21: JAN-JUNE 2025 | V21: as of JULY 2025
L22: Waterworks | M22: Balibago | N22: Mactan Rock | O22: Panglao Water Services | P22: Richli | S22: Waterworks | T22: Balibago | U22: Mactan Rock | V22: Panglao Water Services | W22: Richli
K23: Bil-isan | L23: 462 | M23: 0 | N23: 0 | O23: no data | P23: no data | R23: Bil-isan | S23: 15 | T23: 0 | U23: 0 | V23: no data | W23: no data
K24: Bolod | L24: 531 | M24: 8 | N24: 0 | O24: no data | P24: no data | R24: Bolod | S24: 32 | T24: 14 | U24: 0 | V24: no data | W24: no data
K25: Danao | L25: 775 | M25: 40 | N25: 49 | O25: no data | P25: no data | R25: Danao | S25: 51 | T25: 39 | U25: 25 | V25: no data | W25: no data
K26: Doljo | L26: 740 | M26: 4 | N26: 0 | O26: no data | P26: no data | R26: Doljo | S26: 45 | T26: 1 | U26: 0 | V26: no data | W26: no data
K27: Libaong | L27: 571 | M27: 30 | N27: 0 | O27: no data | P27: no data | R27: Libaong | S27: 45 | T27: 16 | U27: 0 | V27: no data | W27: no data
K28: Looc | L28: 376 | M28: 0 | N28: 0 | O28: no data | P28: no data | R28: Looc | S28: 28 | T28: 0 | U28: 0 | V28: no data | W28: no data
K29: Lourdes | L29: 836 | M29: 0 | N29: 0 | O29: no data | P29: no data | R29: Lourdes | S29: 127 | T29: 0 | U29: 0 | V29: no data | W29: no data
K30: Poblacion | L30: 1386 | M30: 2 | N30: 0 | O30: no data | P30: no data | R30: Poblacion | S30: 138 | T30: 2 | U30: 0 | V30: no data | W30: no data
K31: Tangnan | L31: 1072 | M31: 0 | N31: 0 | O31: no data | P31: no data | R31: Tangnan | S31: 40 | T31: 0 | U31: 0 | V31: no data | W31: no data
K32: Tawala | L32: 621 | M32: 57 | N32: 86 | O32: no data | P32: no data | R32: Tawala | S32: 125 | T32: 93 | U32: 56 | V32: no data | W32: no data
K33: TOTAL | L33: =SUM(L23:L32) -> 7370 | M33: =SUM(M23:M32) -> 141 | N33: =SUM(N23:N32) -> 135 | O33: no data | P33: no data | R33: TOTAL | S33: =SUM(S23:S32) -> 646 | T33: =SUM(T23:T32) -> 165 | U33: =SUM(U23:U32) -> 81 | V33: no data | W33: no data

Sheet Albur bgy details
C1: Alburquerque | D1: 4.3 | E1: HH size
C3: Barangay | D3: Total Population | E3: Projected HH | F3: Prevailing WSP in the brgy | G3: Barangay Presence | J3: Total WSC | M3: % of population served | Q3: Water Availability | T3: NRW (%) | W3: Water Quality (customer side)
D4: (based on projected 2024 pop'n) | E4: (HH size: 4.3 ) | G4: Alburquerque Waterworks | H4: Ponong Waterworks System Management Association, Inc. (BWSA) | I4: Upper Sta. Filomena Integrated Development Organization | J4: Alburquerque Waterworks | K4: Ponong Waterworks System Management Association, Inc. (BWSA) | L4: Upper Sta. Filomena Integrated Development Organization | M4: Alburquerque Waterworks | N4: Ponong Waterworks System Management Association, Inc. (BWSA) | O4: Upper Sta. Filomena Integrated Development Organization | Q4: Alburquerque Waterworks | R4: Ponong Waterworks System Management Association, Inc. (BWSA) | S4: Upper Sta. Filomena Integrated Development Organization | T4: Alburquerque Waterworks | U4: Ponong Waterworks System Management Association, Inc. (BWSA) | V4: Upper Sta. Filomena Integrated Development Organization | W4: Alburquerque Waterworks | X4: Ponong Waterworks System Management Association, Inc. (BWSA) | Y4: Upper Sta. Filomena Integrated Development Organization
B5: 1 | C5: Bahi | D5: 1122.6685 | E5: =D5/$D$1 -> 261.0857 | F5: Alburquerque Waterworks | G5: served | H5: unserved | I5: unserved | J5: =J24+O24+T24 -> 315 | K5: =K24+P24+U24 -> 0 | L5: =L24+Q24+V24 -> 0 | M5: =J24/$E5 -> 1.0839353 | N5: =K24/$E5 -> 0 | O5: =L24/$E5 -> 0 | Q5: 24
B6: 2 | C6: Basacdacu | D6: 909.69325 | E6: =D6/$D$1 -> 211.55657 | F6: Alburquerque Waterworks | G6: served | H6: unserved | I6: unserved | J6: =J25+O25+T25 -> 169 | K6: =K25+P25+U25 -> 0 | L6: =L25+Q25+V25 -> 0 | M6: =J25/$E6 -> 0.77520637 | N6: =K25/$E6 -> 0 | O6: =L25/$E6 -> 0 | Q6: 24
B7: 3 | C7: Cantiguib | D7: 646.41732 | E7: =D7/$D$1 -> 150.32961 | F7: Alburquerque Waterworks | G7: served | H7: unserved | I7: unserved | J7: =J26+O26+T26 -> 88 | K7: =K26+P26+U26 -> 0 | L7: =L26+Q26+V26 -> 0 | M7: =J26/$E7 -> 0.55877216 | N7: =K26/$E7 -> 0 | O7: =L26/$E7 -> 0 | Q7: 24 (lower); 12 (upper)
B8: 4 | C8: Dangay | D8: 850.83074 | E8: =D8/$D$1 -> 197.86761 | F8: Alburquerque Waterworks | G8: served | H8: unserved | I8: unserved | J8: =J27+O27+T27 -> 180 | K8: =K27+P27+U27 -> 0 | L8: =L27+Q27+V27 -> 0 | M8: =J27/$E8 -> 0.88948361 | N8: =K27/$E8 -> 0 | O8: =L27/$E8 -> 0 | Q8: 24
B9: 5 | C9: East Poblacion | D9: 2398.3795 | E9: =D9/$D$1 -> 557.76267 | F9: Alburquerque Waterworks | G9: served | H9: unserved | I9: unserved | J9: =J28+O28+T28 -> 554 | K9: =K28+P28+U28 -> 0 | L9: =L28+Q28+V28 -> 0 | M9: =J28/$E9 -> 0.89105999 | N9: =K28/$E9 -> 0 | O9: =L28/$E9 -> 0 | Q9: 24
B10: 6 | C10: Ponong | D10: 1351.6971 | E10: =D10/$D$1 -> 314.34817 | F10: BWSA | G10: unserved | H10: served | I10: unserved | J10: =J29+O29+T29 -> 0 | K10: =K29+P29+U29 -> 280 | L10: =L29+Q29+V29 -> 0 | M10: =J29/$E10 -> 0 | N10: =K29/$E10 -> 0.89073207 | O10: =L29/$E10 -> 0 | Q10: 24
B11: 7 | C11: San Agustin | D11: 651.76846 | E11: =D11/$D$1 -> 151.57406 | F11: Alburquerque Waterworks | G11: served | H11: unserved | I11: unserved | J11: =J30+O30+T30 -> 190 | K11: =K30+P30+U30 -> 0 | L11: =L30+Q30+V30 -> 0 | M11: =J30/$E11 -> 1.0951742 | N11: =K30/$E11 -> 0 | O11: =L30/$E11 -> 0 | Q11: 24
B12: 8 | C12: Santa Filomena | D12: 1030.6289 | E12: =D12/$D$1 -> 239.68115 | F12: Alburquerque Waterworks | G12: served | H12: unserved | I12: served | J12: =J31+O31+T31 -> 200 | K12: =K31+P31+U31 -> 0 | L12: =L31+Q31+V31 -> 134 | M12: =J31/$E12 -> 0.77603099 | N12: =K31/$E12 -> 0 | O12: =L31/$E12 -> 0.55907609 | Q12: 24
B13: 9 | C13: Tagbuane | D13: 993.17098 | E13: =D13/$D$1 -> 230.97 | F13: Alburquerque Waterworks | G13: served | H13: unserved | I13: unserved | J13: =J32+O32+T32 -> 207 | K13: =K32+P32+U32 -> 0 | L13: =L32+Q32+V32 -> 0 | M13: =J32/$E13 -> 0.86591334 | N13: =K32/$E13 -> 0 | O13: =L32/$E13 -> 0 | Q13: 24
B14: 10 | C14: Toril | D14: 873.30552 | E14: =D14/$D$1 -> 203.09431 | F14: Alburquerque Waterworks | G14: served | H14: unserved | I14: unserved | J14: =J33+O33+T33 -> 139 | K14: =K33+P33+U33 -> 0 | L14: =L33+Q33+V33 -> 0 | M14: =J34/$E14 -> 1.3442031 | N14: =K34/$E14 -> 0 | O14: =L34/$E14 -> 0 | Q14: 24
B15: 11 | C15: West Poblacion | D15: 1207.2165 | E15: =D15/$D$1 -> 280.74801 | F15: Alburquerque Waterworks | G15: served | H15: unserved | I15: unserved | J15: =J34+O34+T34 -> 330 | K15: =K34+P34+U34 -> 0 | L15: =L34+Q34+V34 -> 0 | M15: =J34/$E15 -> 0.97240225 | N15: =K34/$E15 -> 0 | O15: =L34/$E15 -> 0 | Q15: 24
C16: TOTAL | D16: =SUM(D5:D15) -> 12035.777 | E16: =SUM(E5:E15) -> 2799.0179 | J16: =SUM(J5:J15) -> 2372 | K16: =SUM(K5:K15) -> 280 | L16: =SUM(L5:L15) -> 134 | M16: =J35/$E16 -> 0.77277106 | N16: =K35/$E16 -> 0.10003509 | O16: =L35/$E16 -> 0.047873935
C18: Remarks
C19: Reference | G19: based on interview and data provided during Oct 21-24, 2025 DD | H19: based on interview and data provided during Oct 21-24, 2025 DD | I19: based on interview and data provided during Oct 21-24, 2025 DD | J19: based on interview and data provided during Oct 21-24, 2025 DD | K19: based on interview and data provided during Oct 21-24, 2025 DD | L19: based on interview and data provided during Oct 21-24, 2025 DD
J21: Residential | N21: Commercial | S21: Institutional
J22: as of Aug 2025 | N22: as of Aug 2025 | S22: as of Aug 2025
J23: Waterworks | K23: Ponong | L23: Sta Filomena | O23: Waterworks | P23: Ponong | Q23: Sta Filomena | T23: Waterworks | U23: Ponong | V23: Sta Filomena
I24: Bahi | J24: 283 | N24: Bahi | O24: 23 | S24: Bahi | T24: 9
I25: Basacdacu | J25: 164 | N25: Basacdacu | O25: 3 | S25: Basacdacu | T25: 2
I26: Cantiguib | J26: 84 | N26: Cantiguib | O26: 0 | S26: Cantiguib | T26: 4
I27: Dangay | J27: 176 | N27: Dangay | O27: 0 | S27: Dangay | T27: 4
I28: East Poblacion | J28: 497 | N28: East Poblacion | O28: 38 | S28: East Poblacion | T28: 19
I29: Ponong | K29: 280 | N29: Ponong | S29: Ponong
I30: San Agustin | J30: 166 | N30: San Agustin | O30: 15 | S30: San Agustin | T30: 9
I31: Santa Filomena | J31: 186 | L31: 134 | N31: Santa Filomena | O31: 9 | S31: Santa Filomena | T31: 5
I32: Tagbuane | J32: 200 | N32: Tagbuane | O32: 3 | S32: Tagbuane | T32: 4
I33: Toril | J33: 134 | N33: Toril | O33: 2 | S33: Toril | T33: 3
I34: West Poblacion | J34: 273 | N34: West Poblacion | O34: 54 | S34: West Poblacion | T34: 3
I35: TOTAL | J35: =SUM(J24:J34) -> 2163 | K35: =SUM(K24:K34) -> 280 | L35: =SUM(L24:L34) -> 134 | N35: TOTAL | O35: =SUM(O24:O34) -> 147 | P35: =SUM(P24:P34) -> 0 | Q35: =SUM(Q24:Q34) -> 0 | S35: TOTAL | T35: =SUM(T24:T34) -> 62 | U35: =SUM(U24:U34) -> 0 | V35: =SUM(V24:V34) -> 0

Sheet Albur summary
C1: =1.47-0.07-1.02 -> 0.38
B2: ALBURQUERQUE | C2: Alburquerque Waterworks | D2: Ponong Waterworks System Management Association, Inc. (BWSA) | E2: Upper Sta. Filomena Integrated Development Organization
B3: Served municipalities | C3: Alburquerque | D3: Alburquerque | E3: Alburquerque
B4: Served Barangays in Alburquerque | C4: 10 out of 11 (Bahi, Basacdacu, Cantiguib, Dangay, East Poblacion, San Agustin,Santa Filomena, Tagbuane, Toril, West Poblacion) | D4: Ponong | E4: Sta. Filomena (upper part)
B5: Total population served | C5: approx 9,300 people | D5: approx. 1,200 people | E5: approx 570 people
B6: Billed volume (MLD) | C6: 0.89 (as of Aug 2025) | D6: 0.02 (estimate based on collection) | E6: 0.05 (estimate based on collection)
B7: Production volume (MLD) | C7: 1.02
B8: NRW (%) | C8: =(C7-0.89)/C7 -> 0.12745098
B9: Water availability (hours/day) | C9: 24 | D9: every 4 days | E9: 9 hours/day
B10: Water quality | E10: okay; no water quality complaints and RHU testing results pass
B11: Average pressure (psi) | C11: no data provided | D11: no data provided | E11: no data provided
B12: Water supply source | C12: deepwells and spring | D12: deepwells | E12: spring
B13: Water supply treatment
B15: Water Service Connections in Alburquerque
B16: Residential | C16: ='Albur bgy details'!J35 -> 2163 | D16: no data provided | E16: no data provided
B17: Commercial | C17: ='Albur bgy details'!O35 -> 147 | D17: no data provided | E17: no data provided
B18: Institutional | C18: ='Albur bgy details'!T35 -> 62 | D18: no data provided | E18: no data provided
B19: Industrial | C19: 0 | D19: no data provided | E19: no data provided
B20: Bulk | C20: 0 | D20: no data provided | E20: no data provided
B21: Total | C21: =SUM(C16:C20) -> 2372 | D21: ='Albur bgy details'!K16 -> 280 | E21: 134
B22: Average monthly consumption (cu.m/conn/month) | C22: 11.4 | D22: 2.7 | E22: 12
B24: Annual revenue (PhP)
B25: Annual water sales (PhP)
B26: Collection efficiency (%)
B27: Annual Operating Expenses (PhP/year)
B28: Minimum Tariff (PhP/cum) | C28: Residential: 0-5 cum: PhP 100.00 6-10 cum: PhP 23.00/cu.m Commercial: 0-5 cum: PhP 130.00 6-10 cum: PhP 27.00/cu.m | D28: PhP 20.00 / cu.m | E28: PhP 10.00 / cu.m
B29: Average Tariff (PhP/cum)
B31: Demand gap:

Sheet Dauis bgy details
C1: Dauis | D1: 4.6 | E1: HH size
C3: Barangay | D3: Total Population | E3: Projected HH | F3: Prevailing WSP in the brgy | G3: Barangay Presence | P3: Total WSC | X3: % of population served | AG3: Water Availability | AN3: NRW (%) | AU3: Water Quality (customer side)
D4: (based on projected 2024 pop'n) | E4: (HH size: 4.6) | G4: Dauis Waterworks | H4: South Balibago | I4: Richli | J4: Biking Waterworks System (BLGU-run) | K4: Brgy. Dao (BLGU-run) | L4: Brgy. San Isidro (BLGU-run) | M4: BLGU-run (Brgy. Tabalong) | N4: BLGU-run (Brgy. Bingag) | P4: =G4 -> Dauis Waterworks | Q4: =H4 -> South Balibago | R4: =I4 -> Richli | S4: =J4 -> Biking Waterworks System (BLGU-run) | T4: =K4 -> Brgy. Dao (BLGU-run) | U4: =L4 -> Brgy. San Isidro (BLGU-run) | V4: =M4 -> BLGU-run (Brgy. Tabalong) | W4: =N4 -> BLGU-run (Brgy. Bingag) | X4: =P4 -> Dauis Waterworks | Y4: =Q4 -> South Balibago | Z4: =R4 -> Richli | AA4: =S4 -> Biking Waterworks System (BLGU-run) | AB4: =T4 -> Brgy. Dao (BLGU-run) | AC4: =U4 -> Brgy. San Isidro (BLGU-run) | AD4: =V4 -> BLGU-run (Brgy. Tabalong) | AE4: =W4 -> BLGU-run (Brgy. Bingag) | AG4: =X4 -> Dauis Waterworks | AH4: =Y4 -> South Balibago | AI4: =Z4 -> Richli | AJ4: =AA4 -> Biking Waterworks System (BLGU-run) | AK4: =AB4 -> Brgy. Dao (BLGU-run) | AL4: =AC4 -> Brgy. San Isidro (BLGU-run) | AM4: =AE4 -> BLGU-run (Brgy. Bingag) | AN4: =AG4 -> Dauis Waterworks | AO4: =AH4 -> South Balibago | AP4: =AI4 -> Richli | AQ4: =AJ4 -> Biking Waterworks System (BLGU-run) | AR4: =AK4 -> Brgy. Dao (BLGU-run) | AS4: =AL4 -> Brgy. San Isidro (BLGU-run) | AT4: =AM4 -> BLGU-run (Brgy. Bingag) | AU4: =AN4 -> Dauis Waterworks | ... BA4: =AT4 -> BLGU-run (Brgy. Bingag)
B5: 1 | C5: Biking | D5: 4141.7799 | E5: =D5/$D$1 -> 900.38692 | F5: Biking Waterworks System (BLGU-run) | G5: served | H5: served | I5: served | J5: served | Q5: =M25+V25+AD25 -> 81 | R5: no data | S5: =P25+X25+AF25 -> 1000 | T5: =Q25+Y25+AG25 -> 0 | U5: =R25+Z25+AH25 -> 0 | Y5: =M25/$E5 -> 0.077744354 | Z5: no data | AA5: =P25/$E5 -> 1.1106336
B6: 2 | C6: Bingag | D6: 5465.6511 | E6: =D6/$D$1 -> 1188.185 | F6: BLGU-run (Brgy. Bingag) | I6: served | N6: served | P6: =L26+U26+AC26 -> 0 | Q6: =M26+V26+AD26 -> 0 | R6: no data | S6: =P26+X26+AF26 -> 0 | T6: =Q26+Y26+AG26 -> 0 | U6: =R26+Z26+AH26 -> 0 | W6: no data | X6: =L26/$E6 -> 0 | Y6: =M26/$E6 -> 0 | Z6: no data | AE6: no data
B7: 3 | C7: Catarman | D7: 5490.2663 | E7: =D7/$D$1 -> 1193.5362 | F7: Dauis Waterworks | G7: served | I7: served | P7: =L27+U27+AC27 -> 1015 | Q7: =M27+V27+AD27 -> 0 | R7: no data | S7: =P27+X27+AF27 -> 0 | T7: =Q27+Y27+AG27 -> 0 | U7: =R27+Z27+AH27 -> 0 | X7: =L27/$E7 -> 0.84371135 | Y7: =M27/$E7 -> 0 | Z7: no data
B8: 4 | C8: Dao | D8: 2553.5625 | E8: =D8/$D$1 -> 555.12227 | F8: Brgy. Dao (BLGU-run) | H8: served | I8: served | K8: served | P8: =L28+U28+AC28 -> 0 | Q8: =M28+V28+AD28 -> 40 | R8: no data | S8: =P28+X28+AF28 -> 0 | T8: =Q28+Y28+AG28 -> 527 | U8: =R28+Z28+AH28 -> 0 | X8: =L28/$E8 -> 0 | Y8: =M28/$E8 -> 0.045035123 | Z8: no data | AB8: =Q28/$E8 -> 0.9493404
B9: 5 | C9: Mariveles | D9: 4063.6533 | E9: =D9/$D$1 -> 883.40288 | F9: Dauis Waterworks | G9: served | I9: served | P9: =L29+U29+AC29 -> 1486 | Q9: =M29+V29+AD29 -> 0 | R9: no data | S9: =P29+X29+AF29 -> 0 | T9: =Q29+Y29+AG29 -> 0 | U9: =R29+Z29+AH29 -> 0 | X9: =L29/$E9 -> 1.6708118 | Y9: =M29/$E9 -> 0 | Z9: no data
B10: 6 | C10: Mayacabac | D10: 5202.3752 | E10: =D10/$D$1 -> 1130.9511 | F10: Dauis Waterworks | G10: served | I10: served | P10: =L30+U30+AC30 -> 957 | Q10: =M30+V30+AD30 -> 0 | R10: no data | S10: =P30+X30+AF30 -> 0 | T10: =Q30+Y30+AG30 -> 0 | U10: =R30+Z30+AH30 -> 0 | X10: =L30/$E10 -> 0.84619042 | Y10: =M30/$E10 -> 0 | Z10: no data
B11: 7 | C11: Poblacion | D11: 3184.9966 | E11: =D11/$D$1 -> 692.39056 | F11: Dauis Waterworks | G11: served | I11: served | P11: =L31+U31+AC31 -> 639 | Q11: =M31+V31+AD31 -> 0 | R11: no data | S11: =P31+X31+AF31 -> 0 | T11: =Q31+Y31+AG31 -> 0 | U11: =R31+Z31+AH31 -> 0 | X11: =L31/$E11 -> 0.89255982 | Y11: =M33/$E11 -> 0 | Z11: no data
B12: 8 | C12: San Isidro (Canlongon) | D12: 1926.4092 | E12: =D12/$D$1 -> 418.78462 | F12: Brgy. San Isidro (BLGU-run) | H12: served | I12: served | L12: served | P12: =L32+U32+AC32 -> 0 | Q12: =M32+V32+AD32 -> 16 | R12: no data | S12: =P32+X32+AF32 -> 0 | T12: =Q32+Y32+AG32 -> 0 | U12: =R32+Z32+AH32 -> 1000 | X12: =L32/$E12 -> 0 | Y12: =M34/$E12 -> 0 | Z12: no data | AC12: =R32/$E12 -> 2.3878623
B13: 9 | C13: Songculan | D13: 5487.0556 | E13: =D13/$D$1 -> 1192.8382 | F13: Dauis Waterworks | G13: served | I13: served | P13: =L33+U33+AC33 -> 762 | Q13: =M33+V33+AD33 -> 0 | R13: no data | S13: =P33+X33+AF33 -> 0 | T13: =Q33+Y33+AG33 -> 0 | U13: =R33+Z33+AH33 -> 0 | X13: =L33/$E13 -> 0.63713588 | Y13: =M35/$E13 -> 0 | Z13: no data
B14: 10 | C14: Tabalong | D14: 6637.55 | E14: =D14/$D$1 -> 1442.9457 | F14: BLGU-run (Brgy. Tabalong) | I14: served | M14: served | P14: =L34+U34+AC34 -> 0 | Q14: =M34+V34+AD34 -> 0 | R14: no data | S14: =P34+X34+AF34 -> 0 | T14: =Q34+Y34+AG34 -> 0 | U14: =R34+Z34+AH34 -> 0 | V14: no data | X14: =L34/$E14 -> 0 | Y14: =M34/$E14 -> 0 | Z14: no data
B15: 11 | C15: Tinago | D15: 3558.5059 | E15: =D15/$D$1 -> 773.58825 | F15: Dauis Waterworks | G15: served | I15: served | P15: =L35+U35+AC35 -> 1020 | Q15: =M35+V35+AD35 -> 0 | R15: no data | S15: =P35+X35+AF35 -> 0 | T15: =Q35+Y35+AG35 -> 0 | U15: =R35+Z35+AH35 -> 0 | X15: =L35/$E15 -> 1.3056041 | Y15: =M35/$E15 -> 0 | Z15: no data | AD15: no data
B16: 12 | C16: Totolan | D16: 8466.5686 | E16: =D16/$D$1 -> 1840.5584 | F16: Dauis Waterworks | G16: served | I16: served | P16: =L36+U36+AC36 -> 522 | Q16: =M36+V36+AD36 -> 0 | R16: no data | S16: =P36+X36+AF36 -> 0 | T16: =Q36+Y36+AG36 -> 0 | U16: =R36+Z36+AH36 -> 0 | X16: =L36/$E16 -> 0.27871976 | Y16: =M36/$E16 -> 0 | Z16: no data
C17: TOTAL | D17: =SUM(D5:D16) -> 56178.374 | E17: =SUM(E5:E16) -> 12212.69 | P17: =SUM(P5:P16) -> 6401 | Q17: =SUM(Q5:Q16) -> 137 | R17: no data | S17: =SUM(S5:S16) -> 1000 | T17: =SUM(T5:T16) -> 527 | U17: =SUM(U5:U16) -> 1000 | V17: no data | W17: no data | X17: =L37/$E17 -> 0.51921403 | Y17: =M37/$E17 -> 0.0082700863 | Z17: no data | AA17: =P37/$E17 -> 0.081882042 | AB17: =Q37/$E17 -> 0.043151836 | AC17: =R37/$E17 -> 0.081882042 | AD17: no data | AE17: no data
C19: Remarks
C20: Reference
L22: Residential | U22: Commercial | AD22: Institutional
L23: as of Aug 2025 | M23: as of June 2025
L24: Dauis Waterworks | M24: South Balibago | N24: Richli | P24: Biking Waterworks System (BLGU-run) | Q24: Brgy. Dao (BLGU-run) | R24: Brgy. San Isidro (BLGU-run) | U24: =L24 -> Dauis Waterworks | V24: =M24 -> South Balibago | W24: =N24 -> Richli | X24: =P24 -> Biking Waterworks System (BLGU-run) | Y24: =Q24 -> Brgy. Dao (BLGU-run) | Z24: =R24 -> Brgy. San Isidro (BLGU-run) | AC24: =L24 -> Dauis Waterworks | AD24: =M24 -> South Balibago | AE24: =N24 -> Richli | AF24: =P24 -> Biking Waterworks System (BLGU-run) | AG24: =Q24 -> Brgy. Dao (BLGU-run) | AH24: =R24 -> Brgy. San Isidro (BLGU-run)
K25: Biking | M25: 70 | N25: no data | P25: 1000 | T25: =K25 -> Biking | V25: 11 | AB25: =T25 -> Biking
K26: Bingag | N26: no data | T26: =K26 -> Bingag | AB26: =T26 -> Bingag
K27: Catarman | L27: 1007 | N27: no data | T27: =K27 -> Catarman | U27: 3 | AB27: =T27 -> Catarman | AC27: 5
K28: Dao | M28: 25 | N28: no data | Q28: 527 | T28: =K28 -> Dao | V28: 15 | AB28: =T28 -> Dao
K29: Mariveles | L29: 1476 | N29: no data | T29: =K29 -> Mariveles | U29: 5 | AB29: =T29 -> Mariveles | AC29: 5
K30: Mayacabac | L30: 957 | N30: no data | T30: =K30 -> Mayacabac | AB30: =T30 -> Mayacabac
K31: Poblacion+Union | L31: =341+277 -> 618 | N31: no data | T31: =K31 -> Poblacion+Union | U31: =2+4 -> 6 | AB31: =T31 -> Poblacion+Union | AC31: =7+8 -> 15
K32: San Isidro (Canlongon) | M32: 6 | N32: no data | R32: 1000 | T32: =K32 -> San Isidro (Canlongon) | V32: 10 | AB32: =T32 -> San Isidro (Canlongon)
K33: Songculan | L33: 760 | N33: no data | T33: =K33 -> Songculan | U33: 0 | AB33: =T33 -> Songculan | AC33: 2
K34: Tabalong | N34: no data | T34: =K34 -> Tabalong | AB34: =T34 -> Tabalong
K35: Tinago | L35: 1010 | N35: no data | T35: =K35 -> Tinago | U35: 3 | AB35: =T35 -> Tinago | AC35: 7
K36: Totolan | L36: 513 | N36: no data | T36: =K36 -> Totolan | U36: 4 | AB36: =T36 -> Totolan | AC36: 5
K37: TOTAL | L37: =SUM(L25:L36) -> 6341 | M37: =SUM(M25:M36) -> 101 | N37: no data | P37: =SUM(P25:P36) -> 1000 | Q37: =SUM(Q25:Q36) -> 527 | R37: =SUM(R25:R36) -> 1000 | T37: TOTAL | U37: =SUM(U25:U36) -> 21 | V37: =SUM(V25:V36) -> 36 | W37: =SUM(W25:W36) -> 0 | X37: =SUM(X25:X36) -> 0 | Y37: =SUM(Y25:Y36) -> 0 | Z37: =SUM(Z25:Z36) -> 0 | AB37: TOTAL | AC37: =SUM(AC25:AC36) -> 39 | AD37: =SUM(AD25:AD36) -> 0 | AE37: =SUM(AE25:AE36) -> 0 | AF37: =SUM(AF25:AF36) -> 0 | AG37: =SUM(AG25:AG36) -> 0 | AH37: =SUM(AH25:AH36) -> 0
L40: assumed based on July 2025 BV data
L41: assumed based on Dec 2023 WSC

Sheet calculations
B2: TAGBILARAN WATERWORKS | M2: PANGLAO WATERWORKS | V2: ALBURQUERQUE WATERWORKS | AD2: DAUIS WATERWORKS
C4: Jan-June 2025 (cum) | D4: MLD | E4: no of days | F4: remarks | N4: 2024 | O4: MLD | P4: no of days | Q4: remarks | W4: 2024 | X4: MLD | Y4: no of days | Z4: remarks
B5: BV | C5: 952194 | D5: =C5/E5/1000 -> 5.2607403 | E5: =31+28+31+30+31+30 -> 181 | F5: MLD calculated based on actual provided data | L5: chris: | M5: BV | N5: 1393427 | O5: =N5/P5/1000 -> 3.8071776 | P5: 366 | Q5: MLD calculated based on actual provided data | V5: BV | W5: 323566 | X5: =W5/Y5/1000 -> 0.88406011 | Y5: 366 | Z5: MLD calculated based on actual provided data | AD5: BASED ON ACTUAL READ ACCTS | AE5: August 2025 (cum) | AF5: MLD | AG5: no of days | AH5: remarks
B6: Prodn | C6: 1385950 | D6: =C6/E6/1000 -> 7.6571823 | E6: =31+28+31+30+31+30 -> 181 | F6: MLD calculated based on actual provided data | L6: 6645 cum/day | M6: Prodn | N6: =6645.83*P6 -> 2432373.8 | O6: =N6/P6/1000 -> 6.64583 | P6: 366 | Q6: pump flow rate in cum/hr x run time x estimated pump efficiency | V6: Prodn | W6: =1023.89*Y6 -> 374743.74 | X6: =W6/Y6/1000 -> 1.02389 | Y6: 366 | Z6: pump flow rate in cum/hr x run time x estimated pump efficiency (based on Chris' calcu) | AD6: BV | AE6: ='dauis data'!F102 -> 62240 | AF6: =AE6/1000/31 -> 2.0077419 | AG6: 31 | AH6: MLD calculated based on actual provided data
B7: % NRW | D7: =(D6-D5)/D6 -> 0.31296656 | F7: calculated based on actual data | M7: % NRW | O7: =(O6-O5)/O6 -> 0.42713286 | Q7: calculated based on actual data | V7: % NRW | X7: =(X6-X5)/X6 -> 0.1365673 | Z7: calculated based on actual data | AD7: Prodn - WW wells (cum/day) | AE7: 2062.54 | AF7: =AE7/1000 -> 2.06254 | AG7: 31 | AH7: for wells:pump flow rate in cum/hr x run time x estimated pump efficiency
B8: WSC | C8: 6084 | M8: WSC | N8: 7781 | O8: (active wsc 2024) | V8: WSC | W8: 2310 | X8: active wsc 2024 | AD8: Prodn - BWUI bulk | AF8: 2.5 | AH8: from BWUI data
B9: avecons (cum/conn/mo) | D9: =C5/6/C8 -> 26.084648 | E9: cum/conn/mo | M9: avecons (cum/conn/mo) | O9: =N5/12/N8 -> 14.923392 | P9: cum/conn/mo | V9: avecons (cum/conn/mo) | X9: =W5/12/W8 -> 11.672655 | Y9: cum/conn/mo | AD9: % NRW | AF9: =(AF7+AF8-AF6)/(AF7+AF8) -> 0.55995083 | AH9: calculated based on actual data
AD10: WSC | AE10: ='dauis data'!F81 -> 3958
C11: 2024 | D11: MLD | E11: remarks | N11: Jan-June 2025 (cum) | O11: MLD | P11: no of days | Q11: remarks | W11: Jan-Aug 2025 (cum) | X11: MLD | Y11: no of days | Z11: remarks | AD11: avecons (cum/conn/mo) | AF11: =AE6/AE10 -> 15.725114 | AG11: cum/conn/mo
B12: BV | C12: 1883134 | D12: =C12/366/1000 -> 5.1451749 | E12: MLD calculated based on actual provided data | L12: chris: | M12: BV | N12: =SUM(N29:O29) -> 757963 | O12: =N12/P12/1000 -> 4.1876409 | P12: =31+28+31+30+31+30 -> 181 | Q12: MLD calculated based on actual provided data | V12: BV | W12: 215234 | X12: =W12/Y12/1000 -> 0.88573663 | Y12: =31+28+31+30+31+30+31+31 -> 243 | Z12: MLD calculated based on actual provided data
B13: Prodn | C13: 3049028 | D13: =C13/366/1000 -> 8.3306776 | E13: MLD calculated based on actual provided data | L13: 6645 cum/day | M13: Prodn | N13: =6645.83*P13 -> 1202895.2 | O13: =N13/P13/1000 -> 6.64583 | P13: =31+28+31+30+31+30 -> 181 | Q13: pump flow rate in cum/hr x run time x estimated pump efficiency | V13: Prodn | W13: =1023.89*Y13 -> 248805.27 | X13: =W13/Y13/1000 -> 1.02389 | Y13: =31+28+31+30+31+30+31+31 -> 243 | Z13: pump flow rate in cum/hr x run time x estimated pump efficiency (based on Chris' calcu) | AD13: IF WITH ASSUMED CONSUMPTIONS FOR MARIVELES and MAYACABAC) | AE13: August 2025 (cum) | AF13: MLD | AG13: no of days | AH13: remarks
D14: =(D13-D12)/D13 -> 0.38238219 | E14: calculated based on actual data | M14: % NRW | O14: =(O13-O12)/O13 -> 0.36988444 | Q14: calculated based on actual data | V14: % NRW | X14: =(X13-X12)/X13 -> 0.1349299 | Z14: calculated based on actual data | AD14: Consumption data | AE14: ='dauis data'!F108 -> 93598 | AF14: =AE14/1000/31 -> 3.0192903 | AG14: 31 | AH14: MLD calculated based on actual provided data
B15: WSC | C15: 6461 | M15: WSC | N15: =SUM(Q29:R29) -> 8016 | V15: WSC | W15: 2366 | X15: wsc aug 2025 | AD15: Prodn - WW wells (cum/day) | AE15: =AE7 -> 2062.54 | AF15: =AE15/1000 -> 2.06254 | AG15: 31 | AH15: for wells:pump flow rate in cum/hr x run time x estimated pump efficiency
B16: avecons (cum/conn/mo) | D16: =C12/12/C15 -> 24.288474 | E16: cum/conn/mo | M16: avecons (cum/conn/mo) | O16: =N12/6/N15 -> 15.759377 | P16: cum/conn/mo | V16: avecons (cum/conn/mo) | X16: =W12/8/W15 -> 11.371196 | Y16: cum/conn/mo | AD16: Prodn - BWUI bulk | AF16: 2.5 | AH16: from BWUI data
AD17: % NRW | AF17: =(AF15+AF16-AF14)/(AF15+AF16) -> 0.33824354 | AH17: calculated based on actual data
C18: 2023 | D18: MLD | E18: remarks | N18: 2025 BV res | O18: 2025 BV com | Q18: 2025 WSC res | R18: 2025 WSC com | AD18: WSC | AE18: ='dauis data'!F84 -> 6401.4574
B19: BV | C19: 1897357 | D19: =C19/365/1000 -> 5.1982384 | E19: MLD calculated based on actual provided data | M19: TANGNAN | N19: 119153 | O19: 12264 | Q19: 1072 | R19: 40 | V19: Brgy. Ponong | AD19: avecons (cum/conn/mo) | AF19: =AE14/AE18 -> 14.621358 | AG19: cum/conn/mo
B20: Prodn | C20: 3535036 | D20: =C20/365/1000 -> 9.6850301 | E20: MLD calculated based on actual provided data | M20: BIL-ISAN | N20: 48277 | O20: 2216 | Q20: 462 | R20: 15 | V20: BV calculation:
D21: =(D20-D19)/D20 -> 0.46327081 | E21: calculated based on actual data | M21: LOOC | N21: 28460 | O21: 1970 | Q21: 376 | R21: 28 | V21: Rate | W21: 20 | X21: per cum
M22: DOLJO | N22: 54480 | O22: 5178 | Q22: 740 | R22: 45 | V22: Monthly coll | W22: 15000 | X22: php per month
M23: POBLACION | N23: 98889 | O23: 12945 | Q23: 1386 | R23: 138 | V23: BV cum | W23: =W22/W21 -> 750
B24: BWUI | M24: LOURDES | N24: 108060 | O24: 32456 | Q24: 836 | R24: 127
B25: for whole BWUI service area: | M25: LIBAONG | N25: 57617 | O25: 8277 | Q25: 571 | R25: 45 | X25: MLD | Y25: no of days | Z25: remarks
C26: Jan-July 2025 (cum) | D26: MLD | E26: no of days | F26: remarks | M26: BOLOD | N26: 60540 | O26: 4826 | Q26: 531 | R26: 32 | V26: BV | W26: =W23 -> 750 | X26: =W26/Y26/1000 -> 0.024671053 | Y26: 30.4 | Z26: MLD calculated based on actual provided data
B27: BV | C27: 3875844 | D27: =C27/E27/1000 -> 18.282283 | E27: 212 | F27: based on actual data | M27: TAWALA | N27: 33016 | O27: 3997 | Q27: 621 | R27: 125 | V27: WSC | W27: 280 | Z27: based on KII
B28: Prodn | C28: 4317599 | D28: =C28/E28/1000 -> 20.366033 | E28: 212 | F28: based on actual data | M28: DANAO | N28: 61247 | O28: 4095 | Q28: 775 | R28: 51 | V28: avecons (cum/conn/mo) | X28: =W26/W27 -> 2.6785714 | Y28: cum/conn/mo
B29: % NRW | D29: =(D28-D27)/D28 -> 0.10231497 | F29: calculated | N29: =SUM(N19:N28) -> 669739 | O29: =SUM(O19:O28) -> 88224 | Q29: =SUM(Q19:Q28) -> 7370 | R29: =SUM(R19:R28) -> 646
V30: Brgy. Sta Filomena
C31: 2024 | D31: MLD | E31: remarks | V31: BV calculation:
B32: BV | C32: 6541668 | D32: =C32/E32/1000 -> 17.87341 | E32: 366 | F32: based on actual data | M32: South Balibago | V32: Rate | W32: 10 | X32: per cum
B33: Prodn | C33: 7442969 | D33: =C33/E33/1000 -> 20.335981 | E33: 366 | F33: based on actual data | M33: TOTAL | V33: Monthly coll | W33: 23000 | X33: php per month
D34: =(D33-D32)/D33 -> 0.12109428 | F34: calculated | N34: Jan-June 2025 (cum) | O34: MLD | P34: no of days | Q34: remarks | V34: Coll due to maintenance fee | W34: =50*W39 -> 6700
M35: BV | N35: 320592 | O35: =N35/P35/1000 -> 1.7712265 | P35: =31+28+31+30+31+30 -> 181 | Q35: MLD calculated based on actual provided data | V35: Coll due to consumption | W35: =W33-W34 -> 16300
B36: calculation for tagbilaran only: | M36: Prodn | N36: 378091 | O36: =N36/P36/1000 -> 2.0889006 | P36: =31+28+31+30+31+30 -> 181 | Q36: MLD calculated based on actual provided data | V36: BV cum | W36: =W35/W32 -> 1630
C37: Jan-July 2025 (cum) | D37: MLD | E37: no of days | F37: remarks | M37: % NRW | O37: =(O36-O35)/O36 -> 0.15207715 | Q37: calculated based on actual data | X37: MLD | Y37: no of days | Z37: remarks
B38: BV | C38: 3298398 | D38: =C38/E38/1000 -> 15.558481 | E38: 212 | F38: based on actual data | M38: WSC | N38: =AD100 -> 451 | V38: BV | W38: =W36 -> 1630 | X38: =W38/Y38/1000 -> 0.053618421 | Y38: 30.4 | Z38: MLD calculated based on actual provided data
B39: Prodn | C39: =C38/(1-D40) -> 3674337.7 | D39: =C39/E39/1000 -> 17.331782 | E39: 212 | F39: calculated using overall % NRW | M39: avecons (cum/conn/mo) | O39: =N35/6/N38 -> 118.4745 | P39: cum/conn/mo | V39: WSC | W39: 134 | Z39: based on KII
B40: % NRW | D40: =D29 -> 0.10231497 | F40: assumed overall % NRW | V40: avecons (cum/conn/mo) | X40: =W38/W39 -> 12.164179 | Y40: cum/conn/mo
B41: WSC | C41: 15040 | N41: 2024 | O41: MLD | P41: no of days | Q41: remarks
B42: avecons (cum/conn/mo) | D42: =C38/7/C41 -> 31.329768 | E42: cum/conn/mo | M42: BV | N42: 632351 | O42: =N42/P42/1000 -> 1.727735 | P42: 366 | Q42: MLD calculated based on actual provided data
M43: Prodn | N43: 794487 | O43: =N43/P43/1000 -> 2.1707295 | P43: 366 | Q43: MLD calculated based on actual provided data
M44: % NRW | O44: =(O43-O42)/O43 -> 0.20407634 | Q44: calculated based on actual data
C45: 2024 | D45: MLD | E45: remarks | M45: WSC | N45: =AD104 -> 456 | O45: (active wsc 2024)
B46: BV | C46: 5575065 | D46: =C46/E46/1000 -> 15.232418 | E46: 366 | F46: based on actual data | M46: avecons (cum/conn/mo) | O46: =N42/12/N45 -> 115.56122 | P46: cum/conn/mo
B47: Prodn | C47: =C46/(1-D48) -> 6343188.9 | D47: =C47/E47/1000 -> 17.331117 | E47: 366 | F47: calculated using overall % NRW
D48: =D34 -> 0.12109428 | F48: assumed overall % NRW | M48: PANGLAO
N49: Jan-June 2025 (cum) | O49: MLD | P49: no of days | Q49: remarks
B50: calculation for dauis bulk: | M50: BV | N50: =R76 -> 223205.96 | O50: =N50/P50/1000 -> 1.2331821 | P50: =31+28+31+30+31+30 -> 181 | Q50: MLD calculated based on actual provided data
C51: Jan-July 2025 (cum) | D51: MLD | E51: no of days | M51: Prodn | N51: =N50/(1-O37) -> 263238.52 | O51: =N51/P51/1000 -> 1.4543565 | P51: =31+28+31+30+31+30 -> 181 | Q51: MLD calculated based on actual provided data
B52: BV | C52: 475417 | D52: =C52/E52/1000 -> 2.242533 | E52: 212 | F52: based on actual data | M52: % NRW | O52: =(O51-O50)/O51 -> 0.15207715 | Q52: calculated based on actual data
B53: Prodn | C53: =C52/(1-D54) -> 529603.35 | D53: =C53/E53/1000 -> 2.498129 | E53: 212 | F53: calculated using overall % NRW | M53: WSC | N53: =Q76 -> 314
B54: % NRW | D54: =D40 -> 0.10231497 | F54: assumed overall % NRW | M54: avecons (cum/conn/mo) | O54: =N50/6/N53 -> 118.4745 | P54: cum/conn/mo
C56: 2024 | D56: MLD | E56: remarks | N56: 2024 | O56: MLD | P56: no of days | Q56: remarks
B57: BV | C57: 803743 | D57: =C57/E57/1000 -> 2.1960191 | E57: 366 | F57: based on actual data | M57: BV | N57: =R92 -> 445141.82 | O57: =N57/P57/1000 -> 1.2162345 | P57: 366 | Q57: MLD calculated based on actual provided data
B58: Prodn | C58: =C57/(1-D59) -> 914481.48 | D58: =C58/E58/1000 -> 2.4985833 | E58: 366 | F58: calculated using overall % NRW | M58: Prodn | N58: =N57/(1-O44) -> 559277.03 | O58: =N58/P58/1000 -> 1.5280793 | P58: 366 | Q58: MLD calculated based on actual provided data
D59: =D48 -> 0.12109428 | F59: assumed overall % NRW | M59: % NRW | O59: =(O58-O57)/O58 -> 0.20407634 | Q59: calculated based on actual data
M60: WSC | N60: =Q92 -> 321 | O60: (active wsc 2024)
M61: avecons (cum/conn/mo) | O61: =N57/12/N60 -> 115.56122 | P61: cum/conn/mo
N64: 2025
N65: Brgy | O65: Res | P65: Comm | Q65: total | R65: BV
N66: Bil-isan
N67: Bolod | O67: 8 | P67: 14 | Q67: =SUM(O67:P67) -> 22
N68: Danao | O68: 40 | P68: 39 | Q68: =SUM(O68:P68) -> 79
N69: Doljo | O69: 4 | P69: 1 | Q69: =SUM(O69:P69) -> 5
N70: Libaong | O70: 38 | P70: 16 | Q70: =SUM(O70:P70) -> 54 | AD70: South Balibago
N71: Looc | AD71: DAUIS
N72: Lourdes | AE72: Jan-June 2025 (cum) | AF72: MLD | AG72: no of days | AH72: remarks
N73: Poblacion | O73: 2 | P73: 2 | Q73: =SUM(O73:P73) -> 4 | AD73: BV | AE73: =AI90 -> 97386.04 | AF73: =AE73/AG73/1000 -> 0.53804442 | AG73: =31+28+31+30+31+30 -> 181 | AH73: MLD calculated based on actual provided data
N74: Tangnan | AD74: Prodn | AE74: =AE73/(1-AF75) -> 114852.48 | AF74: =AE74/AG74/1000 -> 0.63454407 | AG74: =31+28+31+30+31+30 -> 181 | AH74: MLD calculated based on actual provided data
N75: Tawala | O75: 57 | P75: 93 | Q75: =SUM(O75:P75) -> 150 | AD75: % NRW | AF75: =O52 -> 0.15207715 | AH75: calculated based on actual data
N76: TOTAL | O76: =SUM(O66:O75) -> 149 | P76: =SUM(P66:P75) -> 165 | Q76: =SUM(O76:P76) -> 314 | R76: =Q76*O39*6 -> 223205.96 | AD76: WSC | AE76: =AH90 -> 137
AD77: avecons (cum/conn/mo) | AF77: =O54 -> 118.4745 | AG77: cum/conn/mo
AE79: 2024 | AF79: MLD | AG79: no of days | AH79: remarks
N80: 2024 | AD80: BV | AE80: =AI96 -> 187209.18 | AF80: =AE80/AG80/1000 -> 0.51150049 | AG80: 366 | AH80: MLD calculated based on actual provided data
N81: Brgy | O81: Res | P81: Comm | Q81: total | AD81: Prodn | AE81: =AE80/(1-AF82) -> 235209.97 | AF81: =AE81/AG81/1000 -> 0.64265018 | AG81: 366 | AH81: MLD calculated based on actual provided data
N82: Bil-isan | AD82: % NRW | AF82: =O44 -> 0.20407634 | AH82: calculated based on actual data
N83: Bolod | O83: 7 | P83: 14 | Q83: =SUM(O83:P83) -> 21 | AD83: WSC | AE83: =AH115 -> based on KII | AF83: (active wsc 2024)
N84: Danao | O84: 45 | P84: 39 | Q84: =SUM(O84:P84) -> 84 | AD84: avecons (cum/conn/mo) | AF84: =O46 -> 115.56122 | AG84: cum/conn/mo
N85: Doljo | O85: 7 | P85: 5 | Q85: =SUM(O85:P85) -> 12
N86: Libaong | O86: 31 | P86: 12 | Q86: =SUM(O86:P86) -> 43 | AE86: 2025 WSC | AF86: Res | AG86: Comm | AH86: TOTAL | AI86: BV
N87: Looc | AE87: Biking | AF87: 70 | AG87: 11 | AH87: =SUM(AF87:AG87) -> 81
N88: Lourdes | AE88: San Isidro | AF88: 6 | AG88: 10 | AH88: =SUM(AF88:AG88) -> 16
N89: Poblacion | O89: 2 | P89: 2 | Q89: =SUM(O89:P89) -> 4 | AE89: Dao | AF89: 25 | AG89: 15 | AH89: =SUM(AF89:AG89) -> 40
N90: Tangnan | AE90: TOTAL | AF90: =SUM(AF87:AF89) -> 101 | AG90: =SUM(AG87:AG89) -> 36 | AH90: =SUM(AF90:AG90) -> 137 | AI90: =AH90*AF77*6 -> 97386.04
N91: Tawala | O91: 61 | P91: 96 | Q91: =SUM(O91:P91) -> 157
N92: TOTAL | O92: =SUM(O82:O91) -> 153 | P92: =SUM(P82:P91) -> 168 | Q92: =SUM(O92:P92) -> 321 | R92: =Q92*O46*12 -> 445141.82 | AE92: 2024 WSC | AF92: Res | AG92: Comm | AH92: TOTAL
AE93: Biking | AF93: 70 | AG93: 11 | AH93: =SUM(AF93:AG93) -> 81
M94: Mactan Rock | AE94: San Isidro | AF94: 5 | AG94: 10 | AH94: =SUM(AF94:AG94) -> 15
L95: =N96/6 -> 26416.5 | N95: Jan-June 2025 (cum) | O95: MLD | P95: no of days | Q95: remarks | AE95: Dao | AF95: 26 | AG95: 13 | AH95: =SUM(AF95:AG95) -> 39
L96: =N97/6 -> 34000 | M96: BV | N96: =127270+31229 -> 158499 | O96: =N96/P96/1000 -> 0.87568508 | P96: =31+28+31+30+31+30 -> 181 | Q96: MLD calculated based on actual provided data | AE96: TOTAL | AF96: =SUM(AF93:AF95) -> 101 | AG96: =SUM(AG93:AG95) -> 34 | AH96: =SUM(AF96:AG96) -> 135 | AI96: =AH96*AF84*12 -> 187209.18
M97: Prodn | N97: =34000*6 -> 204000 | O97: =N97/P97/1000 -> 1.1270718 | P97: =31+28+31+30+31+30 -> 181 | Q97: monthly prodn:34000 cum/mo
M98: % NRW | O98: =(O97-O96)/O97 -> 0.22304412 | Q98: calculated based on actual data | AD98: check:
M99: WSC | N99: =86+56+49+25 -> 216 | AD99: =AE73+N50 -> 320592 | AE99: total BV | AF99: =AD99-N35 -> 0
M100: avecons (cum/conn/mo) | O100: =N96/6/N99 -> 122.29861 | P100: cum/conn/mo | AD100: =AE76+N53 -> 451 | AE100: total wsc 2025
AD101: =AF90+O76 -> 250 | AE101: total res wsc
L102: =N103/12 -> 25246 | N102: 2024 | O102: MLD | P102: no of days | Q102: remarks | AD102: =AG90+P76 -> 201 | AE102: total comm wsc
L103: =N104/12 -> 34000 | M103: BV | N103: =54630+248322 -> 302952 | O103: =N103/P103/1000 -> 0.8277377 | P103: 366 | Q103: MLD calculated based on actual provided data
M104: Prodn | N104: =34000*12 -> 408000 | O104: =N104/P104/1000 -> 1.1147541 | P104: 366 | Q104: monthly prodn:34000 cum/mo | AD104: =AH96+Q92 -> 456 | AE104: total wsc 2024
M105: % NRW | O105: =(O104-O103)/O104 -> 0.25747059 | Q105: calculated based on actual data provided
M106: WSC | N106: =80+50+40+15 -> 185
...

Sheet dauis data
B3: TOTAL WSC | C3: Dec | D3: Dec | E3: Aug | G3: WSC and BV to use
B4: Barangay | C4: 2023 | D4: 2024 | E4: 2025 | G4: 2025 | H4: remarks
B5: Biking | C5: 84 | G5: =C5 -> 84 | H5: as of Dec 2023
B6: Bingag
B7: Catarman | C7: 1196 | E7: 1258 | G7: =E7 -> 1258 | H7: as of Aug 2025
B8: Dao
B9: Mariveles | C9: 1122 | D9: 1172 | G9: =E9 -> 0 | H9: as of July 2025 | I9: with actual BV, WSC calculated using historical avecons
B10: Mayacabac | C10: 957 | G10: =C10 -> 957 | H10: as of Dec 2023
B11: Poblacion | C11: 417 | D11: 423 | E11: 427 | G11: =E11 -> 427 | H11: as of Aug 2025
B12: San Isidro (Canlongon)
B13: Songculan | C13: 1123 | D13: 1138 | E13: 1164 | G13: =E13 -> 1164 | H13: as of Aug 2025
B14: Tabalong
B15: Tinago | C15: 1083 | D15: 1147 | E15: 1183 | G15: =E15 -> 1183 | H15: as of Aug 2025
B16: Totolan | C16: 1313 | E16: 1341 | G16: =E16 -> 1341 | H16: as of Aug 2025
B17: Union | C17: 366 | E17: 389 | G17: =E17 -> 389 | H17: as of Aug 2025
B18: NHA | E18: 223 | G18: =E18 -> 223 | H18: as of Aug 2025
C20: =SUM(C5:C18) -> 7661 | D20: =SUM(D5:D18) -> 3880 | E20: =SUM(E5:E18) -> 5985 | G20: =SUM(G5:G18) -> 7026
B23: TOTAL BV (cum) | C23: Dec | D23: Dec | E23: Aug | G23: BV to use
B24: Barangay | C24: 2023 | D24: 2024 | E24: 2025 | G24: 2025 | H24: remarks
B25: Biking | C25: 14 | G25: =C25 -> 14 | H25: as of Dec 2023
B26: Bingag
B27: Catarman | C27: 6534 | E27: 6752 | G27: =E27 -> 6752 | H27: as of Aug 2025
B28: Dao
B29: Mariveles | C29: 11563 | D29: 13119 | G29: =E29 -> 0 | H29: as of July 2025
B30: Mayacabac | C30: 14289 | G30: =C30 -> 14289 | H30: as of Dec 2023
B31: Poblacion | C31: 6350 | D31: 15394 | E31: 7221 | G31: =E31 -> 7221 | H31: as of Aug 2025
B32: San Isidro (Canlongon)
B33: Songculan | C33: 7439 | D33: 3644 | E33: 5961 | G33: =E33 -> 5961 | H33: as of Aug 2025
B34: Tabalong
B35: Tinago | C35: 21517 | D35: 12426 | E35: =30833 -> 30833 | G35: =E35 -> 30833 | H35: as of Aug 2025
B36: Totolan | C36: 3762 | E36: 4686 | G36: =E36 -> 4686 | H36: as of Aug 2025
B37: Union | C37: 5663 | E37: 6787 | G37: =E37 -> 6787 | H37: as of Aug 2025
B38: NHA | E38: 562 | G38: =E38 -> 562 | H38: as of Aug 2025
C40: =SUM(C25:C38) -> 77131 | D40: =SUM(D25:D38) -> 44583 | E40: =SUM(E25:E38) -> 62802 | G40: =SUM(G25:G38) -> 77105
B41: in MLD | C41: =C40/1000/31 -> 2.4880968 | D41: =D40/1000/31 -> 1.4381613 | E41: =E40/1000/31 -> 2.025871 | G41: =G40/1000/31 -> 2.4872581
B42: annual cum | C42: =C40*12 -> 925572 | D42: =D40*12 -> 534996 | E42: =E40*12 -> 753624 | G42: =G40*12 -> 925260
C44: =C40/C20 -> 10.068007 | D44: =D40/D20 -> 11.490464 | E44: =E40/E20 -> 10.493233 | G44: =G40/G20 -> 10.974239
C45: avecons Dec 2023 | D45: avecons Dec 2024 | E45: avecon Aug 2025 | G45: avecons reconstructed data
B47: avecons per brgy | C47: Dec | D47: Dec | E47: Aug | G47: BV to use
B48: Barangay | C48: 2023 | D48: 2024 | E48: 2025 | G48: 2025
B49: Biking | C49: =C25/C5 -> 0.16666667 | D49: =D25/D5 -> #DIV/0! | E49: =E25/E5 -> #DIV/0! | G49: =G25/G5 -> 0.16666667 | H49: as of Dec 2023
B50: Bingag | C50: =C26/C6 -> #DIV/0! | D50: =D26/D6 -> #DIV/0! | E50: =E26/E6 -> #DIV/0! | G50: =G26/G6 -> #DIV/0!
B51: Catarman | C51: =C27/C7 -> 5.4632107 | D51: =D27/D7 -> #DIV/0! | E51: =E27/E7 -> 5.3672496 | G51: =G27/G7 -> 5.3672496 | H51: as of Aug 2025
B52: Dao | C52: =C28/C8 -> #DIV/0! | D52: =D28/D8 -> #DIV/0! | E52: =E28/E8 -> #DIV/0! | G52: =G28/G8 -> #DIV/0!
B53: Mariveles | C53: =C29/C9 -> 10.305704 | D53: =D29/D9 -> 11.193686 | E53: =E29/E9 -> #DIV/0! | G53: =G29/G9 -> #DIV/0! | H53: as of Dec 2024
B54: Mayacabac | C54: =C30/C10 -> 14.931034 | D54: =D30/D10 -> #DIV/0! | E54: =E30/E10 -> #DIV/0! | G54: =G30/G10 -> 14.931034 | H54: as of Dec 2023
B55: Poblacion | C55: =C31/C11 -> 15.227818 | D55: =D31/D11 -> 36.392435 | E55: =E31/E11 -> 16.911007 | G55: =G31/G11 -> 16.911007 | H55: as of Aug 2025
B56: San Isidro (Canlongon) | C56: =C32/C12 -> #DIV/0! | D56: =D32/D12 -> #DIV/0! | E56: =E32/E12 -> #DIV/0! | G56: =G32/G12 -> #DIV/0!
B57: Songculan | C57: =C33/C13 -> 6.6242208 | D57: =D33/D13 -> 3.202109 | E57: =E33/E13 -> 5.121134 | G57: =G33/G13 -> 5.121134 | H57: as of Aug 2025
B58: Tabalong | C58: =C34/C14 -> #DIV/0! | D58: =D34/D14 -> #DIV/0! | E58: =E34/E14 -> #DIV/0! | G58: =G34/G14 -> #DIV/0!
B59: Tinago | C59: =C35/C15 -> 19.867959 | D59: =D35/D15 -> 10.833479 | E59: =E35/E15 -> 26.063398 | G59: =G35/G15 -> 26.063398 | H59: as of Aug 2025
B60: Totolan | C60: =C36/C16 -> 2.8651942 | D60: =D36/D16 -> #DIV/0! | E60: =E36/E16 -> 3.4944072 | G60: =G36/G16 -> 3.4944072 | H60: as of Aug 2025
B61: Union | C61: =C37/C17 -> 15.472678 | D61: =D37/D17 -> #DIV/0! | E61: =E37/E17 -> 17.447301 | G61: =G37/G17 -> 17.447301 | H61: as of Aug 2025
B62: NHA | C62: =C38/C18 -> #DIV/0! | D62: =D38/D18 -> #DIV/0! | E62: =E38/E18 -> 2.5201794 | G62: =G38/G18 -> 2.5201794 | H62: as of Aug 2025
B65: 2025 WSC per classification
B66: Barangay | C66: Res | D66: Comm | E66: Inst | F66: Total
B67: Biking | G67: no reading
B68: Bingag
B69: Catarman | C69: 1007 | D69: =3 -> 3 | E69: =5 -> 5 | F69: =SUM(C69:E69) -> 1015
B70: Dao
B71: Mariveles | C71: =C92/D53 -> 1476.4574 | D71: 5 | E71: 5 | F71: =SUM(C71:E71) -> 1486.4574 | G71: no reading Aug 2025; July 2025 data used; res WSC calculated using Dec 2024 Mariveles avecons
B72: Mayacabac | C72: =C10 -> 957 | F72: =SUM(C72:E72) -> 957 | G72: no reading; assumed Dec 2023 WSC data
B73: Poblacion | C73: 341 | D73: 2 | E73: 7 | F73: =SUM(C73:E73) -> 350
B74: San Isidro (Canlongon)
B75: Songculan | C75: 760 | D75: 0 | E75: 2 | F75: =SUM(C75:E75) -> 762
B76: Tabalong
B77: Tinago | C77: 1010 | D77: 3 | E77: 7 | F77: =SUM(C77:E77) -> 1020
B78: Totolan | C78: 513 | D78: 4 | E78: 5 | F78: =SUM(C78:E78) -> 522
B79: Union | C79: 277 | D79: 4 | E79: 8 | F79: =SUM(C79:E79) -> 289
B80: NHA | H80: =C81/F81 -> 0.98736736 | I80: % res
B81: TOTAL actual Aug | C81: =SUM(C69,C73,C75,C77,C78,C79) -> 3908 | D81: =SUM(D69,D73,D75,D77,D78,D79) -> 16 | E81: =SUM(E69,E73,E75,E77,E78,E79) -> 34 | F81: =SUM(F69,F73,F75,F77,F78,F79) -> 3958 | H81: =D81/F81 -> 0.0040424457 | I81: %com
H82: =E81/F81 -> 0.0085901971 | I82: %i inst
B83: TOTAL with July data (Mariveles) | C83: =C81+C71 -> 5384.4574 | D83: =D81+D71 -> 21 | E83: =E81+E71 -> 39 | F83: =F81+F71 -> 5444.4574
B84: Total with Dec 2023 data (Mayacabac) | C84: =SUM(C83,C72,C67) -> 6341.4574 | D84: =SUM(D83,D72,D67) -> 21 | E84: =SUM(E83,E72,E67) -> 39 | F84: =SUM(F83,F72,F67) -> 6401.4574
B86: 2025 BV per classification
B87: Barangay | C87: Res | D87: Comm | E87: Inst | F87: Total
B88: Biking | F88: =SUM(C88:E88) -> 0 | G88: no reading
B89: Bingag
B90: Catarman | C90: 6657 | D90: 43 | E90: 52 | F90: =SUM(C90:E90) -> 6752
B91: Dao
B92: Mariveles | C92: 16527 | D92: 233 | E92: 309 | F92: =SUM(C92:E92) -> 17069 | G92: no reading Aug 2025; July 2025 data used
B93: Mayacabac | C93: =C30 -> 14289 | F93: =SUM(C93:E93) -> 14289 | G93: no reading; assumed Dec 2023 WSC data
B94: Poblacion | C94: 6819 | D94: 115 | E94: 287 | F94: =SUM(C94:E94) -> 7221
B95: San Isidro (Canlongon)
B96: Songculan | C96: 5932 | D96: 0 | E96: 29 | F96: =SUM(C96:E96) -> 5961
B97: Tabalong
B98: Tinago | C98: 30264 | D98: 224 | E98: 345 | F98: =SUM(C98:E98) -> 30833
B99: Totolan | C99: 4174 | D99: 272 | E99: 240 | F99: =SUM(C99:E99) -> 4686
B100: Union | C100: 5876 | D100: 128 | E100: 783 | F100: =SUM(C100:E100) -> 6787
B101: NHA
B102: TOTAL cum (Actual Aug 2025) | C102: =SUM(C90,C94,C96,C98,C99,C100) -> 59722 | D102: =SUM(D90,D94,D96,D98,D99,D100) -> 782 | E102: =SUM(E90,E94,E96,E98,E99,E100) -> 1736 | F102: =SUM(F90,F94,F96,F98,F99,F100) -> 62240
B103: in MLD | C103: =C102/1000/31 -> 1.9265161 | D103: =D102/1000/31 -> 0.025225806 | E103: =E102/1000/31 -> 0.056 | F103: =F102/1000/31 -> 2.0077419
B105: TOTAL with July data (Mariveles) | C105: =C102+C92 -> 76249 | D105: =D102+D92 -> 1015 | E105: =E102+E92 -> 2045 | F105: =F102+F92 -> 79309
B106: in MLD | C106: =(C102/1000/31) -> 1.9265161 | D106: =D105/1000/31 -> 0.032741935 | E106: =E105/1000/31 -> 0.065967742 | F106: =F105/1000/31 -> 2.5583548
B108: Total with Dec 2023 data (Mayacabac) | C108: =C105+C93+C88 -> 90538 | D108: =D105+D93+D88 -> 1015 | E108: =E105+E93+E88 -> 2045 | F108: =F105+F93+F88 -> 93598
B109: in MLD | C109: =(C105/1000/31) -> 2.4596452 | D109: =D108/1000/31 -> 0.032741935 | E109: =E108/1000/31 -> 0.065967742 | F109: =F108/1000/31 -> 3.0192903
B112: avecons per brgy
B113: Barangay | C113: Res | D113: Comm | E113: Inst | F113: Total
B114: Biking
B115: Bingag
...
